Workbook

Sheet Active Employees
A1: Last name, First name | B1: Work Email | C1: Hire Date | D1: Job Information: Date | E1: Division | F1: Department | G1: Job Title | H1: Reporting to | I1: Team | J1: Sub Team
A2: Abaidoo, Larissa | B2: larissa.abaidoo@docker.com | C2: 45426 | D2: 45888 | E2: Products | F2: PROD-Accounts & Billing | G2: Staff Product Manager | H2: Dave Morris | I2: Billing
A3: Abishai, Esther | B3: esther.abishai@docker.com | C3: 45272 | D3: 45870 | E3: Sales | F3: SLS-Solutions Engineering | G3: Sr Solutions Engineer, Enterprise | H3: Kevin Barfield | I3: SE
A4: Adcock, Nicholas | B4: nick.adcock@docker.com | C4: 43529 | D4: 45870 | E4: Engineering | F4: ENG-AI Cloud | G4: Sr Software Engineer | H4: Marko Papic | I4: Build Cloud
A5: Agodjro, Innell | B5: innell.agodjro@docker.com | C5: 45790 | D5: 45839 | E5: General & Administrative | F5: GA-People | G5: Sr People Partner | H5: Linda Tan
A6: Agrawal, Pooja | B6: pooja.agrawal@docker.com | C6: 45496 | D6: 45496 | E6: General & Administrative | F6: GA-Finance | G6: Sr Manager, FP&A | H6: Joe Becic
A7: Ahmed, Suhaib | B7: suhaib.ahmed@docker.com | C7: 45265 | D7: 45870 | E7: Marketing | F7: MKT-Marketing Ops | G7: Staff Data Engineer | H7: Trisha McCanna
A8: Ainsworth-Patrick, Christopher | B8: chris.ainsworth-patrick@docker.com | C8: 44649 | D8: 45870 | E8: Engineering | F8: ENG-SCS | G8: Staff Software Engineer | H8: Stéphanie Hertrich | I8: Secure Supply Chain
A9: Aizawa, Daisuke | B9: daisuke.aizawa@docker.com | C9: 45244 | D9: 45870 | E9: Sales | F9: SLS-MidEnterprise-EMEA | G9: Associate Account Executive, Mid-Enterprise | H9: Jay Goodman
A10: Albu, Andrei | B10: andrei.albu@docker.com | C10: 44768 | D10: 45870 | E10: Engineering | F10: ENG-DD & Core DX | G10: Manager, Engineering | H10: Chris Crone | I10: Release and Platform
A11: Albus, Roderick | B11: roderick.albus@docker.com | C11: 45482 | D11: 45482 | E11: Sales | F11: SLS-Enterprise-EMEA | G11: Sr Account Executive, Enterprise | H11: James Hammons | I11: Enterprise
A12: Aleyner, Elia | B12: Elia.Aleyner@docker.com | C12: 45280 | D12: 45870 | E12: Products | F12: PROD-General | G12: Head of Technical Alliances | H12: Mark Cavage
A13: Allen, Abigail | B13: abigail.allen@docker.com | C13: 45083 | D13: 45870 | E13: Sales | F13: SLS-Growth & Renewals | G13: Renewals Manager I | H13: Jon Stout | I13: Renewals
A14: Allen, John | B14: john.allen@docker.com | C14: 45908 | D14: 45908 | E14: Sales | F14: SLS-Channel | G14: Partner Sales Manager | H14: Aaron Morrison
A15: Allen, Mark | B15: mark.allen@docker.com | C15: 45412 | D15: 45870 | E15: Sales | F15: SLS-Solutions Engineering | G15: Solutions Engineer, Strategic | H15: Kevin Barfield | I15: Solutions Engineers
A16: Allsopp, Patricia | B16: trish.allsopp@docker.com | C16: 44607 | D16: 45231 | E16: General & Administrative | F16: GA-People | G16: Lead, Recruiting Operations | H16: Breanna Paredes
A17: Alonso, Javier | B17: javier.alonso@docker.com | C17: 44950 | D17: 45870 | E17: Products | F17: PROD-Product Design | G17: Staff Product Designer | H17: Earl Carlson | I17: Performance and Stability
A18: AlSaif, Manal | B18: manal.alsaif@docker.com | C18: 45223 | D18: 45870 | E18: Products | F18: PROD-Product Design | G18: Sr Product Designer | H18: Earl Carlson | I18: Core Experiences
A19: Alvarez, Kevin | B19: kevin.alvarez@docker.com | C19: 44368 | D19: 45870 | E19: Engineering | F19: ENG-DD & Core DX | G19: Staff Software Engineer | H19: Shaun Thompson | I19: Core Components
A20: Amandong, Ashime | B20: ashime.ashime@docker.com | C20: 44615 | D20: 45870 | E20: Customer Success | F20: CS-Support | G20: Sr Solutions Architect | H20: Walker McCandrew | I20: CS Enablement
A21: Amarendiran, Kavindira | B21: kavindira.amarendiran@docker.com | C21: 45098 | D21: 45870 | E21: Customer Success | F21: CS-Support | G21: Sr Sustaining Engineer | H21: Gagan Arora | I21: Sustaining Engineers
A22: Angeles, Jennifer | B22: jennifer.angeles@docker.com | C22: 45006 | D22: 45870 | E22: Marketing | F22: MKT-Product Marketing | G22: Sr Manager, Enablement GTM | H22: Nikhil Kaul
A23: Anhalt, Fabienne | B23: fabienne.anhalt@docker.com | C23: 45916 | D23: 45916 | E23: Engineering | F23: ENG-SCS | G23: Software Engineer II | H23: Elliot Rushton
A24: Ani, Eileen | B24: eileen.ani@docker.com | C24: 44775 | D24: 45870 | E24: Products | F24: PROD-Product Design | G24: Director, Product Design | H24: Tushar Jain
A25: Arora, Gagan | B25: gagan.arora@docker.com | C25: 44979 | D25: 45870 | E25: Customer Success | F25: CS-Support | G25: Sr Manager, Sustaining Engineering | H25: Jerry Baker | I25: Sustaining Engineers
A26: Asim, Ozair | B26: ozair.asim@docker.com | C26: 45195 | D26: 45870 | E26: Engineering | F26: ENG-SCS | G26: Sr Software Engineer | H26: Stéphanie Hertrich | I26: Registry
A27: Aslam, Zubair | B27: zubair.aslam@docker.com | C27: 45132 | D27: 45870 | E27: Sales | F27: SLS-Solutions Engineering | G27: Principal Solutions Manager | H27: Andrew Muollo | I27: SE
A28: Axsom, Shawn | B28: shawn.axsom@docker.com | C28: 44102 | D28: 45888 | E28: Engineering | F28: ENG-Accounts & Billing | G28: Director, Engineering | H28: Dave Morris | I28: Billing
A29: Ayub, John | B29: john.ayub@docker.com | C29: 45441 | D29: 45870 | E29: Marketing | F29: MKT-Product Marketing | G29: Staff Product Marketing Manager | H29: Nikhil Kaul
A30: Azevedo, Hugo | B30: hugo.azevedo@docker.com | C30: 45426 | D30: 45870 | E30: Sales | F30: SLS-Solutions Engineering | G30: Sr Solutions Engineer, Enterprise | H30: Kevin Barfield | I30: SE
A31: Azhar, Maxime | B31: maxime.azhar@docker.com | C31: 44796 | D31: 45870 | E31: Sales | F31: SLS-Growth & Renewals | G31: Sr Renewals Manager II | H31: Jon Stout | I31: Renewals
A32: Baker, Jerry | B32: jerry.baker@docker.com | C32: 44144 | D32: 45870 | E32: Customer Success | F32: CS-Support | G32: Director, Support | H32: Dixie Dunn | I32: Support
A33: Ballback, Stacee | B33: stacee.ballback@docker.com | C33: 44439 | D33: 45894 | E33: Marketing | F33: MKT-Growth Marketing | G33: Sr Global Integrated Campaigns Manager | H33: Maria Johnson
A34: Barfield, Kevin | B34: kevin.barfield@docker.com | C34: 45028 | D34: 45870 | E34: Sales | F34: SLS-Solutions Engineering | G34: Director, Solution Engineers | H34: Cody Green | I34: Solutions Architects
A35: Barker, Christopher | B35: chris.barker@docker.com | C35: 45741 | D35: 45870 | E35: Sales | F35: SLS-Solutions Engineering | G35: Sr Solutions Engineer, Enterprise | H35: Kevin Barfield | I35: Solutions Engineers
A36: Barnaby, Allison | B36: allison.barnaby@docker.com | C36: 45230 | D36: 45870 | E36: Sales | F36: SLS-MidEnterprise-NA | G36: Sr Manager, Mid Enterprise East | H36: Tyler Kluempke
A37: Basnayake, Sadeepa | B37: tharinda.basnayake@docker.com | C37: 44502 | D37: 45870 | E37: Sales | F37: SLS-TAM | G37: Technical Account Manager | H37: Maja Chapus | I37: Customer Advisory Team
A38: Baumgartner, Edwin | B38: scott.baumgartner@docker.com | C38: 43916 | D38: 45701 | E38: General & Administrative | F38: GA-Finance | G38: CFO | H38: Don Johnson
A39: Becic, Joseph | B39: joe.becic@docker.com | C39: 43291 | D39: 45047 | E39: General & Administrative | F39: GA-Finance | G39: Director, Finance | H39: Scott Baumgartner
A40: Beck, Nicolas | B40: nicolas.beck@docker.com | C40: 44748 | D40: 45870 | E40: Engineering | F40: ENG-AI Cloud | G40: Sr Software Engineer | H40: Ivan Curkovic | I40: Build Cloud
A41: Behnisch, Carl | B41: caspar.behnisch@docker.com | C41: 44901 | D41: 45470 | E41: Sales | F41: SLS-Enterprise-EMEA | G41: Account Executive, Enterprise | H41: James Hammons | I41: Enterprise
A42: Bell, William | B42: will.bell@docker.com | C42: 45069 | D42: 45870 | E42: Products | F42: PROD-Data & Growth | G42: Analytics Engineer II | H42: Dragos Georgescu | I42: Data Analysts / Analytics Engineers
A43: Bélorgey, Romain | B43: romain.belorgey@docker.com | C43: 43004 | D43: 45870 | E43: Engineering | F43: ENG-AI Cloud | G43: Staff Software Engineer | H43: Rob Braden | I43: Infra
A44: Benavides, Jose | B44: joel.benavides@docker.com | C44: 44831 | D44: 44831 | E44: General & Administrative | F44: GA-Legal | G44: Head of Legal | H44: Scott Baumgartner
A45: Bendebury, Catherine | B45: catherine.bendebury@docker.com | C45: 45846 | D45: 45894 | E45: Products | F45: PROD-General | G45: Staff GTM AI Engineer | H45: Christopher Pluntke
A46: Benson, Erin | B46: erin.benson@docker.com | C46: 45013 | D46: 45778 | E46: Sales | F46: SLS-Strategic-NA | G46: Sr Account Executive, Strategic | H46: Will Schulz | I46: Strategic
A47: Bercea, Nick | B47: nick.bercea@docker.com | C47: 45265 | D47: 45870 | E47: Products | F47: PROD-Product Design | G47: Staff Product Designer | H47: Earl Carlson | I47: Design Systems
A48: Berezin Stelzer, Daniel | B48: dan.stelzer@docker.com | C48: 45049 | D48: 45870 | E48: Marketing | F48: MKT-Product Marketing | G48: Sr Manager, Partner GTM | H48: Nikhil Kaul
A49: Bernalte Pérez, Lucas | B49: lucas.bernalte@docker.com | C49: 44699 | D49: 45870 | E49: Engineering | F49: ENG-SCS | G49: Sr Software Engineer | H49: Stéphanie Hertrich | I49: Hub Experience
A50: Berry, Austin | B50: austin.berry@docker.com | C50: 44664 | D50: 45870 | E50: Engineering | F50: ENG-AI Cloud | G50: Software Engineer II | H50: Ivan Curkovic | I50: Build Cloud
A51: Bessoni, Shannyn | B51: shannyn.bessoni@docker.com | C51: 44039 | D51: 45839 | E51: General & Administrative | F51: GA-Ops | G51: Sr Manager, Operations | H51: Jeffrey Strauss
A52: Bittinger, Nathan | B52: nate.bittinger@docker.com | C52: 45874 | D52: 45874 | E52: Engineering | F52: ENG-SCS | G52: Vice President, Engineering | H52: Tushar Jain | I52: Supply Chain Security
A53: Bivins, Jason | B53: jason.bivins@docker.com | C53: 44615 | D53: 45870 | E53: Customer Success | F53: CS-Support | G53: Sustaining Engineer III | H53: Gagan Arora | I53: Sustaining Engineers
A54: Black, Alexander | B54: alexander.black@docker.com | C54: 45559 | D54: 45874 | E54: Sales | F54: SLS-Sales Operations | G54: Sr Revenue Insights Manager | H54: Matthew Irick | I54: Rev Ops
A55: Blodget, Britney | B55: britney.blodget@docker.com | C55: 44509 | D55: 45870 | E55: Products | F55: PROD-SCS | G55: Sr Product Manager | H55: Michael Donovan | I55: Hub Experience
A56: Bojorges Rodriguez, Eva | B56: eva.bojorges@docker.com | C56: 44453 | D56: 45870 | E56: Marketing | F56: MKT-Developer Success | G56: Sr Community Success Manager | H56: Per Krogslund
A57: Bost, Aaron | B57: aaron.bost@docker.com | C57: 45189 | D57: 45211 | E57: Sales | F57: SLS-Growth & Renewals | G57: Sr Renewals Manager I | H57: Joey Marrone III | I57: Renewals
A58: Braden, James | B58: james.braden@docker.com | C58: 45020 | D58: 45874 | E58: Engineering | F58: ENG-AI Cloud | G58: Manager, Engineering | H58: Karan Vohra | I58: Infra
A59: Brady, Sean | B59: sean.brady@docker.com | C59: 44894 | D59: 45870 | E59: Products | F59: PROD-Product Design | G59: Staff Product Designer | H59: Eileen Ani | I59: Hub Experience
A60: Braun, Michael | B60: eric.braun@docker.com | C60: 45797 | D60: 45870 | E60: Sales | F60: SLS-General | G60: Sr VP, Growth | H60: Mark Cavage
A61: Brawner, Anna | B61: anna.brawner@docker.com | C61: 44291 | D61: 45231 | E61: General & Administrative | F61: GA-People | G61: Recruiting Coordinator | H61: Trish Allsopp
A62: Breja, Andrew | B62: andrew.breja@docker.com | C62: 45223 | D62: 45870 | E62: Engineering | F62: ENG-DD & Core DX | G62: Sr Software Engineer | H62: Rick Redondo | I62: Dev Team ProdX
A63: Briend, Jean-Philippe | B63: jeanphilippe.briend@docker.com | C63: 45349 | D63: 45870 | E63: Engineering | F63: ENG-SCS | G63: Staff Software Engineer | H63: Stéphanie Hertrich | I63: Core Components
A64: Briney, Emmanuel | B64: emmanuel.briney@docker.com | C64: 42310 | D64: 45870 | E64: Engineering | F64: ENG-DD & Core DX | G64: Staff Software Engineer | H64: Andrei Albu | I64: Performance and Stability
A65: Briol, Magali | B65: magali.briol@docker.com | C65: 44811 | D65: 45870 | E65: Sales | F65: SLS-Growth & Renewals | G65: Sr Renewals Manager | H65: Jon Stout | I65: Renewals
A66: Bunselmeyer, William | B66: william.bunselmeyer@docker.com | C66: 45104 | D66: 45870 | E66: Engineering | F66: ENG-DD & Core DX | G66: Manager, Engineering | H66: Chris Crone | I66: Projects
A67: Buote Jr., Paul | B67: paul.buote@docker.com | C67: 45776 | D67: 45776 | E67: Sales | F67: SLS-Strategic-NA | G67: Sr Account Executive, Strategic | H67: Will Schulz | I67: Strategic
A68: Burigo, Robert | B68: robert.burigo@docker.com | C68: 45636 | D68: 45870 | E68: Products | F68: PROD-Data & Growth | G68: Sr Data Analyst | H68: Dragos Georgescu | I68: Data Analysts
A69: Burov, Oleg | B69: oleg.burov@docker.com | C69: 43473 | D69: 45870 | E69: Engineering | F69: ENG-Accounts & Billing | G69: Principal Software Engineer | H69: Shawn Axsom | I69: Billing
A70: Californias, Iván | B70: ivan.californias@docker.com | C70: 44565 | D70: 45870 | E70: Engineering | F70: ENG-Accounts & Billing | G70: Staff Software Engineer | H70: Shawn Axsom | I70: IAM
A71: Callaghan, Megan | B71: megan.callaghan@docker.com | C71: 44375 | D71: 45870 | E71: Products | F71: PROD-Product Design | G71: Staff Product Designer | H71: Earl Carlson | I71: Design Systems
A72: Camacho, Iain | B72: iain.camacho@docker.com | C72: 45006 | D72: 45870 | E72: Products | F72: PROD-Product Design | G72: Staff Product Designer | H72: Earl Carlson | I72: Cloud
A73: Campbell, Julianne | B73: julianne.campbell@docker.com | C73: 44854 | D73: 44909 | E73: General & Administrative | F73: GA-General | G73: Executive Assistant | H73: Alex Rojas
A74: Carle, Michael | B74: michael.carle@docker.com | C74: 45489 | D74: 45489 | E74: Sales | F74: SLS-Strategic-NA | G74: Account Executive, Strategic | H74: Will Schulz | I74: Strategic
A75: Carlson, Earl | B75: earl.carlson@docker.com | C75: 45370 | D75: 45870 | E75: Products | F75: PROD-Product Design | G75: Sr Manager, Product Design | H75: Eileen Ani
A76: Carlson, Nathan | B76: nathan.carlson@docker.com | C76: 44663 | D76: 45870 | E76: Sales | F76: SLS-MidEnterprise-NA | G76: Sr Account Executive, Mid-Enterprise | H76: Matthew Preston | I76: Scaled Acquisition
A77: Carter, Alec | B77: alec.carter@docker.com | C77: 44992 | D77: 45231 | E77: General & Administrative | F77: GA-People | G77: Recruiting Coordinator | H77: Trish Allsopp
A78: Carter, Jeffrey | B78: jeff.carter@docker.com | C78: 44221 | D78: 45874 | E78: Engineering | F78: ENG-SCS | G78: Principal Software Engineer | H78: Nate Bittinger
A79: Casey, Emily | B79: emily.casey@docker.com | C79: 45280 | D79: 45870 | E79: Engineering | F79: ENG-AI Cloud | G79: Staff Software Engineer | H79: Kevin Wittek | I79: AI Enablement
A80: Castañeda, Devin | B80: devin.castaneda@docker.com | C80: 45405 | D80: 45870 | E80: Engineering | F80: ENG-Accounts & Billing | G80: Sr Software Engineer | H80: Shawn Axsom | I80: Billing
A81: Cattaneo, Yusuf | B81: yusuf.cattaneo@docker.com | C81: 45398 | D81: 45870 | E81: Sales | F81: SLS-Solutions Engineering | G81: Sr Solutions Engineer, Enterprise | H81: Kevin Barfield | I81: Solutions Engineers
A82: Cavage, Mark | B82: mark.cavage@docker.com | C82: 45719 | D82: 45719 | E82: General & Administrative | F82: GA-General | G82: President & Chief Operating Officer | H82: Don Johnson
A83: Cerantonio, Martin | B83: martin.cerantonio@docker.com | C83: 45272 | D83: 45870 | E83: Sales | F83: SLS-Channel | G83: Sr Channel Manager | H83: Aaron Morrison | I83: Channel
A84: Cezar-George, Martin | B84: martin.cezar-george@docker.com | C84: 44992 | D84: 45870 | E84: Customer Success | F84: CS-Support | G84: Sr Technical Support Engineer | H84: Kristel Touron | I84: Support
A85: Champlon, Mathieu | B85: mathieu.champlon@docker.com | C85: 43193 | D85: 45870 | E85: Engineering | F85: ENG-DD & Core DX | G85: Principal Software Engineer | H85: Andrei Albu | I85: Release and Platform
A86: Chao, Monica | B86: monica.chao@docker.com | C86: 45321 | D86: 45870 | E86: Customer Success | F86: CS-Support | G86: Sustaining Engineer III | H86: Gagan Arora | I86: Sustaining Engineers
A87: Chapus, Maja | B87: maja.chapus@docker.com | C87: 45069 | D87: 45870 | E87: Sales | F87: SLS-TAM | G87: Sr Manager, Technical Account Managers | H87: Stuart Minchington
A88: Charrière, Philippe | B88: philippe.charriere@docker.com | C88: 45279 | D88: 45870 | E88: Customer Success | F88: CS-General | G88: Principal Solutions Architect | H88: Kevin Barfield | I88: Solutions Architects
A89: Chernyshova, Ganna | B89: anna.chernyshova@docker.com | C89: 45280 | D89: 45870 | E89: Sales | F89: SLS-Solutions Engineering | G89: Sr Solutions Engineer, Commercial | H89: Cody Green | I89: SE
A90: Chhokar, Preet | B90: preet.chhokar@docker.com | C90: 45503 | D90: 45503 | E90: Sales | F90: SLS-Strategic-NA | G90: Sr Account Executive, Strategic | H90: Will Schulz | I90: Strategic
A91: Childs, James | B91: james.childs@docker.com | C91: 44880 | D91: 45870 | E91: Engineering | F91: ENG-Accounts & Billing | G91: Software Engineer III | H91: Shawn Axsom | I91: Billing
A92: Ching, Jason | B92: jason.ching@docker.com | C92: 45636 | D92: 45888 | E92: Products | F92: PROD-Accounts & Billing | G92: Staff Product Manager | H92: Dave Morris
A93: Choe, Eugene | B93: eugene.choe@docker.com | C93: 45531 | D93: 45870 | E93: Sales | F93: SLS-TAM | G93: Technical Account Manager | H93: Andrew Muollo | I93: Customer Success
A94: Christou, Nicolas | B94: nick.christou@docker.com | C94: 45398 | D94: 45870 | E94: Sales | F94: SLS-MidEnterprise-NA | G94: Sr Director, Mid Enterprise West | H94: Eric Braun | I94: Mid Market
A95: Ciccariello, Luciano | B95: luciano.ciccariello@docker.com | C95: 45202 | D95: 45870 | E95: Engineering | F95: ENG-DD & Core DX | G95: Sr Software Engineer | H95: Barbara Fusinska | I95: Performance and Stability
A96: Clark, Bradley | B96: jim.clark@docker.com | C96: 44720 | D96: 45870 | E96: Engineering | F96: ENG-AI Cloud | G96: Principal Software Engineer | H96: Ilker Temir | I96: AI Tools
A97: Clement, Maxime | B97: maxime.clement@docker.com | C97: 44656 | D97: 45870 | E97: Engineering | F97: ENG-DD & Core DX | G97: Sr Software Engineer | H97: Andrei Albu | I97: Release and Platform
A98: Clemons, Jana | B98: jana.clemons@docker.com | C98: 45636 | D98: 45909 | E98: Marketing | F98: MKT-General | G98: Sr Principal Product Manager | H98: James Coleman
A99: Coleman, James | B99: james.coleman@docker.com | C99: 45909 | D99: 45909 | E99: Marketing | F99: MKT-Growth Marketing | G99: Vice President, Growth Product | H99: Andy Ramirez
A100: Coleman, Mike | B100: mike.coleman@docker.com | C100: 45468 | D100: 45870 | E100: Customer Success | F100: CS-General | G100: Staff Solutions Architect | H100: Kevin Barfield | I100: Customer Success
...

Sheet Cloudflare
A1: Work Email | B1: roles | C1: Reviewed by: | D1: Downgraded Permissions or Removed (If disabled for 90+ days, please remove) | E1: Notes | F1: Active Employee | G1: VLOOKUP
A2: aaron.solomon@docker.com | B2: Billing, Analytics | F2: No | G2: =VLOOKUP(A2,'Active Employees'!$B$2:$B$498,1,false) -> #N/A
A3: karan.vohra@docker.com | B3: Super Administrator - All Privileges | F3: No | G3: =VLOOKUP(A3,'Active Employees'!$B$2:$B$498,1,false) -> #N/A
A4: alex.hokanson@docker.com | B4: Super Administrator - All Privileges | F4: Yes | G4: =VLOOKUP(A4,'Active Employees'!$B$2:$B$498,1,false) -> alex.hokanson@docker.com
A5: silvin.lubecki@docker.com | B5: Administrator Read Only | F5: Yes | G5: =VLOOKUP(A5,'Active Employees'!$B$2:$B$498,1,false) -> silvin.lubecki@docker.com
A6: romain.belorgey@docker.com | B6: Super Administrator - All Privileges | F6: Yes | G6: =VLOOKUP(A6,'Active Employees'!$B$2:$B$498,1,false) -> romain.belorgey@docker.com
A7: james.braden@docker.com | B7: Super Administrator - All Privileges, Administrator | F7: Yes | G7: =VLOOKUP(A7,'Active Employees'!$B$2:$B$498,1,false) -> james.braden@docker.com
A8: ozair.asim@docker.com | B8: Administrator Read Only | F8: Yes | G8: =VLOOKUP(A8,'Active Employees'!$B$2:$B$498,1,false) -> ozair.asim@docker.com
A9: jeff.carter@docker.com | B9: Super Administrator - All Privileges, Administrator | F9: Yes | G9: =VLOOKUP(A9,'Active Employees'!$B$2:$B$498,1,false) -> jeff.carter@docker.com
A10: stephanie.hertrich@docker.com | B10: Super Administrator - All Privileges | F10: Yes | G10: =VLOOKUP(A10,'Active Employees'!$B$2:$B$498,1,false) -> stephanie.hertrich@docker.com
A11: vincent.damery@docker.com | B11: Administrator Read Only | F11: Yes | G11: =VLOOKUP(A11,'Active Employees'!$B$2:$B$498,1,false) -> vincent.damery@docker.com
A12: gabriele.dibernardo@docker.com | B12: Administrator Read Only | F12: Yes | G12: =VLOOKUP(A12,'Active Employees'!$B$2:$B$498,1,false) -> gabriele.dibernardo@docker.com
A13: shelton.graves@docker.com | B13: Administrator Read Only | F13: Yes | G13: =VLOOKUP(A13,'Active Employees'!$B$2:$B$498,1,false) -> shelton.graves@docker.com
... A21: kyle.trantham@docker.com | B21: Administrator Read Only | F21: Yes | G21: =VLOOKUP(A21,'Active Employees'!$B$2:$B$498,1,false) -> kyle.trantham@docker.com
A22: infra+cloudflare@docker.com | B22: Super Administrator - All Privileges | G22: =VLOOKUP(A22,'Active Employees'!$B$2:$B$498,1,false) -> #N/A

Sheet Github - Docker
A1: login | B1: name | C1: is_public | D1: role | E1: saml_name_id | F1: Reviewed by: | G1: Downgraded Permissions or Removed (If disabled for 90+ days, please remove) | H1: Notes | I1: VLOOKUP | J1: Active Employee
A2: brentseaton92 | C2: FALSE | D2: Owner | E2: brent_seaton@docker.com | I2: Contractor | J2: Yes
A3: cdupuis | B3: Christian Dupuis | C3: FALSE | D3: Owner | E3: christian.dupuis@docker.com | I3: =VLOOKUP(E3,'Active Employees'!$B$2:$B$498,1,false) -> christian.dupuis@docker.com | J3: Yes
A4: chris-crone | B4: Chris Crone | C4: TRUE | D4: Owner | E4: christopher.crone@docker.com | I4: =VLOOKUP(E4,'Active Employees'!$B$2:$B$498,1,false) -> christopher.crone@docker.com | J4: Yes
A5: danwschultz | B5: Dan Schultz | C5: FALSE | D5: Owner | E5: daniel.schultz@docker.com | I5: =VLOOKUP(E5,'Active Employees'!$B$2:$B$498,1,false) -> daniel.schultz@docker.com | J5: Yes
A6: fjmcs | B6: Fiona McShane | C6: FALSE | D6: Owner | E6: fiona.mcshane@docker.com | I6: =VLOOKUP(E6,'Active Employees'!$B$2:$B$498,1,false) -> fiona.mcshane@docker.com | J6: Yes
A7: ipedrazas | B7: Ivan Pedrazas | C7: FALSE | D7: Owner | E7: ivan.pedrazas@docker.com | I7: =VLOOKUP(E7,'Active Employees'!$B$2:$B$498,1,false) -> ivan.pedrazas@docker.com | J7: Yes
A8: jeanlaurent | B8: Jean-Laurent de Morlhon | C8: TRUE | D8: Owner | E8: jeanlaurent@docker.com | I8: =VLOOKUP(E8,'Active Employees'!$B$2:$B$498,1,false) -> jeanlaurent@docker.com | J8: Yes
A9: jeffreystrauss | B9: Jeff Strauss | C9: FALSE | D9: Owner | E9: jeffrey.strauss@docker.com | I9: =VLOOKUP(E9,'Active Employees'!$B$2:$B$498,1,false) -> jeffrey.strauss@docker.com | J9: Yes
A10: masegraye | B10: Mase Graye | C10: FALSE | D10: Owner | E10: mason.graye@docker.com | I10: =VLOOKUP(E10,'Active Employees'!$B$2:$B$498,1,false) -> mason.graye@docker.com | J10: Yes
A11: neilprosser | B11: Neil Prosser | C11: FALSE | D11: Owner | E11: neil.prosser@docker.com | I11: =VLOOKUP(E11,'Active Employees'!$B$2:$B$498,1,false) -> neil.prosser@docker.com | J11: Yes
A12: nfdocker | B12: Nate Fitch | C12: FALSE | D12: Owner | E12: nate.fitch@docker.com | I12: =VLOOKUP(E12,'Active Employees'!$B$2:$B$498,1,false) -> nate.fitch@docker.com | J12: Yes
A13: nicks | B13: Nick Santos | C13: FALSE | D13: Owner | E13: nick.santos@docker.com | I13: =VLOOKUP(E13,'Active Employees'!$B$2:$B$498,1,false) -> nick.santos@docker.com | J13: Yes
A14: shawnaxsom | B14: Shawn Axsom | C14: FALSE | D14: Owner | E14: shawn.axsom@docker.com | I14: =VLOOKUP(E14,'Active Employees'!$B$2:$B$498,1,false) -> shawn.axsom@docker.com | J14: Yes
... A21: vallieres | B21: Alexandre Vallières-Lagacé | C21: FALSE | D21: Owner | E21: alexandre.valliereslagace@docker.com | I21: =VLOOKUP(E21,'Active Employees'!$B$2:$B$498,1,false) -> alexandre.valliereslagace@docker.com | J21: Yes

Sheet Azure
A1: Tenant Name | B1: Scope Type | C1: Scope Name | D1: Work Email | E1: User Display Name | F1: Role Name | G1: Assignment Type | H1: Active Employee | I1: Reviewed by: | J1: Downgraded Permissions or Removed (If disabled for 90+ days, please remove) | K1: Notes | L1: VLOOKUP
A2: docker.co | B2: Azure AD Directory | C2: Directory-level | D2: okta.auth@dotcloud.onmicrosoft.com | E2: Okta Auth | F2: Knowledge Administrator | G2: Direct
A3: docker.co | B3: Azure AD Directory | C3: Directory-level | D3: okta.auth@dotcloud.onmicrosoft.com | E3: Okta Auth | F3: Virtual Visits Administrator | G3: Direct
A4: docker.co | B4: Azure AD Directory | C4: Directory-level | D4: okta.auth@dotcloud.onmicrosoft.com | E4: Okta Auth | F4: Exchange Recipient Administrator | G4: Direct
A5: docker.co | B5: Azure AD Directory | C5: Directory-level | D5: okta.auth@dotcloud.onmicrosoft.com | E5: Okta Auth | F5: Attribute Assignment Reader | G5: Direct
A6: docker.co | B6: Azure AD Directory | C6: Directory-level | D6: okta.auth@dotcloud.onmicrosoft.com | E6: Okta Auth | F6: Identity Governance Administrator | G6: Direct
A7: docker.co | B7: Azure AD Directory | C7: Directory-level | D7: okta.auth@dotcloud.onmicrosoft.com | E7: Okta Auth | F7: Customer LockBox Access Approver | G7: Direct
A8: docker.co | B8: Azure AD Directory | C8: Directory-level | D8: okta.auth@dotcloud.onmicrosoft.com | E8: Okta Auth | F8: Application Administrator | G8: Direct
A9: docker.co | B9: Azure AD Directory | C9: Directory-level | D9: okta.auth@dotcloud.onmicrosoft.com | E9: Okta Auth | F9: Windows 365 Administrator | G9: Direct
A10: docker.co | B10: Azure AD Directory | C10: Directory-level | D10: okta.auth@dotcloud.onmicrosoft.com | E10: Okta Auth | F10: Compliance Administrator | G10: Direct
A11: docker.co | B11: Azure AD Directory | C11: Directory-level | D11: okta.auth@dotcloud.onmicrosoft.com | E11: Okta Auth | F11: Edge Administrator | G11: Direct
A12: docker.co | B12: Azure AD Directory | C12: Directory-level | D12: okta.auth@dotcloud.onmicrosoft.com | E12: Okta Auth | F12: Exchange Administrator | G12: Direct
A13: docker.co | B13: Azure AD Directory | C13: Directory-level | D13: skalable.tech@docker.co | E13: Skalable | F13: Global Administrator | G13: Direct | H13: Contractor | L13: =VLOOKUP(D13,'Active Employees'!$B$2:$B$498,1,false) -> #N/A
A14: docker.co | B14: Azure AD Directory | C14: Directory-level | D14: okta.auth@dotcloud.onmicrosoft.com | E14: Okta Auth | F14: Cloud Device Administrator | G14: Direct | L14: =VLOOKUP(D14,'Active Employees'!$B$2:$B$498,1,false) -> #N/A
A15: docker.co | B15: Azure AD Directory | C15: Directory-level | D15: okta.auth@dotcloud.onmicrosoft.com | E15: Okta Auth | F15: Cloud App Security Administrator | G15: Direct | L15: =VLOOKUP(D15,'Active Employees'!$B$2:$B$498,1,false) -> #N/A
A16: docker.co | B16: Azure AD Directory | C16: Directory-level | D16: okta.auth@dotcloud.onmicrosoft.com | E16: Okta Auth | F16: Search Editor | G16: Direct | L16: =VLOOKUP(D16,'Active Employees'!$B$2:$B$498,1,false) -> #N/A
A17: docker.co | B17: Azure AD Directory | C17: Directory-level | D17: okta.auth@dotcloud.onmicrosoft.com | E17: Okta Auth | F17: Teams Devices Administrator | G17: Direct | L17: =VLOOKUP(D17,'Active Employees'!$B$2:$B$498,1,false) -> #N/A
A18: docker.co | B18: Azure AD Directory | C18: Directory-level | D18: okta.auth@dotcloud.onmicrosoft.com | E18: Okta Auth | F18: Attack Payload Author | G18: Direct | L18: =VLOOKUP(D18,'Active Employees'!$B$2:$B$498,1,false) -> #N/A
A19: docker.co | B19: Subscription | C19: Azure subscription 1 | D19: skalable.tech@docker.co | E19: Skalable | F19: User Access Administrator | G19: Direct | H19: Contractor | L19: =VLOOKUP(D19,'Active Employees'!$B$2:$B$498,1,false) -> #N/A
A20: docker.co | B20: Azure AD Directory | C20: Directory-level | D20: okta.auth@dotcloud.onmicrosoft.com | E20: Okta Auth | F20: External ID User Flow Administrator | G20: Direct | L20: =VLOOKUP(D20,'Active Employees'!$B$2:$B$498,1,false) -> #N/A
A21: docker.co | B21: Azure AD Directory | C21: Directory-level | D21: okta.auth@dotcloud.onmicrosoft.com | E21: Okta Auth | F21: License Administrator | G21: Direct | L21: =VLOOKUP(D21,'Active Employees'!$B$2:$B$498,1,false) -> #N/A
A22: docker.co | B22: Azure AD Directory | C22: Directory-level | D22: okta.auth@dotcloud.onmicrosoft.com | E22: Okta Auth | F22: Azure AD Joined Device Local Administrator | G22: Direct | L22: =VLOOKUP(D22,'Active Employees'!$B$2:$B$498,1,false) -> #N/A
A23: docker.co | B23: Azure AD Directory | C23: Directory-level | D23: okta.auth@dotcloud.onmicrosoft.com | E23: Okta Auth | F23: Attribute Definition Administrator | G23: Direct | L23: =VLOOKUP(D23,'Active Employees'!$B$2:$B$498,1,false) -> #N/A
A24: docker.co | B24: Azure AD Directory | C24: Directory-level | D24: okta.auth@dotcloud.onmicrosoft.com | E24: Okta Auth | F24: B2C IEF Keyset Administrator | G24: Direct | L24: =VLOOKUP(D24,'Active Employees'!$B$2:$B$498,1,false) -> #N/A
A25: docker.co | B25: Azure AD Directory | C25: Directory-level | D25: okta.auth@dotcloud.onmicrosoft.com | E25: Okta Auth | F25: Attribute Assignment Administrator | G25: Direct | L25: =VLOOKUP(D25,'Active Employees'!$B$2:$B$498,1,false) -> #N/A
A26: docker.co | B26: Azure AD Directory | C26: Directory-level | D26: okta.auth@dotcloud.onmicrosoft.com | E26: Okta Auth | F26: Directory Readers | G26: Direct | L26: =VLOOKUP(D26,'Active Employees'!$B$2:$B$498,1,false) -> #N/A
A27: docker.co | B27: Azure AD Directory | C27: Directory-level | D27: okta.auth@dotcloud.onmicrosoft.com | E27: Okta Auth | F27: SharePoint Administrator | G27: Direct | L27: =VLOOKUP(D27,'Active Employees'!$B$2:$B$498,1,false) -> #N/A
A28: docker.co | B28: Subscription | C28: Engineering Partnership Test | D28: skalable.tech@docker.co | E28: Skalable | F28: User Access Administrator | G28: Direct | H28: Contractor | L28: =VLOOKUP(D28,'Active Employees'!$B$2:$B$498,1,false) -> #N/A
A29: docker.co | B29: Subscription | C29: IAM Team | D29: skalable.tech@docker.co | E29: Skalable | F29: User Access Administrator | G29: Direct | H29: Contractor | L29: =VLOOKUP(D29,'Active Employees'!$B$2:$B$498,1,false) -> #N/A
A30: docker.co | B30: Azure AD Directory | C30: Directory-level | D30: okta.auth@dotcloud.onmicrosoft.com | E30: Okta Auth | F30: Azure DevOps Administrator | G30: Direct | L30: =VLOOKUP(D30,'Active Employees'!$B$2:$B$498,1,false) -> #N/A
A31: docker.co | B31: Azure AD Directory | C31: Directory-level | D31: okta.auth@dotcloud.onmicrosoft.com | E31: Okta Auth | F31: Kaizala Administrator | G31: Direct | L31: =VLOOKUP(D31,'Active Employees'!$B$2:$B$498,1,false) -> #N/A
A32: docker.co | B32: Azure AD Directory | C32: Directory-level | D32: okta.auth@dotcloud.onmicrosoft.com | E32: Okta Auth | F32: Insights Analyst | G32: Direct | L32: =VLOOKUP(D32,'Active Employees'!$B$2:$B$498,1,false) -> #N/A
A33: docker.co | B33: Azure AD Directory | C33: Directory-level | D33: okta.auth@dotcloud.onmicrosoft.com | E33: Okta Auth | F33: Insights Business Leader | G33: Direct | L33: =VLOOKUP(D33,'Active Employees'!$B$2:$B$498,1,false) -> #N/A
A34: docker.co | B34: Subscription | C34: IAM Team | D34: skalable.tech@docker.co | E34: Skalable | F34: User Access Administrator | G34: Direct | H34: Contractor | L34: =VLOOKUP(D34,'Active Employees'!$B$2:$B$498,1,false) -> #N/A
A35: docker.co | B35: Azure AD Directory | C35: Directory-level | D35: okta.auth@dotcloud.onmicrosoft.com | E35: Okta Auth | F35: Billing Administrator | G35: Direct | H35: Yes | L35: =VLOOKUP(D35,'Active Employees'!$B$2:$B$498,1,false) -> #N/A
A36: docker.co | B36: Subscription | C36: Sandbox | D36: skalable.tech@docker.co | E36: Skalable | F36: User Access Administrator | G36: Direct | H36: Contractor | L36: =VLOOKUP(D36,'Active Employees'!$B$2:$B$498,1,false) -> #N/A
A37: docker.co | B37: Subscription | C37: Security | D37: skalable.tech@docker.co | E37: Skalable | F37: User Access Administrator | G37: Direct | H37: Contractor | L37: =VLOOKUP(D37,'Active Employees'!$B$2:$B$498,1,false) -> #N/A
A38: docker.co | B38: Subscription | C38: Sustaining Engineering Team | D38: skalable.tech@docker.co | E38: Skalable | F38: User Access Administrator | G38: Direct | H38: Contractor | L38: =VLOOKUP(D38,'Active Employees'!$B$2:$B$498,1,false) -> #N/A
A39: docker.co | B39: Subscription | C39: Visual Studio Enterprise Subscription – MPN | D39: skalable.tech@docker.co | E39: Skalable | F39: User Access Administrator | G39: Direct | H39: Contractor | L39: =VLOOKUP(D39,'Active Employees'!$B$2:$B$498,1,false) -> #N/A
A40: docker.co | B40: Management Group | C40: Tenant Root Group | D40: skalable.tech@docker.co | E40: Skalable | F40: User Access Administrator | G40: Direct | H40: Contractor | L40: =VLOOKUP(D40,'Active Employees'!$B$2:$B$498,1,false) -> #N/A
A41: docker.com | B41: Azure AD Directory | C41: Directory-level | D41: skalable.tech@docker.com | E41: Skalable | F41: Global Administrator | G41: Direct | H41: Contractor | L41: =VLOOKUP(D41,'Active Employees'!$B$2:$B$498,1,false) -> #N/A
A42: docker.co | B42: Azure AD Directory | C42: Directory-level | D42: okta.auth@dotcloud.onmicrosoft.com | E42: Okta Auth | F42: Azure Information Protection Administrator | G42: Direct | H42: Yes | L42: =VLOOKUP(D42,'Active Employees'!$B$2:$B$498,1,false) -> #N/A
A43: docker.co | B43: Azure AD Directory | C43: Directory-level | D43: okta.auth@dotcloud.onmicrosoft.com | E43: Okta Auth | F43: Directory Writers | G43: Direct | H43: Yes | L43: =VLOOKUP(D43,'Active Employees'!$B$2:$B$498,1,false) -> #N/A
A44: docker.co | B44: Azure AD Directory | C44: Directory-level | D44: okta.auth@dotcloud.onmicrosoft.com | E44: Okta Auth | F44: Reports Reader | G44: Direct | H44: Yes | L44: =VLOOKUP(D44,'Active Employees'!$B$2:$B$498,1,false) -> #N/A
A45: docker.co | B45: Azure AD Directory | C45: Directory-level | D45: okta.auth@dotcloud.onmicrosoft.com | E45: Okta Auth | F45: Global Reader | G45: Direct | H45: Yes | L45: =VLOOKUP(D45,'Active Employees'!$B$2:$B$498,1,false) -> #N/A
... A143: docker.co | B143: Subscription | C143: Visual Studio Enterprise Subscription – MPN | D143: ryan.hristovski@docker.co | E143: Ryan Hristovski | F143: Owner (via group: Infra Team) | G143: Group | H143: No | L143: =VLOOKUP(D143,'Active Employees'!$B$2:$B$498,1,false) -> #N/A
A144: docker.co | B144: Subscription | C144: Engineering Partnership Test | D144: ServicePrincipal: CloudPosture/securityOperators/DefenderCSPMSecurityOperator | E144: CloudPosture/securityOperators/DefenderCSPMSecurityOperator | F144: Role Based Access Control Administrator | G144: Service Principal | L144: =VLOOKUP(D144,'Active Employees'!$B$2:$B$498,1,false) -> #N/A
A145: docker.co | B145: Subscription | C145: Engineering Partnership Test | D145: ServicePrincipal: StorageAccounts/securityOperators/DefenderForStorageSecurityOperator | E145: StorageAccounts/securityOperators/DefenderForStorageSecurityOperator | F145: Role Based Access Control Administrator | G145: Service Principal | L145: =VLOOKUP(D145,'Active Employees'!$B$2:$B$498,1,false) -> #N/A
A146: docker.co | B146: Subscription | C146: Engineering Partnership Test | D146: ServicePrincipal: dockerdevboxidentity | E146: dockerdevboxidentity | F146: Contributor | G146: Service Principal | L146: =VLOOKUP(D146,'Active Employees'!$B$2:$B$498,1,false) -> #N/A
A147: docker.co | B147: Subscription | C147: Engineering Partnership Test | D147: ServicePrincipal: devcenter2 | E147: devcenter2 | F147: Owner | G147: Service Principal | L147: =VLOOKUP(D147,'Active Employees'!$B$2:$B$498,1,false) -> #N/A
A148: docker.co | B148: Subscription | C148: Engineering Partnership Test | D148: ServicePrincipal: devcenter2 | E148: devcenter2 | F148: Contributor | G148: Service Principal | L148: =VLOOKUP(D148,'Active Employees'!$B$2:$B$498,1,false) -> #N/A
A149: docker.co | B149: Subscription | C149: Engineering Partnership Test | D149: ServicePrincipal: thedevcenternew | E149: thedevcenternew | F149: Contributor | G149: Service Principal | L149: =VLOOKUP(D149,'Active Employees'!$B$2:$B$498,1,false) -> #N/A
A150: docker.co | B150: Subscription | C150: Engineering Partnership Test | D150: ServicePrincipal: thedevcenternew | E150: thedevcenternew | F150: Contributor | G150: Service Principal | L150: =VLOOKUP(D150,'Active Employees'!$B$2:$B$498,1,false) -> #N/A
A151: docker.co | B151: Subscription | C151: Engineering Partnership Test | D151: ServicePrincipal: testdevcenternew | E151: testdevcenternew | F151: Contributor | G151: Service Principal | L151: =VLOOKUP(D151,'Active Employees'!$B$2:$B$498,1,false) -> #N/A
A152: docker.com | B152: Azure AD Directory | C152: Directory-level | D152: ryan.hristovski@docker.com | E152: Ryan Hristovski | F152: Global Administrator (via group: Infrastructure Team) | G152: Group | H152: No | L152: =VLOOKUP(D152,'Active Employees'!$B$2:$B$498,1,false) -> #N/A
A153: docker.com | B153: Subscription | C153: Docker Azure Marketplace | D153: ryan.hristovski@docker.com | E153: Ryan Hristovski | F153: Owner (via group: Infra) | G153: Group | H153: No | L153: =VLOOKUP(D153,'Active Employees'!$B$2:$B$498,1,false) -> #N/A
A154: docker.com | B154: Subscription | C154: Docker CI | D154: ryan.hristovski@docker.com | E154: Ryan Hristovski | F154: Owner (via group: Infra) | G154: Group | H154: No | L154: =VLOOKUP(D154,'Active Employees'!$B$2:$B$498,1,false) -> #N/A
A155: docker.com | B155: Subscription | C155: official_github_actions | D155: ryan.hristovski@docker.com | E155: Ryan Hristovski | F155: Owner (via group: Infra) | G155: Group | H155: No | L155: =VLOOKUP(D155,'Active Employees'!$B$2:$B$498,1,false) -> #N/A
A156: docker.com | B156: Subscription | C156: Docker Azure Marketplace | D156: azure-sub@docker.com | E156: azure-sub@azuresubdocker.onmicrosoft.com | F156: User Access Administrator | G156: Direct | H156: Yes | L156: =VLOOKUP(D156,'Active Employees'!$B$2:$B$498,1,false) -> #N/A
A157: docker.com | B157: Subscription | C157: Docker CI | D157: azure-sub@docker.com | E157: azure-sub@azuresubdocker.onmicrosoft.com | F157: User Access Administrator | G157: Direct | H157: Yes | L157: =VLOOKUP(D157,'Active Employees'!$B$2:$B$498,1,false) -> #N/A
A158: docker.com | B158: Subscription | C158: lsp integrations insights | D158: azure-sub@docker.com | E158: azure-sub@azuresubdocker.onmicrosoft.com | F158: User Access Administrator | G158: Direct | H158: Yes | L158: =VLOOKUP(D158,'Active Employees'!$B$2:$B$498,1,false) -> #N/A
A159: docker.com | B159: Subscription | C159: Microsoft Azure Enterprise | D159: azure-sub@docker.com | E159: azure-sub@azuresubdocker.onmicrosoft.com | F159: User Access Administrator | G159: Direct | H159: Yes | L159: =VLOOKUP(D159,'Active Employees'!$B$2:$B$498,1,false) -> #N/A
A160: docker.com | B160: Subscription | C160: Migrating subscription | D160: azure-sub@docker.com | E160: azure-sub@azuresubdocker.onmicrosoft.com | F160: User Access Administrator | G160: Direct | H160: Yes | L160: =VLOOKUP(D160,'Active Employees'!$B$2:$B$498,1,false) -> #N/A
A161: docker.com | B161: Subscription | C161: official_github_actions | D161: azure-sub@docker.com | E161: azure-sub@azuresubdocker.onmicrosoft.com | F161: User Access Administrator | G161: Direct | H161: Yes | L161: =VLOOKUP(D161,'Active Employees'!$B$2:$B$498,1,false) -> #N/A
A162: docker.com | B162: Subscription | C162: Play with Docker | D162: azure-sub@docker.com | E162: azure-sub@azuresubdocker.onmicrosoft.com | F162: User Access Administrator | G162: Direct | H162: Yes | L162: =VLOOKUP(D162,'Active Employees'!$B$2:$B$498,1,false) -> #N/A
A163: docker.com | B163: Subscription | C163: Security | D163: azure-sub@docker.com | E163: azure-sub@azuresubdocker.onmicrosoft.com | F163: User Access Administrator | G163: Direct | H163: Yes | L163: =VLOOKUP(D163,'Active Employees'!$B$2:$B$498,1,false) -> #N/A
... A187: docker.co | B187: Subscription | C187: Sandbox | D187: yves.brissaud@docker.co | E187: Yves Brissaud | F187: Contributor | G187: Direct | H187: No | L187: =VLOOKUP(D187,'Active Employees'!$B$2:$B$498,1,false) -> #N/A
A188: docker.co | B188: Subscription | C188: Sandbox | D188: zubair.aslam@docker.co | E188: Zubair | F188: Contributor (via group: Solutions Engineering Team) | G188: Group | H188: No
A189: docker.co | B189: Subscription | C189: Engineering Partnership Test | D189: zhelyazko.petrov@docker.co | E189: Zhel Petrov | F189: Contributor (via group: Security Team) | G189: Group | H189: No | L189: NO
A190: docker.co | B190: Subscription | C190: Engineering Partnership Test | D190: zhelyazko.petrov@docker.co | E190: Zhel Petrov | F190: Owner (via group: Security Team) | G190: Group | H190: No | L190: NO
A191: docker.co | B191: Subscription | C191: Sandbox | D191: zhelyazko.petrov@docker.co | E191: Zhel Petrov | F191: Contributor (via group: Security Team) | G191: Group | H191: No | L191: NO
A192: docker.co | B192: Subscription | C192: Sandbox | D192: zhelyazko.petrov@docker.co | E192: Zhel Petrov | F192: Owner (via group: Security Team) | G192: Group | H192: No | L192: NO
A193: docker.co | B193: Subscription | C193: Security | D193: zhelyazko.petrov@docker.co | E193: Zhel Petrov | F193: Owner (via group: Security Team) | G193: Group | H193: No | L193: NO
A194: docker.co | B194: Subscription | C194: Sustaining Engineering Team | D194: zhelyazko.petrov@docker.co | E194: Zhel Petrov | F194: Owner (via group: Security Team) | G194: Group | H194: No | L194: NO
A195: docker.co | B195: Subscription | C195: Sustaining Engineering Team | D195: zhelyazko.petrov@docker.co | E195: Zhel Petrov | F195: Contributor (via group: Security Team) | G195: Group | H195: No | L195: NO
A196: docker.co | B196: Subscription | C196: Visual Studio Enterprise Subscription – MPN | D196: zhelyazko.petrov@docker.co | E196: Zhel Petrov | F196: Contributor (via group: Security Team) | G196: Group | H196: No | L196: NO
A197: docker.co | B197: Subscription | C197: Visual Studio Enterprise Subscription – MPN | D197: zhelyazko.petrov@docker.co | E197: Zhel Petrov | F197: Owner (via group: Security Team) | G197: Group | H197: No | L197: NO
A198: docker.com | B198: Subscription | C198: Docker Azure Marketplace | D198: zhelyazko.petrov@docker.com | E198: Zhel Petrov | F198: Contributor (via group: Security Team) | G198: Group | H198: No | L198: NO
A199: docker.com | B199: Subscription | C199: Docker CI | D199: zhelyazko.petrov@docker.com | E199: Zhel Petrov | F199: Owner (via group: Security Team) | G199: Group | H199: No | L199: NO
A200: docker.com | B200: Subscription | C200: Docker CI | D200: zhelyazko.petrov@docker.com | E200: Zhel Petrov | F200: Contributor (via group: Security Team) | G200: Group | H200: No | L200: NO
... A211: docker.com | B211: Subscription | C211: Testcontainers | D211: zhelyazko.petrov@docker.com | E211: Zhel Petrov | F211: Contributor (via group: Security Team) | G211: Group | H211: No | L211: NO
A212: docker.co | B212: Subscription | C212: IAM Team | D212: akhilesh.yarabarla@docker.co | E212: Akhilesh | F212: Contributor (via group: IAM Team) | G212: Group | H212: Yes | L212: =VLOOKUP(D212,'Active Employees'!$B$2:$B$498,1,false) -> #N/A
A213: docker.co | B213: Subscription | C213: IAM Team | D213: akhilesh.yarabarla@docker.co | E213: Akhilesh | F213: User Access Administrator (via group: IAM Team) | G213: Group | H213: Yes | L213: =VLOOKUP(D213,'Active Employees'!$B$2:$B$498,1,false) -> #N/A
A214: docker.co | B214: Subscription | C214: Engineering Partnership Test | D214: alex.hokanson@docker.co | E214: Alex | F214: Owner (via group: Infra Team) | G214: Group | H214: Yes | L214: =VLOOKUP(D214,'Active Employees'!$B$2:$B$498,1,false) -> #N/A
A215: docker.co | B215: Subscription | C215: Sandbox | D215: alex.hokanson@docker.co | E215: Alex | F215: Owner (via group: Infra Team) | G215: Group | H215: Yes | L215: =VLOOKUP(D215,'Active Employees'!$B$2:$B$498,1,false) -> #N/A
A216: docker.co | B216: Subscription | C216: Sustaining Engineering Team | D216: alex.hokanson@docker.co | E216: Alex | F216: Owner (via group: Infra Team) | G216: Group | H216: Yes | L216: =VLOOKUP(D216,'Active Employees'!$B$2:$B$498,1,false) -> #N/A
A217: docker.co | B217: Subscription | C217: Sustaining Engineering Team | D217: alex.hokanson@docker.co | E217: Alex | F217: Owner | G217: Direct | H217: Yes | L217: =VLOOKUP(D217,'Active Employees'!$B$2:$B$498,1,false) -> #N/A
A218: docker.co | B218: Subscription | C218: Visual Studio Enterprise Subscription – MPN | D218: alex.hokanson@docker.co | E218: Alex | F218: Owner (via group: Infra Team) | G218: Group | H218: Yes | L218: =VLOOKUP(D218,'Active Employees'!$B$2:$B$498,1,false) -> #N/A
A219: docker.com | B219: Azure AD Directory | C219: Directory-level | D219: alex.hokanson@docker.com | E219: Alex | F219: Global Administrator (via group: Infrastructure Team) | G219: Group | H219: Yes | L219: =VLOOKUP(D219,'Active Employees'!$B$2:$B$498,1,false) -> alex.hokanson@docker.com
A220: docker.com | B220: Subscription | C220: Docker AI Agent | D220: alex.hokanson@docker.com | E220: Alex | F220: User Access Administrator | G220: Direct | H220: Yes | L220: =VLOOKUP(D220,'Active Employees'!$B$2:$B$498,1,false) -> alex.hokanson@docker.com
A221: docker.com | B221: Subscription | C221: Docker AI Runtime | D221: alex.hokanson@docker.com | E221: Alex | F221: User Access Administrator | G221: Direct | H221: Yes | L221: =VLOOKUP(D221,'Active Employees'!$B$2:$B$498,1,false) -> alex.hokanson@docker.com
A222: docker.com | B222: Subscription | C222: Docker Azure Marketplace | D222: alex.hokanson@docker.com | E222: Alex | F222: Owner (via group: Infra) | G222: Group | H222: Yes | L222: =VLOOKUP(D222,'Active Employees'!$B$2:$B$498,1,false) -> alex.hokanson@docker.com
A223: docker.com | B223: Subscription | C223: Docker Azure Marketplace | D223: alex.hokanson@docker.com | E223: Alex | F223: User Access Administrator | G223: Direct | H223: Yes | L223: =VLOOKUP(D223,'Active Employees'!$B$2:$B$498,1,false) -> alex.hokanson@docker.com
... A233: docker.com | B233: Subscription | C233: Play with Docker | D233: alex.hokanson@docker.com | E233: Alex | F233: Owner (via group: Infra) | G233: Group | H233: Yes | L233: =VLOOKUP(D233,'Active Employees'!$B$2:$B$498,1,false) -> alex.hokanson@docker.com
A234: docker.co | B234: Subscription | C234: Sandbox | D234: ServicePrincipal: TestServicePrincipal | E234: TestServicePrincipal | F234: Contributor | G234: Service Principal | L234: =VLOOKUP(D234,'Active Employees'!$B$2:$B$498,1,false) -> #N/A
A235: docker.com | B235: Subscription | C235: Play with Docker | D235: alex.hokanson@docker.com | E235: Alex | F235: Owner (via group: azure admins) | G235: Group | H235: Yes | L235: =VLOOKUP(D235,'Active Employees'!$B$2:$B$498,1,false) -> alex.hokanson@docker.com
A236: docker.com | B236: Subscription | C236: Play with Docker | D236: alex.hokanson@docker.com | E236: Alex | F236: User Access Administrator | G236: Direct | H236: Yes | L236: =VLOOKUP(D236,'Active Employees'!$B$2:$B$498,1,false) -> alex.hokanson@docker.com
A237: docker.com | B237: Subscription | C237: Security | D237: alex.hokanson@docker.com | E237: Alex | F237: User Access Administrator | G237: Direct | H237: Yes | L237: =VLOOKUP(D237,'Active Employees'!$B$2:$B$498,1,false) -> alex.hokanson@docker.com
A238: docker.com | B238: Subscription | C238: TC Engineering | D238: alex.hokanson@docker.com | E238: Alex | F238: Owner (via group: Infrastructure Team) | G238: Group | H238: Yes | L238: =VLOOKUP(D238,'Active Employees'!$B$2:$B$498,1,false) -> alex.hokanson@docker.com
A239: docker.com | B239: Subscription | C239: TC Engineering | D239: alex.hokanson@docker.com | E239: Alex | F239: User Access Administrator | G239: Direct | H239: Yes | L239: =VLOOKUP(D239,'Active Employees'!$B$2:$B$498,1,false) -> alex.hokanson@docker.com
...

Sheet AWS
A1: account_id | B1: account_name | C1: permission_set | D1: user_name | E1: group_name | F1: Reviewed by: | G1: Downgraded Permissions or Removed (If disabled for 90+ days, please remove) | H1: Notes | I1: VLOOKUP | J1: Active Employee
A2: 10438487392 | B2: Docker Data Stage | C2: Administrators | D2: gabriela.georgieva@docker.com | E2: AWSSSO_Administrators | I2: =VLOOKUP(D2,'Active Employees'!$B$2:$B$498,1,false) -> #N/A | J2: No
A3: 47302296459 | B3: Docker Security Tooling Stage | C3: Administrators | D3: gabriela.georgieva@docker.com | E3: AWSSSO_Administrators | I3: =VLOOKUP(D3,'Active Employees'!$B$2:$B$498,1,false) -> #N/A | J3: No
A4: 58264503038 | B4: Docker Image Signing - Stage | C4: Administrators | D4: gabriela.georgieva@docker.com | E4: AWSSSO_Administrators | I4: =VLOOKUP(D4,'Active Employees'!$B$2:$B$498,1,false) -> #N/A | J4: No
A5: 99407438094 | B5: Docker Platform Stage | C5: Administrators | D5: gabriela.georgieva@docker.com | E5: AWSSSO_Administrators | I5: =VLOOKUP(D5,'Active Employees'!$B$2:$B$498,1,false) -> #N/A | J5: No
A6: 111664719423 | B6: Docker Atomist | C6: Administrators | D6: gabriela.georgieva@docker.com | E6: AWSSSO_Administrators | I6: =VLOOKUP(D6,'Active Employees'!$B$2:$B$498,1,false) -> #N/A | J6: No
A7: 175142243308 | B7: Docker Sandbox | C7: Administrators | D7: gabriela.georgieva@docker.com | E7: AWSSSO_Administrators | I7: =VLOOKUP(D7,'Active Employees'!$B$2:$B$498,1,false) -> #N/A | J7: No
A8: 267155176707 | B8: Docker Security | C8: Administrators | D8: gabriela.georgieva@docker.com | E8: AWSSSO_Administrators | I8: =VLOOKUP(D8,'Active Employees'!$B$2:$B$498,1,false) -> #N/A | J8: No
A9: 277603989202 | B9: Docker Harmonia Root | C9: Administrators | D9: gabriela.georgieva@docker.com | E9: AWSSSO_Administrators | I9: =VLOOKUP(D9,'Active Employees'!$B$2:$B$498,1,false) -> #N/A | J9: No
A10: 300042230143 | B10: Docker Offload Customer Workloads - TIAA | C10: Administrators | D10: gabriela.georgieva@docker.com | E10: AWSSSO_Administrators | I10: =VLOOKUP(D10,'Active Employees'!$B$2:$B$498,1,false) -> #N/A | J10: No
A11: 303700122550 | B11: Docker Hub Stage | C11: Administrators | D11: gabriela.georgieva@docker.com | E11: AWSSSO_Administrators | I11: =VLOOKUP(D11,'Active Employees'!$B$2:$B$498,1,false) -> #N/A | J11: No
A12: 313121495448 | B12: Docker AtomicJar Control Plane | C12: Administrators | D12: gabriela.georgieva@docker.com | E12: AWSSSO_Administrators | I12: =VLOOKUP(D12,'Active Employees'!$B$2:$B$498,1,false) -> #N/A | J12: No
A13: 318510287843 | B13: Docker AtomicJar Business Workloads | C13: Administrators | D13: gabriela.georgieva@docker.com | E13: AWSSSO_Administrators | I13: =VLOOKUP(D13,'Active Employees'!$B$2:$B$498,1,false) -> #N/A | J13: No
... A577: 991137750147 | B577: Docker AWS Marketplace | C577: Administrators | D577: stefan.scherer@docker.com | E577: AWSSSO_Administrators | I577: =VLOOKUP(D577,'Active Employees'!$B$2:$B$498,1,false) -> stefan.scherer@docker.com | J577: Yes

Sheet GCP
A1: Email | B1: Scope Type | C1: Scope Name | D1: Scope ID | E1: Roles | F1: Assignment Type | G1: VLOOKUP | H1: Active Employee | I1: Notes | J1: Downgraded Permissions or Removed (If disabled for 90+ days, please remove)
A2: eddu@atomicjar.com | B2: Project | C2: Testcontainers OSS | D2: testcontainers-oss | E2: roles/owner | F2: Direct | G2: =VLOOKUP(A2,'Active Employees'!$B$2:$B$498,1,false) -> #N/A | H2: ? | I2: eddu.melendez@docker.com?
A3: kevin@atomicjar.com | B3: Project | C3: Testcontainers OSS | D3: testcontainers-oss | E3: roles/owner | F3: Direct | G3: =VLOOKUP(A3,'Active Employees'!$B$2:$B$498,1,false) -> #N/A | H3: ?
A4: brett.inman@docker.com | B4: Project | C4: docker-looker | D4: docker-looker | E4: roles/owner | F4: Direct | G4: =VLOOKUP(A4,'Active Employees'!$B$2:$B$498,1,false) -> #N/A | H4: No
A5: brett.inman@docker.com | B5: Project | C5: Ask Docker | D5: ask-docker | E5: roles/owner | F5: Direct | G5: =VLOOKUP(A5,'Active Employees'!$B$2:$B$498,1,false) -> #N/A | H5: No
A6: brett.inman@docker.com | B6: Project | C6: Dear Moby Extension | D6: dear-moby-extension | E6: roles/owner | F6: Direct | G6: =VLOOKUP(A6,'Active Employees'!$B$2:$B$498,1,false) -> #N/A | H6: No
A7: brett.inman@docker.com | B7: Project | C7: 1Password SCIM Bridge | D7: password-scim-bridge-360620 | E7: roles/owner | F7: Direct | G7: =VLOOKUP(A7,'Active Employees'!$B$2:$B$498,1,false) -> #N/A | H7: No
A8: brett.inman@docker.com | B8: Project | C8: FeatureFlags | D8: deep-lore-323516 | E8: roles/owner | F8: Direct | G8: =VLOOKUP(A8,'Active Employees'!$B$2:$B$498,1,false) -> #N/A | H8: No
A9: brett.inman@docker.com | B9: Project | C9: On-call automation | D9: mikes-on-call-automation | E9: roles/owner | F9: Direct | G9: =VLOOKUP(A9,'Active Employees'!$B$2:$B$498,1,false) -> #N/A | H9: No
A10: brett.inman@docker.com | B10: Project | C10: docker-oauth2proxy | D10: docker-oauth2proxy | E10: roles/owner | F10: Direct | G10: =VLOOKUP(A10,'Active Employees'!$B$2:$B$498,1,false) -> #N/A | H10: No
A11: brett.inman@docker.com | B11: Project | C11: cloudfront-bq | D11: cloudfront-bq | E11: roles/owner | F11: Direct | G11: =VLOOKUP(A11,'Active Employees'!$B$2:$B$498,1,false) -> #N/A | H11: No
A12: bryan.short@docker.com | B12: Project | C12: roadMapDiffGenerator | D12: roadmapdiffgenerator | E12: roles/owner | F12: Direct | G12: =VLOOKUP(A12,'Active Employees'!$B$2:$B$498,1,false) -> #N/A | H12: No
A13: colin.mcneil@docker.com | B13: Project | C13: Ask Docker | D13: ask-docker | E13: roles/bigquery.admin | F13: Direct | G13: =VLOOKUP(A13,'Active Employees'!$B$2:$B$498,1,false) -> #N/A | H13: No
A14: gianluca.brindisi@docker.com | B14: Project | C14: InfoSec Internal Apps | D14: infosec-internal-apps | E14: roles/owner | F14: Direct | G14: =VLOOKUP(A14,'Active Employees'!$B$2:$B$498,1,false) -> #N/A | H14: No
... A29: skalable.tech@docker.com | B29: Project | C29: My First Project | D29: manifest-campus-349917 | E29: roles/owner | F29: Direct | G29: =VLOOKUP(A29,'Active Employees'!$B$2:$B$498,1,false) -> #N/A | H29: No
A30: svc-google-pather-alerting@docker.com | B30: Project | C30: Panther Integration | D30: panther-integration-376501 | E30: roles/owner | F30: Direct | G30: =VLOOKUP(A30,'Active Employees'!$B$2:$B$498,1,false) -> #N/A | H30: No | I30: Assignment type mislabeled? Should be Service Account
A31: svc-midasbot@docker.com | B31: Project | C31: data-team | D31: data-team-231118 | E31: roles/editor | F31: Direct | G31: =VLOOKUP(A31,'Active Employees'!$B$2:$B$498,1,false) -> #N/A | H31: No | I31: Assignment type mislabeled? Should be Service Account
A32: tackle-service-gcp@tackle.io | B32: Project | C32: docker-public | D32: docker-public-445216 | E32: roles/owner | F32: Direct | G32: =VLOOKUP(A32,'Active Employees'!$B$2:$B$498,1,false) -> #N/A | H32: No | I32: Assignment type mislabeled? Should be Service Account
A33: thomas.psyhogeos@docker.com | B33: Project | C33: My First Project | D33: rare-gate-377301 | E33: roles/owner | F33: Direct | G33: =VLOOKUP(A33,'Active Employees'!$B$2:$B$498,1,false) -> #N/A | H33: No
A34: thomas.psyhogeos@docker.com | B34: Project | C34: k8sproject | D34: k8sproject-378311 | E34: roles/editor | F34: Direct | G34: =VLOOKUP(A34,'Active Employees'!$B$2:$B$498,1,false) -> #N/A | H34: No
A35: thomas.psyhogeos@docker.com | B35: Project | C35: My First Project | D35: emerald-vent-378714 | E35: roles/owner | F35: Direct | G35: =VLOOKUP(A35,'Active Employees'!$B$2:$B$498,1,false) -> #N/A | H35: No
A36: victor.bersy@docker.com | B36: Project | C36: Runtime Team | D36: runtime-team | E36: roles/owner | F36: Direct | G36: =VLOOKUP(A36,'Active Employees'!$B$2:$B$498,1,false) -> #N/A | H36: No
A37: zhelyazko.petrov@docker.com | B37: Project | C37: InfoSec Internal Apps | D37: infosec-internal-apps | E37: roles/owner | F37: Direct | G37: =VLOOKUP(A37,'Active Employees'!$B$2:$B$498,1,false) -> zhelyazko.petrov@docker.com | H37: No
A38: zhelyazko.petrov@docker.com | B38: Project | C38: Tines-GoogleSheet Integration | D38: valid-moment-385016 | E38: roles/owner | F38: Direct | G38: =VLOOKUP(A38,'Active Employees'!$B$2:$B$498,1,false) -> zhelyazko.petrov@docker.com | H38: No
A39: zhelyazko.petrov@docker.com | B39: Project | C39: Panther Integration | D39: panther-integration-376501 | E39: roles/owner | F39: Direct | G39: =VLOOKUP(A39,'Active Employees'!$B$2:$B$498,1,false) -> zhelyazko.petrov@docker.com | H39: No
A40: adm-brent_seaton@docker.com | B40: Project | C40: Chorus | D40: chorus-464720 | E40: roles/owner | F40: Direct | G40: =VLOOKUP(A40,'Active Employees'!$B$2:$B$498,1,false) -> #N/A | H40: Yes
A41: adm-brent_seaton@docker.com | B41: Project | C41: GAM Project | D41: gam-project-lmr3q | E41: roles/owner | F41: Direct | G41: =VLOOKUP(A41,'Active Employees'!$B$2:$B$498,1,false) -> #N/A | H41: Yes
A42: adm-brent_seaton@docker.com | B42: Project | C42: GAM Project | D42: gam-project-xb6-drw-v6z | E42: roles/owner | F42: Direct | G42: =VLOOKUP(A42,'Active Employees'!$B$2:$B$498,1,false) -> #N/A | H42: Yes
A43: ajeet_raina@docker.com | B43: Project | C43: Meetup-Demo | D43: meetup-demo-384606 | E43: roles/owner | F43: Direct | G43: =VLOOKUP(A43,'Active Employees'!$B$2:$B$498,1,false) -> #N/A | H43: Yes
A44: jamie_newell@docker.com | B44: Project | C44: Web Recaptcha | D44: web-recaptcha-396022 | E44: roles/editor | F44: Direct | G44: =VLOOKUP(A44,'Active Employees'!$B$2:$B$498,1,false) -> #N/A | H44: Yes
A45: alex.hokanson@docker.com | B45: Organization | C45: Organization 756105189467 | D45: 756105189467 | E45: roles/resourcemanager.organizationAdmin | F45: Direct | G45: =VLOOKUP(A45,'Active Employees'!$B$2:$B$498,1,false) -> alex.hokanson@docker.com | H45: Yes
A46: david.dooling@docker.com | B46: Organization | C46: Organization 756105189467 | D46: 756105189467 | E46: roles/resourcemanager.organizationAdmin | F46: Direct | G46: =VLOOKUP(A46,'Active Employees'!$B$2:$B$498,1,false) -> david.dooling@docker.com | H46: Yes
A47: james.braden@docker.com | B47: Organization | C47: Organization 756105189467 | D47: 756105189467 | E47: roles/resourcemanager.organizationAdmin | F47: Direct | G47: =VLOOKUP(A47,'Active Employees'!$B$2:$B$498,1,false) -> james.braden@docker.com | H47: Yes
A48: jeffrey.strauss@docker.com | B48: Organization | C48: Organization 756105189467 | D48: 756105189467 | E48: roles/billing.admin; roles/orgpolicy.policyAdmin; roles/resourcemanager.organizationAdmin; roles/resourcemanager.projectCreator; roles/resourcemanager.projectDeleter; roles/resourcemanager.projectMover | F48: Direct | G48: =VLOOKUP(A48,'Active Employees'!$B$2:$B$498,1,false) -> jeffrey.strauss@docker.com | H48: Yes
A49: robert.lorimer@docker.com | B49: Organization | C49: Organization 756105189467 | D49: 756105189467 | E49: roles/orgpolicy.policyAdmin; roles/resourcemanager.organizationAdmin | F49: Direct | G49: =VLOOKUP(A49,'Active Employees'!$B$2:$B$498,1,false) -> Robert.Lorimer@docker.com | H49: Yes
A50: shawn.shakir@docker.com | B50: Organization | C50: Organization 756105189467 | D50: 756105189467 | E50: roles/orgpolicy.policyAdmin; roles/resourcemanager.projectCreator | F50: Direct | G50: =VLOOKUP(A50,'Active Employees'!$B$2:$B$498,1,false) -> shawn.shakir@docker.com | H50: Yes
A51: abhi.singh@docker.com | B51: Project | C51: My First Project | D51: neon-glyph-389219 | E51: roles/owner | F51: Direct | G51: =VLOOKUP(A51,'Active Employees'!$B$2:$B$498,1,false) -> abhi.singh@docker.com | H51: Yes
A52: adm-daniel.schultz@docker.com | B52: Project | C52: Calm GCP Project | D52: calm-gcp-project | E52: roles/owner; roles/storage.admin | F52: Direct | G52: =VLOOKUP(A52,'Active Employees'!$B$2:$B$498,1,false) -> #N/A | H52: Yes
A53: adm-daniel.schultz@docker.com | B53: Project | C53: GAM Project | D53: gam-project-aa9-i1u-0ab | E53: roles/owner | F53: Direct | G53: =VLOOKUP(A53,'Active Employees'!$B$2:$B$498,1,false) -> #N/A | H53: Yes
A54: adm-daniel.schultz@docker.com | B54: Project | C54: GAM Project | D54: gam-project-xb6-drw-v6z | E54: roles/owner | F54: Direct | G54: =VLOOKUP(A54,'Active Employees'!$B$2:$B$498,1,false) -> #N/A | H54: Yes
A55: adm-fiona.mcshane@docker.com | B55: Project | C55: GAM Project | D55: gam-project-44xz9 | E55: roles/owner | F55: Direct | G55: =VLOOKUP(A55,'Active Employees'!$B$2:$B$498,1,false) -> #N/A | H55: Yes
A56: adm-fiona.mcshane@docker.com | B56: Project | C56: GAM Project | D56: gam-project-xb6-drw-v6z | E56: roles/owner | F56: Direct | G56: =VLOOKUP(A56,'Active Employees'!$B$2:$B$498,1,false) -> #N/A | H56: Yes
A57: adm-jeffrey.strauss@docker.com | B57: Project | C57: GAM Project | D57: gam-project-8ck8h | E57: roles/owner | F57: Direct | G57: =VLOOKUP(A57,'Active Employees'!$B$2:$B$498,1,false) -> #N/A | H57: Yes
A58: adm-jeffrey.strauss@docker.com | B58: Project | C58: GAM Project | D58: gam-project-zw0to | E58: roles/owner | F58: Direct | G58: =VLOOKUP(A58,'Active Employees'!$B$2:$B$498,1,false) -> #N/A | H58: Yes
A59: adm-jeffrey.strauss@docker.com | B59: Project | C59: GAM Project | D59: gam-project-aa9-i1u-0ab | E59: roles/owner | F59: Direct | G59: =VLOOKUP(A59,'Active Employees'!$B$2:$B$498,1,false) -> #N/A | H59: Yes
A60: adm-shawn.shakir@docker.com | B60: Project | C60: GAM Project | D60: gam-project-as6bu | E60: roles/owner | F60: Direct | G60: =VLOOKUP(A60,'Active Employees'!$B$2:$B$498,1,false) -> #N/A | H60: Yes
A61: adm-shawn.shakir@docker.com | B61: Project | C61: GAM Project | D61: gam-project-aa9-i1u-0ab | E61: roles/owner | F61: Direct | G61: =VLOOKUP(A61,'Active Employees'!$B$2:$B$498,1,false) -> #N/A | H61: Yes
A62: alano.terblanche@docker.com | B62: Project | C62: MCP catalog | D62: mcp-catalog | E62: roles/owner | F62: Direct | G62: =VLOOKUP(A62,'Active Employees'!$B$2:$B$498,1,false) -> alano.terblanche@docker.com | H62: Yes
... A181: zubair.aslam@docker.com | B181: Project | C181: Zubair Aslam Test Area | D181: zubair-aslam | E181: roles/editor | F181: Direct | G181: =VLOOKUP(A181,'Active Employees'!$B$2:$B$498,1,false) -> zubair.aslam@docker.com | H181: Yes
A182: 1066536109736@cloudservices.gserviceaccount.com | B182: Project | C182: Testcontainers Cloud | D182: testcontainers-cloud | E182: roles/editor | F182: Service Account | G182: =VLOOKUP(A182,'Active Employees'!$B$2:$B$498,1,false) -> #N/A
A183: 1072588105150-compute@developer.gserviceaccount.com | B183: Project | C183: k8sproject | D183: k8sproject-378311 | E183: roles/editor | F183: Service Account | G183: =VLOOKUP(A183,'Active Employees'!$B$2:$B$498,1,false) -> #N/A
A184: 1072588105150@cloudservices.gserviceaccount.com | B184: Project | C184: k8sproject | D184: k8sproject-378311 | E184: roles/editor | F184: Service Account | G184: =VLOOKUP(A184,'Active Employees'!$B$2:$B$498,1,false) -> #N/A
A185: 13492051104-compute@developer.gserviceaccount.com | B185: Project | C185: Gemini API | D185: gen-lang-client-0862120673 | E185: roles/editor | F185: Service Account | G185: =VLOOKUP(A185,'Active Employees'!$B$2:$B$498,1,false) -> #N/A
A186: 13492051104@cloudservices.gserviceaccount.com | B186: Project | C186: Gemini API | D186: gen-lang-client-0862120673 | E186: roles/editor | F186: Service Account | G186: =VLOOKUP(A186,'Active Employees'!$B$2:$B$498,1,false) -> #N/A
A187: 272326217981-compute@developer.gserviceaccount.com | B187: Project | C187: Testcontainers OSS | D187: testcontainers-oss | E187: roles/editor | F187: Service Account | G187: =VLOOKUP(A187,'Active Employees'!$B$2:$B$498,1,false) -> #N/A
A188: 272326217981@cloudservices.gserviceaccount.com | B188: Project | C188: Testcontainers OSS | D188: testcontainers-oss | E188: roles/editor | F188: Service Account | G188: =VLOOKUP(A188,'Active Employees'!$B$2:$B$498,1,false) -> #N/A
A189: 38528517963-compute@developer.gserviceaccount.com | B189: Project | C189: Ask Docker | D189: ask-docker | E189: roles/editor | F189: Service Account | G189: =VLOOKUP(A189,'Active Employees'!$B$2:$B$498,1,false) -> #N/A
A190: 417679349889-compute@developer.gserviceaccount.com | B190: Project | C190: solutions-engineering-sandbox | D190: starlit-tube-469623-d9 | E190: roles/editor | F190: Service Account | G190: =VLOOKUP(A190,'Active Employees'!$B$2:$B$498,1,false) -> #N/A
A191: 417679349889@cloudservices.gserviceaccount.com | B191: Project | C191: solutions-engineering-sandbox | D191: starlit-tube-469623-d9 | E191: roles/editor | F191: Service Account | G191: =VLOOKUP(A191,'Active Employees'!$B$2:$B$498,1,false) -> #N/A
A192: 422840896494-compute@developer.gserviceaccount.com | B192: Project | C192: My First Project | D192: emerald-vent-378714 | E192: roles/editor | F192: Service Account | G192: =VLOOKUP(A192,'Active Employees'!$B$2:$B$498,1,false) -> #N/A
A193: 422840896494@cloudservices.gserviceaccount.com | B193: Project | C193: My First Project | D193: emerald-vent-378714 | E193: roles/editor | F193: Service Account | G193: =VLOOKUP(A193,'Active Employees'!$B$2:$B$498,1,false) -> #N/A
... A374: appsdev-apps-dev-script-auth@system.gserviceaccount.com | B374: Project | C374: Untitled project | D374: sys-43539474321069783626178174 | E374: roles/owner | F374: Service Account | G374: =VLOOKUP(A374,'Active Employees'!$B$2:$B$498,1,false) -> #N/A
A375: appsdev-apps-dev-script-auth@system.gserviceaccount.com | B375: Project | D375: sys-89908322711946970061938814 | E375: roles/owner | F375: Service Account | G375: =VLOOKUP(A375,'Active Employees'!$B$2:$B$498,1,false) -> #N/A
A376: appsdev-apps-dev-script-auth@system.gserviceaccount.com | B376: Project | C376: Reservation Emails | D376: sys-06134653404251229123085814 | E376: roles/owner | F376: Service Account | G376: =VLOOKUP(A376,'Active Employees'!$B$2:$B$498,1,false) -> #N/A
A377: appsdev-apps-dev-script-auth@system.gserviceaccount.com | B377: Project | D377: sys-20846423928355354415275475 | E377: roles/owner | F377: Service Account | G377: =VLOOKUP(A377,'Active Employees'!$B$2:$B$498,1,false) -> #N/A
A378: appsdev-apps-dev-script-auth@system.gserviceaccount.com | B378: Project | C378: Untitled project | D378: sys-86134309057875427972517767 | E378: roles/owner | F378: Service Account | G378: =VLOOKUP(A378,'Active Employees'!$B$2:$B$498,1,false) -> #N/A
A379: appsdev-apps-dev-script-auth@system.gserviceaccount.com | B379: Project | C379: Untitled project | D379: sys-75628296083107153827366492 | E379: roles/owner | F379: Service Account | G379: =VLOOKUP(A379,'Active Employees'!$B$2:$B$498,1,false) -> #N/A
A380: appsdev-apps-dev-script-auth@system.gserviceaccount.com | B380: Project | C380: JD Tracker | D380: sys-80161256023802310844426905 | E380: roles/owner | F380: Service Account | G380: =VLOOKUP(A380,'Active Employees'!$B$2:$B$498,1,false) -> #N/A
A381: appsdev-apps-dev-script-auth@system.gserviceaccount.com | B381: Project | C381: Untitled project | D381: sys-23765565915876843212913930 | E381: roles/owner | F381: Service Account | G381: =VLOOKUP(A381,'Active Employees'!$B$2:$B$498,1,false) -> #N/A
A382: appsdev-apps-dev-script-auth@system.gserviceaccount.com | B382: Project | C382: Untitled project | D382: sys-42748469733347604827714146 | E382: roles/owner | F382: Service Account | G382: =VLOOKUP(A382,'Active Employees'!$B$2:$B$498,1,false) -> #N/A
A383: appsdev-apps-dev-script-auth@system.gserviceaccount.com | B383: Project | C383: Untitled project | D383: sys-08825497024699912003505704 | E383: roles/owner | F383: Service Account | G383: =VLOOKUP(A383,'Active Employees'!$B$2:$B$498,1,false) -> #N/A
A384: appsdev-apps-dev-script-auth@system.gserviceaccount.com | B384: Project | C384: Translate Google Slide | D384: sys-93840625291777242498761191 | E384: roles/owner | F384: Service Account | G384: =VLOOKUP(A384,'Active Employees'!$B$2:$B$498,1,false) -> #N/A
A385: appsdev-apps-dev-script-auth@system.gserviceaccount.com | B385: Project | C385: Time Log | D385: sys-21637435975740282463269241 | E385: roles/owner | F385: Service Account | G385: =VLOOKUP(A385,'Active Employees'!$B$2:$B$498,1,false) -> #N/A
A386: appsdev-apps-dev-script-auth@system.gserviceaccount.com | B386: Project | C386: Recorded Macros HUB User Acco | D386: sys-72948360590671475843490465 | E386: roles/owner | F386: Service Account | G386: =VLOOKUP(A386,'Active Employees'!$B$2:$B$498,1,false) -> #N/A
A387: appsdev-apps-dev-script-auth@system.gserviceaccount.com | B387: Project | C387: Recorded Macros Untitled spre | D387: sys-91542278601827473357600958 | E387: roles/owner | F387: Service Account | G387: =VLOOKUP(A387,'Active Employees'!$B$2:$B$498,1,false) -> #N/A
A388: appsdev-apps-dev-script-auth@system.gserviceaccount.com | B388: Project | C388: Recorded Macros Untitled spre | D388: sys-88753073374609140480862170 | E388: roles/owner | F388: Service Account | G388: =VLOOKUP(A388,'Active Employees'!$B$2:$B$498,1,false) -> #N/A
A389: appsdev-apps-dev-script-auth@system.gserviceaccount.com | B389: Project | C389: Recorded Macros Federal Reser | D389: sys-42241545074940557731154818 | E389: roles/owner | F389: Service Account | G389: =VLOOKUP(A389,'Active Employees'!$B$2:$B$498,1,false) -> #N/A
... A750: zoompersonalmeetingidspreadshe@gam-project-xb6-drw-v6z.iam.gserviceaccount.com | B750: Project | C750: GAM Project | D750: gam-project-xb6-drw-v6z | E750: roles/editor | F750: Service Account | G750: =VLOOKUP(A750,'Active Employees'!$B$2:$B$498,1,false) -> #N/A

Sheet Looker
A1: User Name | B1: User Email | C1: User Is Disabled (Yes / No) | D1: Is Active Employee | E1: User Created Date | F1: Last UI Login Date | G1: User Role Role List | H1: Notes
A2: Team Extensions Service Account | B2: guillaume.tardif+looker_service@docker.com | C2: No | D2: =COUNTIF('Active Employees'!B:B, B2) > 0 -> FALSE | E2: 44888 | F2: 1 | G2: Docker for Desktops Read Only,Gemini,Universal Viewer | H2: Login with API
A3: Looker Panther Service User | B3: panther-looker-integration@docker.com | C3: No | D3: =COUNTIF('Active Employees'!B:B, B3) > 0 -> FALSE | E3: 45113 | F3: 1 | G3: Gemini,Panther Logs Integration,Universal Viewer | H3: Login with API
A4: 0 | B4: svc-coefficient@docker.com | C4: No | D4: =COUNTIF('Active Employees'!B:B, B4) > 0 -> FALSE | E4: 45187 | F4: 1 | G4: Finance User,Gemini,Marketing SalesOps User,Product User | H4: Login with API | I4: Employees flag as FALSE are mostly external consultants
A5: Exit Script Service Account | B5: svc-exit-script+looker@docker.com | C5: No | D5: =COUNTIF('Active Employees'!B:B, B5) > 0 -> FALSE | E5: 45173 | F5: 1 | G5: Admin,Gemini,Universal Viewer | H5: Login with API
A6: Anecdotes User | B6: svc-infosec+anecdotes@docker.com | C6: No | D6: =COUNTIF('Active Employees'!B:B, B6) > 0 -> FALSE | E6: 45036 | F6: 1 | G6: Anecdotes Integration Role,Gemini,Universal Viewer | H6: Login with API
B7: temp_hackathon_service@docker.com | C7: No | D7: =COUNTIF('Active Employees'!B:B, B7) > 0 -> FALSE | E7: 45258 | F7: 1 | G7: Core Monitor User,Gemini,Universal Viewer | H7: Login with API
A8: Skalable Tech | B8: skalable.tech@docker.com | C8: No | D8: =COUNTIF('Active Employees'!B:B, B8) > 0 -> FALSE | E8: 44782 | F8: 44797 | G8: Gemini,ProductivRole,Universal Viewer
A9: Skalable Tech | B9: skalable.tech@docker.com | C9: No | D9: =COUNTIF('Active Employees'!B:B, B9) > 0 -> FALSE | E9: 44707 | F9: 45463 | G9: Gemini,ProductivRole,Universal Viewer
A10: JT Ibe | B10: jt.ibe@docker.com | C10: No | D10: =COUNTIF('Active Employees'!B:B, B10) > 0 -> FALSE | E10: 45027 | F10: 45480 | G10: Gemini,Universal Viewer
A11: Amn Rahman | B11: amn.rahman@docker.com | C11: No | D11: =COUNTIF('Active Employees'!B:B, B11) > 0 -> TRUE | E11: 43032 | F11: 45488 | G11: Admin,Central Data Dev,Central Data User,Core Monitor Dev,Core Monitor User,Gemini,Universal Viewer
A12: Luke Sowinski | B12: luke.sowinski@docker.com | C12: No | D12: =COUNTIF('Active Employees'!B:B, B12) > 0 -> TRUE | E12: 45519 | F12: 45520 | G12: Gemini,Universal Viewer
A13: Paweł Gronowski | B13: pawel.gronowski@docker.com | C13: No | D13: =COUNTIF('Active Employees'!B:B, B13) > 0 -> TRUE | E13: 45538 | F13: 45538 | G13: Gemini,Product User,Universal Viewer
A14: Jamie Newell | B14: jamie_newell@docker.com | C14: No | D14: =COUNTIF('Active Employees'!B:B, B14) > 0 -> FALSE | E14: 45544 | F14: 45544 | G14: Gemini,Universal Viewer
A15: Laurent Goderre | B15: laurent.goderre@docker.com | C15: No | D15: =COUNTIF('Active Employees'!B:B, B15) > 0 -> TRUE | E15: 45182 | F15: 45554 | G15: Gemini,Universal Viewer
A16: Derek McGowan | B16: derek.mcgowan@docker.com | C16: No | D16: =COUNTIF('Active Employees'!B:B, B16) > 0 -> TRUE | E16: 41962 | F16: 45575 | G16: Gemini,Product User
A17: Mahesan Param | B17: mahesan_param@docker.com | C17: No | D17: =COUNTIF('Active Employees'!B:B, B17) > 0 -> FALSE | E17: 45600 | F17: 45600 | G17: Gemini,Universal Viewer
A18: Nicole Tiu | B18: nicole_tiu@docker.com | C18: No | D18: =COUNTIF('Active Employees'!B:B, B18) > 0 -> FALSE | E18: 45600 | F18: 45601 | G18: Gemini,Universal Viewer
A19: Gabriele Di Bernardo | B19: gabriele.dibernardo@docker.com | C19: No | D19: =COUNTIF('Active Employees'!B:B, B19) > 0 -> TRUE | E19: 45300 | F19: 45617 | G19: Gemini,Universal Viewer
... A422: Yifeng Tek | B422: yifeng_tek@docker.com | C422: No | D422: =COUNTIF('Active Employees'!B:B, B422) > 0 -> FALSE | E422: 45600 | F422: 45933 | G422: Finance User,Gemini,Hub User,Marketing SalesOps Dev,Product Dev,Product User,Universal Viewer

Sheet Looker Admin
A1: Name | B1: Email | C1: Is Disabled (Yes / No) | D1: Role List | E1: Created Date | F1: Last Attempted UI Login Date | G1: Notes
A2: Exit Script Service Account | B2: svc-exit-script+looker@docker.com | C2: No | D2: Admin,Gemini,Universal Viewer | E2: 45173 | F2: 1 | G2: Login using API
A3: Amn Rahman | B3: amn.rahman@docker.com | C3: No | D3: Admin,Central Data Dev,Central Data User,Core Monitor Dev,Core Monitor User,Gemini,Universal Viewer | E3: 43032 | F3: 45488
A4: Ola Prokhorova | B4: oleksandra.prokhorova@docker.com | C4: No | D4: Admin,Central Data Dev,Gemini,Universal Viewer | E4: 45723 | F4: 45803
A5: Data Engineering | B5: data-engineering-team@docker.com | C5: No | D5: Admin,Core Monitor User,Gemini,Universal Viewer | E5: 45315 | F5: 45805
A6: Motoki Nakamura | B6: motoki.nakamura@docker.com | C6: No | D6: Admin,Central Data User,Core Monitor Dev,Core Monitor User,Gemini,Universal Viewer | E6: 44726 | F6: 45903
A7: Dave Morris | B7: dave.morris@docker.com | C7: No | D7: Admin,Gemini,Product User,Universal Viewer | E7: 45912 | F7: 45912
A8: Mike Kacherovich | B8: mikhail.kacherovich@docker.com | C8: No | D8: Admin,Central Data User,Core Monitor User,Finance User,Gemini,Marketing SalesOps User,Product User,Universal Viewer,User Plus System Activity | E8: 45212 | F8: 45913
A9: Tatia Markland | B9: tatia.markland@docker.com | C9: No | D9: Admin,Gemini,Universal Viewer | E9: 45609 | F9: 45917
A10: Merinne Mesku | B10: merinne.mesku@docker.com | C10: No | D10: Admin,Central Data Dev,Finance Dev,Gemini,Marketing SalesOps Dev,Product Dev,Universal Viewer | E10: 45527 | F10: 45922
A11: Nicola Watson | B11: nicola.watson@docker.com | C11: No | D11: Admin,Central Data Dev,Core Monitor Dev,DVP Dev,Finance User,Gemini,Marketing SalesOps User,Product Dev,Universal Viewer,User Plus System Activity | E11: 45062 | F11: 45926
A12: Dragos Georgescu | B12: dragos.georgescu@docker.com | C12: No | D12: Admin,Finance User,Gemini,Marketing SalesOps User,Product User,Universal Viewer | E12: 45482 | F12: 45929
A13: Paco Valverde | B13: paco.valverde@docker.com | C13: No | D13: Admin,Gemini,Hub User | E13: 44482 | F13: 45930
A14: Rob Burigo | B14: robert.burigo@docker.com | C14: No | D14: Admin,Central Data Dev,Finance Dev,Gemini,Marketing SalesOps Dev,Product Dev,Universal Viewer | E14: 45636 | F14: 45930
... A20: Abhi Singh | B20: abhi.singh@docker.com | C20: No | D20: Admin,Central Data Dev,Gemini,Universal Viewer | E20: 44782 | F20: 45933

Sheet Snowflake
A1: NAME | B1: EMAIL | C1: OWNER | D1: DEFAULT_ROLE | E1: ALL_ROLES | F1: LAST_SUCCESS_LOGIN | G1: Should Downgrade | H1: Should Delete | I1: Active Employee | J1: Notes | K1: Downgraded Permissions or Removed (If disabled for 90+ days, please remove)
A2: BHAGWINDER_PHUL | B2: bhagwinder.phul@docker.com | C2: USERADMIN | D2: PRODUCT_ANALYST | E2: PRODUCT_ANALYST | H2: Y | I2: =IF(COUNTIF('Active Employees'!B:B, B2)>0,"Y","N") -> Y | J2: Never logged in
A3: BRYAN_ENGLISH | B3: bryan.english@docker.com | C3: USERADMIN | D3: DOCKER_DESKTOP_READONLY | E3: DOCKER_DESKTOP_READONLY | H3: Y | I3: =IF(COUNTIF('Active Employees'!B:B, B3)>0,"Y","N") -> N | J3: Never logged in
A4: CHRIS_MCLELLAN | B4: chris.mclellan@docker.com | C4: USERADMIN | D4: PRODUCT_ANALYST | E4: PRODUCT_ANALYST | H4: Y | I4: =IF(COUNTIF('Active Employees'!B:B, B4)>0,"Y","N") -> Y | J4: Never logged in
A5: EDDU_MELENDEZ | B5: eddu.melendez@docker.com | C5: USERADMIN | D5: PRODUCTION_HUB_READONLY | E5: PRODUCTION_HUB_READONLY | H5: Y | I5: =IF(COUNTIF('Active Employees'!B:B, B5)>0,"Y","N") -> Y | J5: Never logged in
A6: JARRIS_WILKINS | B6: jarris.wilkins@docker.com | C6: SECURITYADMIN | D6: DOCKER_DEFAULT_READONLY | E6: DOCKER_DEFAULT_READONLY | H6: Y | I6: =IF(COUNTIF('Active Employees'!B:B, B6)>0,"Y","N") -> Y | J6: Never logged in
A7: JEAN_LAURENT | B7: jeanlaurent@docker.com | C7: ACCOUNTADMIN | D7: DOCKER_DEFAULT_READONLY | E7: DOCKER_DEFAULT_READONLY | H7: Y | I7: =IF(COUNTIF('Active Employees'!B:B, B7)>0,"Y","N") -> Y | J7: Never logged in
A8: JEFF_CARTER | B8: jeff.carter@docker.com | C8: USERADMIN | D8: PRODUCT_ANALYST | E8: PRODUCT_ANALYST | H8: Y | I8: =IF(COUNTIF('Active Employees'!B:B, B8)>0,"Y","N") -> Y | J8: Never logged in
A9: JONATHAN_STERNBERG | B9: jonathan.sternberg@docker.com | C9: USERADMIN | D9: DOCKER_DESKTOP_READONLY | E9: DOCKER_DESKTOP_READONLY | H9: Y | I9: =IF(COUNTIF('Active Employees'!B:B, B9)>0,"Y","N") -> Y | J9: Never logged in
A10: JOSH_NEWMAN | B10: josh.newman@docker.com | C10: USERADMIN | D10: DOCKER_DEFAULT_READONLY | E10: DOCKER_DEFAULT_READONLY | H10: Y | I10: =IF(COUNTIF('Active Employees'!B:B, B10)>0,"Y","N") -> Y | J10: Never logged in
A11: KATERINA_TOMRUSHKA | B11: katerina.tomrushka@docker.com | C11: USERADMIN | D11: PRODUCT_ANALYST | E11: PRODUCT_ANALYST | H11: Y | I11: =IF(COUNTIF('Active Employees'!B:B, B11)>0,"Y","N") -> Y | J11: Never logged in
A12: CHRIS_AINSWORTH | B12: chris.ainsworth-patrick@docker.com | C12: USERADMIN | D12: SALESOPS_ADMIN | E12: DOCKER_DEFAULT_READONLY, DVP_ADMIN, SALESOPS_ADMIN | F12: 2024-10-03 09:50:28.298 -0400 | I12: =IF(COUNTIF('Active Employees'!B:B, B12)>0,"Y","N") -> Y | J12: Login > 90 days ago
A13: OZAIR_ASIM | B13: ozair.asim@docker.com | C13: USERADMIN | D13: DOCKER_DEFAULT_READONLY | E13: DOCKER_DEFAULT_READONLY | F13: 2024-11-06 08:33:30.277 -0500 | I13: =IF(COUNTIF('Active Employees'!B:B, B13)>0,"Y","N") -> Y | J13: Login > 90 days ago
A14: JAMES_CHILDS | B14: james.childs@docker.com | C14: USERADMIN | D14: DOCKER_DEFAULT_READONLY | E14: BILLING_UNIFIED_CONSUMPTION, DOCKER_DEFAULT_READONLY | F14: 2024-11-12 13:29:07.112 -0500 | I14: =IF(COUNTIF('Active Employees'!B:B, B14)>0,"Y","N") -> Y | J14: Login > 90 days ago
A15: CHONGGHEE_LEE | B15: chongghee_lee@docker.com | C15: USERADMIN | D15: MARKETING_READONLY | E15: MARKETING_READONLY | F15: 2024-11-14 21:28:37.866 -0500 | H15: N | I15: =IF(COUNTIF('Active Employees'!B:B, B15)>0,"Y","N") -> N | J15: External consultant
A16: MISAEL_MOURA | B16: misael_moura@docker.com | C16: USERADMIN | D16: SF_NEOCOL_TEMP_ROLE | E16: SF_NEOCOL_TEMP_ROLE | F16: 2024-11-16 14:39:10.212 -0500 | H16: N | I16: =IF(COUNTIF('Active Employees'!B:B, B16)>0,"Y","N") -> N | J16: External consultant
A17: KAMARIAH_SAIFUL | B17: kamariah_saiful@docker.com | C17: USERADMIN | D17: MARKETING_READONLY | E17: MARKETING_READONLY | F17: 2024-11-17 20:30:05.937 -0500 | H17: N | I17: =IF(COUNTIF('Active Employees'!B:B, B17)>0,"Y","N") -> N | J17: External consultant
A18: IGNACIO_LOPEZLUNA | B18: ignacio.lopezluna@docker.com | C18: USERADMIN | D18: DOCKER_POWER_USER_READONLY | E18: DOCKER_DEFAULT_READONLY, DOCKER_POWER_USER_READONLY, TEST_CONTAINERS_READONLY | F18: 2024-12-18 09:19:54.428 -0500 | I18: =IF(COUNTIF('Active Employees'!B:B, B18)>0,"Y","N") -> Y | J18: Login > 90 days ago
A19: OLEG | B19: oleg.burov@docker.com | C19: USERADMIN | D19: DOCKER_DEFAULT_READONLY | E19: BILLING_UNIFIED_CONSUMPTION, DOCKER_DEFAULT_READONLY | F19: 2025-01-16 17:39:35.769 -0500 | I19: =IF(COUNTIF('Active Employees'!B:B, B19)>0,"Y","N") -> Y | J19: Login > 90 days ago
A20: BRYAN_CHAN | B20: bryan_chan@docker.com | C20: USERADMIN | D20: MARKETING_READONLY | E20: MARKETING_READONLY | F20: 2025-01-17 13:33:43.650 -0500 | H20: N | I20: =IF(COUNTIF('Active Employees'!B:B, B20)>0,"Y","N") -> N | J20: External consultant
A21: NICHOLAS_OREFICE | B21: nicholas.orefice@docker.com | C21: USERADMIN | D21: DOCKER_DEFAULT_READONLY | E21: DOCKER_DEFAULT_READONLY, SEGMENT_DESKTOP_READONLY | F21: 2025-01-17 15:05:27.527 -0500 | I21: =IF(COUNTIF('Active Employees'!B:B, B21)>0,"Y","N") -> Y | J21: Login > 90 days ago
A22: GABRIELE_DIBERNARDO | B22: gabriele.dibernardo@docker.com | C22: USERADMIN | D22: ARCHIVE_EVENTS_READONLY | E22: ARCHIVE_EVENTS_READONLY | F22: 2025-01-28 09:53:53.856 -0500 | I22: =IF(COUNTIF('Active Employees'!B:B, B22)>0,"Y","N") -> Y | J22: Login > 90 days ago
A23: JUSTIN_CORMACK | B23: justin.cormack@docker.com | C23: USERADMIN | D23: PRODUCT_ANALYST | E23: PRODUCT_ANALYST | F23: 2025-02-03 06:43:39.909 -0500 | H23: Y | I23: =IF(COUNTIF('Active Employees'!B:B, B23)>0,"Y","N") -> N | J23: Former employee
A24: SHAUN_THOMPSON | B24: shaun.thompson@docker.com | C24: USERADMIN | D24: DOCKER_POWER_USER_READONLY | E24: DOCKER_DEFAULT_READONLY, DOCKER_POWER_USER_READONLY | F24: 2025-02-10 16:22:39.661 -0500 | I24: =IF(COUNTIF('Active Employees'!B:B, B24)>0,"Y","N") -> Y | J24: Login > 90 days ago
A25: NICK_ADCOCK | B25: nick.adcock@docker.com | C25: USERADMIN | D25: DOCKER_DEFAULT_READONLY | E25: DOCKER_DEFAULT_READONLY | F25: 2025-02-24 12:22:25.380 -0500 | I25: =IF(COUNTIF('Active Employees'!B:B, B25)>0,"Y","N") -> Y | J25: Login > 90 days ago
A26: NICOLAS_DELOOF | B26: nicolas.deloof@docker.com | C26: USERADMIN | D26: SEGMENT_DESKTOP_READONLY | E26: SEGMENT_DESKTOP_READONLY | F26: 2025-02-26 04:55:57.617 -0500 | I26: =IF(COUNTIF('Active Employees'!B:B, B26)>0,"Y","N") -> Y | J26: Login > 90 days ago
A27: GEORGE_GABOLAEV | B27: georgii.gabolaev@docker.com | C27: SECURITYADMIN | D27: SEGMENT_DESKTOP_READONLY | E27: SEGMENT_DESKTOP_READONLY | F27: 2025-03-11 08:30:26.704 -0400 | I27: =IF(COUNTIF('Active Employees'!B:B, B27)>0,"Y","N") -> Y | J27: Login > 90 days ago
A28: DORIN_GEMAN | B28: dorin.geman@docker.com | C28: USERADMIN | D28: PRODUCT_ENGINEER_READONLY | E28: DOCKER_DESKTOP_READONLY, PRODUCT_ENGINEER__READONLY | F28: 2025-03-11 09:04:38.555 -0400 | I28: =IF(COUNTIF('Active Employees'!B:B, B28)>0,"Y","N") -> Y | J28: Login > 90 days ago
A29: AJITH_THILAKAN | B29: ajith.thilakan@docker.com | C29: USERADMIN | D29: DOCKER_DEFAULT_READONLY | E29: DOCKER_DEFAULT_READONLY | F29: 2025-03-16 22:07:18.085 -0400 | I29: =IF(COUNTIF('Active Employees'!B:B, B29)>0,"Y","N") -> Y | J29: Login > 90 days ago
A30: ALBERTO_GARCIA_HIERRO | B30: damaso.hierro@docker.com | C30: USERADMIN | D30: DOCKER_DEFAULT_READONLY | E30: DOCKER_DEFAULT_READONLY | F30: 2025-03-19 11:59:05.968 -0400 | I30: =IF(COUNTIF('Active Employees'!B:B, B30)>0,"Y","N") -> Y | J30: Login > 90 days ago
A31: MAT_WILSON | B31: mat.wilson@docker.com | C31: USERADMIN | D31: DOCKER_DEFAULT_READONLY | E31: DOCKER_DEFAULT_READONLY | F31: 2025-03-20 07:42:05.490 -0400 | I31: =IF(COUNTIF('Active Employees'!B:B, B31)>0,"Y","N") -> Y | J31: Login > 90 days ago
A32: JAVIER_GARCIA | B32: javier.garcia@docker.com | C32: USERADMIN | D32: DOCKER_POWER_USER_READONLY | E32: DOCKER_POWER_USER_READONLY | F32: 2025-03-20 07:46:04.204 -0400 | I32: =IF(COUNTIF('Active Employees'!B:B, B32)>0,"Y","N") -> Y | J32: Login > 90 days ago
A33: EKATERINA_TUGARINOVA | B33: ekaterina.tugarinova@docker.com | C33: USERADMIN | D33: DOCKER_DEFAULT_AND_WORKSPACES_READONLY | E33: DOCKER_DEFAULT_AND_WORKSPACES_READONLY, DOCKER_DEFAULT_READONLY | F33: 2025-03-26 11:07:40.438 -0400 | I33: =IF(COUNTIF('Active Employees'!B:B, B33)>0,"Y","N") -> Y | J33: Login > 90 days ago
A34: IVAN_PEDRAZAS | B34: ivan.pedrazas@docker.com | C34: USERADMIN | D34: DOCKER_DESKTOP_READONLY | E34: DOCKER_DEFAULT_READONLY, DOCKER_DESKTOP_READONLY | F34: 2025-04-09 13:06:45.142 -0400 | I34: =IF(COUNTIF('Active Employees'!B:B, B34)>0,"Y","N") -> Y | J34: Login > 90 days ago
A35: KAVINDIRA_AMARENDIRAN | B35: kavindira.amarendiran@docker.com | C35: SECURITYADMIN | D35: PRODUCTION_DESKTOP_READONLY | E35: PRODUCTION_DESKTOP_READONLY | F35: 2025-04-10 01:42:45.036 -0400 | I35: =IF(COUNTIF('Active Employees'!B:B, B35)>0,"Y","N") -> Y | J35: Login > 90 days ago
... A47: VINCENT_DAMERY | B47: vincent.damery@docker.com | C47: USERADMIN | D47: DOCKER_DEFAULT_READONLY | E47: DOCKER_DEFAULT_READONLY | F47: 2025-06-27 12:30:12.095 -0400 | I47: =IF(COUNTIF('Active Employees'!B:B, B47)>0,"Y","N") -> Y | J47: Login > 90 days ago
A48: FRANCESCO_CORTI | B48: francesco.corti@docker.com | C48: USERADMIN | D48: DOCKER_DEFAULT_READONLY | E48: DOCKER_DEFAULT_READONLY, DOCKER_DESKTOP_READONLY | F48: 2025-07-02 11:35:32.711 -0400 | I48: =IF(COUNTIF('Active Employees'!B:B, B48)>0,"Y","N") -> Y
A49: LUKE_BUNSELMEYER | B49: william.bunselmeyer@docker.com | C49: USERADMIN | D49: DOCKER_DEFAULT_READONLY | E49: DOCKER_DEFAULT_READONLY, DOCKER_DESKTOP_READONLY | F49: 2025-07-07 11:23:07.849 -0400 | I49: =IF(COUNTIF('Active Employees'!B:B, B49)>0,"Y","N") -> Y
A50: LUCAS_BERNALTE | B50: lucas.bernalte@docker.com | C50: USERADMIN | D50: CONSUMPTION_HUB_EXPERIENCES_ROLE | E50: CONSUMPTION_HUB_EXPERIENCES_ROLE, DOCKER_DEFAULT_READONLY | F50: 2025-07-10 03:25:52.634 -0400 | I50: =IF(COUNTIF('Active Employees'!B:B, B50)>0,"Y","N") -> Y
A51: SHELTON_GRAVES | B51: shelton.graves@docker.com | C51: SECURITYADMIN | D51: DOCKER_DEFAULT_READONLY | E51: DOCKER_DEFAULT_READONLY | F51: 2025-07-10 13:49:17.004 -0400 | I51: =IF(COUNTIF('Active Employees'!B:B, B51)>0,"Y","N") -> Y
A52: ALANO_TERBLANCHE | B52: alano.terblanche@docker.com | C52: USERADMIN | D52: SEGMENT_DESKTOP_READONLY | E52: DOCKER_DEFAULT_READONLY, SEGMENT_DESKTOP_READONLY | F52: 2025-07-14 09:17:31.886 -0400 | I52: =IF(COUNTIF('Active Employees'!B:B, B52)>0,"Y","N") -> Y
A53: BRENT_PATERSON | B53: brent.paterson@docker.com | C53: USERADMIN | D53: DOCKER_DEFAULT_READONLY | E53: CONSUMPTION_BILLING, DOCKER_DEFAULT_READONLY | F53: 2025-07-15 15:14:20.400 -0400 | I53: =IF(COUNTIF('Active Employees'!B:B, B53)>0,"Y","N") -> Y
A54: MARK_CAVAGE | B54: mark.cavage@docker.com | C54: USERADMIN | D54: DOCKER_DEFAULT_READONLY | E54: DOCKER_DEFAULT_READONLY | F54: 2025-07-17 05:23:08.794 -0400 | I54: =IF(COUNTIF('Active Employees'!B:B, B54)>0,"Y","N") -> Y
A55: GUILLAUME_LOURS | B55: guillaume.lours@docker.com | C55: USERADMIN | D55: SYSADMIN | E55: DOCKER_DEFAULT_READONLY, DOCKER_POWER_USER_READONLY | F55: 2025-07-18 06:05:35.289 -0400 | I55: =IF(COUNTIF('Active Employees'!B:B, B55)>0,"Y","N") -> Y
A56: ANNA_CHERNYSHOVA | B56: anna.chernyshova@docker.com | C56: ACCOUNTADMIN | D56: DOCKER_DEFAULT_READONLY | E56: DOCKER_DEFAULT_READONLY, SEGMENT_DESKTOP_READONLY | F56: 2025-07-25 10:36:53.070 -0400 | I56: =IF(COUNTIF('Active Employees'!B:B, B56)>0,"Y","N") -> Y
A57: ZHELYAZKO_PETROV | B57: zhelyazko.petrov@docker.com | C57: USERADMIN | D57: SNOWFLAKE_READONLY | E57: INFOSEC, SNOWFLAKE_READONLY | F57: 2025-07-29 10:53:11.420 -0400 | I57: =IF(COUNTIF('Active Employees'!B:B, B57)>0,"Y","N") -> Y
A58: MARIANA_SIMON | B58: mariana.simon@docker.com | C58: USERADMIN | D58: DOCKER_DEFAULT_READONLY | E58: DOCKER_DEFAULT_READONLY, DOCKER_DESKTOP_READONLY | F58: 2025-07-31 16:29:39.503 -0400 | I58: =IF(COUNTIF('Active Employees'!B:B, B58)>0,"Y","N") -> Y
A59: JAIME_LOZANO@DOCKER.COM | B59: jaime_lozano@docker.com | C59: OKTA_PROVISIONER | F59: 2025-08-13 18:00:54.009 -0400 | H59: N | I59: =IF(COUNTIF('Active Employees'!B:B, B59)>0,"Y","N") -> N | J59: External consultant
A60: POOJA.AGRAWAL@DOCKER.COM | B60: pooja.agrawal@docker.com | C60: OKTA_PROVISIONER | D60: DOCKER_DEFAULT_READONLY | E60: DOCKER_DEFAULT_READONLY | F60: 2025-08-26 16:07:13.794 -0400 | I60: =IF(COUNTIF('Active Employees'!B:B, B60)>0,"Y","N") -> Y
A61: ZOEY_KRAMER | B61: zoey.kramer@docker.com | C61: USERADMIN | D61: PRODUCT_ANALYST | E61: PRODUCT_ANALYST | F61: 2025-08-27 10:38:21.290 -0400 | I61: =IF(COUNTIF('Active Employees'!B:B, B61)>0,"Y","N") -> Y
A62: SYLVIA.FAVELLO@DOCKER.COM | B62: sylvia.favello@docker.com | C62: OKTA_PROVISIONER | E62: CONSUMPTION_BILLING | F62: 2025-09-02 18:13:16.515 -0400 | I62: =IF(COUNTIF('Active Employees'!B:B, B62)>0,"Y","N") -> Y
A63: JIM_CLARK | B63: jim.clark@docker.com | C63: ACCOUNTADMIN | D63: DOCKER_DEFAULT_READONLY | E63: DOCKER_DEFAULT_READONLY | F63: 2025-09-03 18:59:21.812 -0400 | I63: =IF(COUNTIF('Active Employees'!B:B, B63)>0,"Y","N") -> Y
A64: HASYIR_HASHIM | B64: hasyir_hashim@docker.com | C64: USERADMIN | D64: MARKETING_READONLY | E64: MARKETING_READONLY | F64: 2025-09-03 23:07:45.824 -0400 | H64: N | I64: =IF(COUNTIF('Active Employees'!B:B, B64)>0,"Y","N") -> N | J64: External consultant
A65: CATHERINE_BENDEBURY | B65: catherine.bendebury@docker.com | C65: USERADMIN | D65: DOCKER_DEFAULT_READONLY | E65: DOCKER_DEFAULT_READONLY, MCP_SERVICE_ACCOUNT_TEMP | F65: 2025-09-09 18:11:11.813 -0400 | I65: =IF(COUNTIF('Active Employees'!B:B, B65)>0,"Y","N") -> Y
A66: BENJAMIN_GRANDFOND | B66: benjamin.grandfond@docker.com | C66: USERADMIN | D66: DVP_ADMIN | E66: CONSUMPTION_HUB_EXPERIENCES_ROLE, DVP_ADMIN, IMAGE_CATEGORIZATION_DEV, SALESOPS_ADMIN | F66: 2025-09-10 04:28:47.319 -0400 | I66: =IF(COUNTIF('Active Employees'!B:B, B66)>0,"Y","N") -> Y
A67: BOBBY_HOUSE | B67: robert.house@docker.com | C67: USERADMIN | D67: DOCKER_DEFAULT_READONLY | E67: DOCKER_DEFAULT_READONLY | F67: 2025-09-11 09:51:26.938 -0400 | I67: =IF(COUNTIF('Active Employees'!B:B, B67)>0,"Y","N") -> Y
A68: RICK_REDONDO | B68: rick.redondo@docker.com | C68: USERADMIN | D68: DOCKER_POWER_USER_READONLY | E68: DOCKER_POWER_USER_READONLY, PRODUCT_ENGINEER__READONLY | F68: 2025-09-11 11:17:34.583 -0400 | I68: =IF(COUNTIF('Active Employees'!B:B, B68)>0,"Y","N") -> Y
A69: KELLY_FREET | B69: kelly.freet@docker.com | C69: USERADMIN | D69: DOCKER_DEFAULT_READONLY | E69: BILLING_UNIFIED_CONSUMPTION, CONSUMPTION_BILLING, DOCKER_DEFAULT_READONLY | F69: 2025-09-12 15:33:01.743 -0400 | I69: =IF(COUNTIF('Active Employees'!B:B, B69)>0,"Y","N") -> Y
A70: REMY_SUEN | B70: remy.suen@docker.com | C70: USERADMIN | D70: PRODUCT_ENGINEER__READONLY | E70: DOCKER_DEFAULT_READONLY, DOCKER_DESKTOP_READONLY, PRODUCT_ENGINEER__READONLY | F70: 2025-09-15 14:05:49.107 -0400 | I70: =IF(COUNTIF('Active Employees'!B:B, B70)>0,"Y","N") -> Y
A71: MATT.LANDIS@DOCKER.COM | B71: matt.landis@docker.com | C71: OKTA_PROVISIONER | E71: DOCKER_DEFAULT_READONLY, DOCKER_DESKTOP_READONLY | F71: 2025-09-15 14:34:27.013 -0400 | I71: =IF(COUNTIF('Active Employees'!B:B, B71)>0,"Y","N") -> Y
A72: JOHANNES_GROSSMANN | B72: johannes.grossmann@docker.com | C72: USERADMIN | D72: segment_readonly | E72: DOCKER_POWER_USER_READONLY | F72: 2025-09-16 04:29:02.285 -0400 | I72: =IF(COUNTIF('Active Employees'!B:B, B72)>0,"Y","N") -> Y
A73: EDWARD_HARRISON | B73: edward.harrison@docker.com | C73: USERADMIN | D73: MARKETING_DEV | E73: AI_DEV, MARKETING_DEV, MLOPS_DEV | F73: 2025-09-17 15:16:23.563 -0400 | I73: =IF(COUNTIF('Active Employees'!B:B, B73)>0,"Y","N") -> Y
A74: ALICE_FINIDORI | B74: alice.finidori@docker.com | C74: USERADMIN | D74: ENGINEERING_DEV | E74: ACCOUNTADMIN, ENGINEERING_ADMIN, ENGINEERING_DEV, SECURITYADMIN, SYSADMIN | F74: 2025-09-19 06:30:26.615 -0400 | H74: Y | I74: =IF(COUNTIF('Active Employees'!B:B, B74)>0,"Y","N") -> N | J74: Former employee
A75: LUKE.SOWINSKI@DOCKER.COM | B75: luke.sowinski@docker.com | C75: OKTA_PROVISIONER | D75: DOCKER_POWER_USER_READONLY | E75: DOCKER_POWER_USER_READONLY | F75: 2025-09-19 10:35:53.954 -0400 | I75: =IF(COUNTIF('Active Employees'!B:B, B75)>0,"Y","N") -> Y
A76: SHAWN_AXSOM | B76: shawn.axsom@docker.com | C76: USERADMIN | D76: DOCKER_DEFAULT_READONLY | E76: DOCKER_DEFAULT_READONLY | F76: 2025-09-19 16:29:49.783 -0400 | I76: =IF(COUNTIF('Active Employees'!B:B, B76)>0,"Y","N") -> Y
A77: COLIN_HEMMINGS | B77: colin.hemmings@docker.com | C77: USERADMIN | D77: DOCKER_POWER_USER_READONLY | E77: DOCKER_DEFAULT_READONLY, DOCKER_POWER_USER_READONLY, PRODUCT_ENGINEER__READONLY | F77: 2025-09-23 05:21:56.616 -0400 | I77: =IF(COUNTIF('Active Employees'!B:B, B77)>0,"Y","N") -> Y
A78: TRAVIS_ROTH | B78: travis.roth@docker.com | C78: USERADMIN | D78: DOCKER_DEFAULT_READONLY | E78: DOCKER_DEFAULT_READONLY, DOCKER_DEFAULT_SALES_READONLY | F78: 2025-09-23 16:01:27.956 -0400 | I78: =IF(COUNTIF('Active Employees'!B:B, B78)>0,"Y","N") -> Y
A79: KEVIN_WITTEK | B79: kevin.wittek@docker.com | C79: SECURITYADMIN | D79: PRODUCT_ANALYST | E79: DOCKER_DESKTOP_READONLY, PRODUCT_ANALYST | F79: 2025-09-25 09:41:08.708 -0400 | I79: =IF(COUNTIF('Active Employees'!B:B, B79)>0,"Y","N") -> Y
A80: ASHLEY.PALARDY@DOCKER.COM | B80: ashley.palardy@docker.com | C80: OKTA_PROVISIONER | D80: PEOPLE_OPS | E80: PEOPLE_OPS | F80: 2025-09-25 10:22:33.032 -0400 | I80: =IF(COUNTIF('Active Employees'!B:B, B80)>0,"Y","N") -> Y
A81: DRAGOS_GEORGESCU | B81: dragos.georgescu@docker.com | C81: USERADMIN | D81: PRODUCT_ANALYST | E81: PRODUCT_ANALYST, SF_INTELLIGENCE_ADMIN, SNOWFLAKE_INTELLIGENCE_DEV | F81: 2025-09-25 11:31:52.794 -0400 | I81: =IF(COUNTIF('Active Employees'!B:B, B81)>0,"Y","N") -> Y
A82: JORDAN_GANOFF | B82: jordan.ganoff@docker.com | C82: USERADMIN | D82: ENGINEERING_DEV | E82: ACCOUNTADMIN, DBT, DOCKER_POWER_USER_READONLY | F82: 2025-09-25 12:33:05.370 -0400 | I82: =IF(COUNTIF('Active Employees'!B:B, B82)>0,"Y","N") -> Y
A83: AKHILESH_YARABARLA | B83: akhilesh.yarabarla@docker.com | C83: USERADMIN | D83: INSIGHTS_DEV | E83: INSIGHTS_DEV, INSIGHTS_SANDBOX_DEV, TEAM_CORE_EXPERIENCES | F83: 2025-09-25 13:57:08.029 -0400 | I83: =IF(COUNTIF('Active Employees'!B:B, B83)>0,"Y","N") -> Y
A84: SUSAN.NETH@DOCKER.COM | B84: susan.neth@docker.com | C84: OKTA_PROVISIONER | D84: PRODUCT_ENGINEER__READONLY | E84: PRODUCT_ANALYST, PRODUCT_ENGINEER__READONLY | F84: 2025-09-25 15:42:04.825 -0400 | I84: =IF(COUNTIF('Active Employees'!B:B, B84)>0,"Y","N") -> Y
A85: STEVEN_NOVICK | B85: steven.novick@docker.com | C85: USERADMIN | D85: PRODUCT_ANALYST | E85: DOCKER_DESKTOP_READONLY, PRODUCT_ANALYST | F85: 2025-09-25 18:51:50.702 -0400 | I85: =IF(COUNTIF('Active Employees'!B:B, B85)>0,"Y","N") -> Y
A86: KYLE.TRANTHAM@DOCKER.COM | B86: kyle.trantham@docker.com | C86: OKTA_PROVISIONER | D86: docker_default_readonly | E86: DOCKER_DEFAULT_READONLY | F86: 2025-09-26 12:38:08.192 -0400 | I86: =IF(COUNTIF('Active Employees'!B:B, B86)>0,"Y","N") -> Y
... A96: TATIA_MARKLAND | B96: tatia.markland@docker.com | C96: OKTA_PROVISIONER | D96: SF_INTELLIGENCE_ADMIN | E96: PRODUCT_ANALYST, SF_INTELLIGENCE_ADMIN | F96: 2025-10-01 18:05:22.592 -0400 | I96: =IF(COUNTIF('Active Employees'!B:B, B96)>0,"Y","N") -> Y
A97: YIFENG_TEK | B97: yifeng_tek@docker.com | C97: USERADMIN | D97: MARKETING_READONLY | E97: MARKETING_READONLY | F97: 2025-10-01 21:03:05.645 -0400 | H97: N | I97: =IF(COUNTIF('Active Employees'!B:B, B97)>0,"Y","N") -> N | J97: External consultant
A98: NICOLA_WATSON | B98: nicola.watson@docker.com | C98: USERADMIN | D98: PRODUCT_ANALYST | E98: DBT, PRODUCT_ANALYST | F98: 2025-10-02 02:41:20.705 -0400 | I98: =IF(COUNTIF('Active Employees'!B:B, B98)>0,"Y","N") -> Y
A99: ANDREI.ALBU@DOCKER.COM | B99: andrei.albu@docker.com | C99: OKTA_PROVISIONER | D99: DOCKER_DESKTOP_READONLY | E99: DOCKER_DEFAULT_READONLY, DOCKER_DESKTOP_READONLY | F99: 2025-10-02 04:03:33.997 -0400 | I99: =IF(COUNTIF('Active Employees'!B:B, B99)>0,"Y","N") -> Y
A100: ROB_BURIGO | B100: robert.burigo@docker.com | C100: OKTA_PROVISIONER | D100: PRODUCT_ANALYST | E100: PRODUCT_ANALYST | F100: 2025-10-02 09:31:20.092 -0400 | I100: =IF(COUNTIF('Active Employees'!B:B, B100)>0,"Y","N") -> Y
A101: MERINNE_MESKU | B101: merinne.mesku@docker.com | C101: USERADMIN | D101: PRODUCT_ANALYST | E101: PRODUCT_ANALYST | F101: 2025-10-02 10:00:03.026 -0400 | I101: =IF(COUNTIF('Active Employees'!B:B, B101)>0,"Y","N") -> Y
A102: OLEKSANDRA_PROKHOROVA | B102: oleksandra.prokhorova@docker.com | C102: OKTA_PROVISIONER | D102: ENGINEERING_DEV | E102: ACCOUNTADMIN, ENGINEERING_DEV, SYSADMIN | F102: 2025-10-02 10:18:26.415 -0400 | I102: =IF(COUNTIF('Active Employees'!B:B, B102)>0,"Y","N") -> Y
A103: MARK_MADONNA | B103: mark.madonna@docker.com | C103: USERADMIN | D103: SALESOPS_DEV | E103: SALESOPS_DEV | F103: 2025-10-02 11:11:14.368 -0400 | I103: =IF(COUNTIF('Active Employees'!B:B, B103)>0,"Y","N") -> Y
A104: BRIAN_PRATT | B104: brian.pratt@docker.com | C104: USERADMIN | D104: DOCKER_DEFAULT_READONLY | E104: DOCKER_DEFAULT_READONLY, SEGMENT_CLOUD_READONLY | F104: 2025-10-02 11:14:02.639 -0400 | I104: =IF(COUNTIF('Active Employees'!B:B, B104)>0,"Y","N") -> Y
A105: DANIEL_FRIEDMAN | B105: daniel.friedman@docker.com | C105: USERADMIN | D105: ENGINEERING_DEV | E105: ACCOUNTADMIN, BILLING_AND_COMPUTE_READONLY, COREDATA_ADMIN, COREDATA_DEV, DBT, ENGINEERING_ADMIN, ENGINEERING_DEV, SECURITYADMIN, SYSADMIN, USERADMIN | F105: 2025-10-02 11:55:35.981 -0400 | I105: =IF(COUNTIF('Active Employees'!B:B, B105)>0,"Y","N") -> Y
A106: NICK_SANTOS | B106: nick.santos@docker.com | C106: USERADMIN | D106: DOCKER_POWER_USER_READONLY | E106: DOCKER_POWER_USER_READONLY | F106: 2025-10-02 11:59:15.712 -0400 | I106: =IF(COUNTIF('Active Employees'!B:B, B106)>0,"Y","N") -> Y
A107: PACO_VALVERDE | B107: paco.valverde@docker.com | C107: USERADMIN | D107: SYSADMIN | E107: ACCOUNTADMIN, ADMIN_PIPES, AI_DEV, DEV_IDENTITY_GRAPH, DOCKER_DEFAULT_READONLY, DOCKER_DEV, DVP_READONLY, ENGINEERING_ADMIN, ENGINEERING_DEV, MLOPS_DEV, SALESOPS_ADMIN, SCOUT_DEVELOPER, SF_INTELLIGENCE_ADMIN | F107: 2025-10-02 12:06:02.769 -0400 | I107: =IF(COUNTIF('Active Employees'!B:B, B107)>0,"Y","N") -> Y
A108: ABHI_SINGH | B108: abhi.singh@docker.com | C108: USERADMIN | D108: PRODUCT_ANALYST | E108: DBT, PRODUCT_ANALYST | F108: 2025-10-02 12:55:50.918 -0400 | I108: =IF(COUNTIF('Active Employees'!B:B, B108)>0,"Y","N") -> Y
A109: WILL_BELL | B109: will.bell@DOCKER.COM | C109: USERADMIN | D109: PRODUCT_ANALYST | E109: PRODUCT_ANALYST, SALESOPS_DEV | F109: 2025-10-02 13:00:27.927 -0400 | I109: =IF(COUNTIF('Active Employees'!B:B, B109)>0,"Y","N") -> Y
... A116: SUHAIB_AHMED | B116: suhaib.ahmed@docker.com | C116: USERADMIN | D116: MARKETING_ADMIN | E116: AI_DEV, MARKETING_ADMIN, MARKETING_DEV, MLOPS_DEV, SALESOPS_DEV | F116: 2025-10-02 16:05:06.579 -0400 | I116: =IF(COUNTIF('Active Employees'!B:B, B116)>0,"Y","N") -> Y
A117: AMN | B117: amn.rahman@docker.com | C117: USERADMIN | D117: ENGINEERING_DEV | E117: ACCOUNTADMIN, COREDATA_ADMIN, COREDATA_DEV, ENGINEERING_DEV, ORGADMIN, SYSADMIN | I117: =IF(COUNTIF('Active Employees'!B:B, B117)>0,"Y","N") -> Y | J117: Amn
A118: CHRISTIAN_KREIS | B118: christian_kreis@docker.com | C118: USERADMIN | D118: PUBLIC | H118: N | I118: =IF(COUNTIF('Active Employees'!B:B, B118)>0,"Y","N") -> N | J118: Former employee
A119: EMILY.CASEY@DOCKER.COM | B119: emily.casey@docker.com | C119: OKTA_PROVISIONER | E119: DOCKER_DEFAULT_READONLY, DOCKER_DESKTOP_READONLY | H119: Y | I119: =IF(COUNTIF('Active Employees'!B:B, B119)>0,"Y","N") -> Y | J119: Never logged in
A120: GUILLAUME_STPIERRE | B120: guillaume.stpierre@docker.com | C120: USERADMIN | D120: INSIGHTS_DEV | E120: INSIGHTS_DEV, TEAM_CORE_EXPERIENCES | H120: Y | I120: =IF(COUNTIF('Active Employees'!B:B, B120)>0,"Y","N") -> Y | J120: Never logged in
A121: JEANPHILIPPE_BRIEND | B121: jeanphilippe.briend@docker.com | C121: SECURITYADMIN | D121: PRODUCT_ENGINEER__READONLY | H121: Y | I121: =IF(COUNTIF('Active Employees'!B:B, B121)>0,"Y","N") -> Y | J121: Never logged in
A122: MALARVANNAN_VELU@DOCKER.COM | B122: malarvannan_velu@docker.com | C122: OKTA_PROVISIONER | H122: Y | I122: =IF(COUNTIF('Active Employees'!B:B, B122)>0,"Y","N") -> N | J122: Former employee
A123: MASON.GRAYE@DOCKER.COM | B123: mason.graye@docker.com | C123: OKTA_PROVISIONER | H123: Y | I123: =IF(COUNTIF('Active Employees'!B:B, B123)>0,"Y","N") -> Y | J123: Never logged in
A124: NICK.CHRISTOU@DOCKER.COM | B124: nick.christou@docker.com | C124: OKTA_PROVISIONER | H124: Y | I124: =IF(COUNTIF('Active Employees'!B:B, B124)>0,"Y","N") -> Y | J124: Never logged in
A125: SNOWFLAKE | B125: snowflake | H125: N | I125: =IF(COUNTIF('Active Employees'!B:B, B125)>0,"Y","N") -> N | J125: Snowflake
A126: XINLU_LIU | B126: xinlu_liu@docker.com | C126: USERADMIN | D126: PUBLIC | H126: Y | I126: =IF(COUNTIF('Active Employees'!B:B, B126)>0,"Y","N") -> N | J126: Former employee

Sheet Snowflake - SVC
A1: NAME | B1: TYPE | C1: OWNER | D1: DEFAULT_ROLE | E1: ALL_ROLES | F1: LAST_SUCCESS_LOGIN | G1: Should Delete | H1: Notes | I1: Downgraded Permissions or Removed (If disabled for 90+ days, please remove)
A2: AIRFLOW_SALESOPS_DEV | B2: SERVICE | C2: USERADMIN | D2: AIRFLOW_SALESOPS | E2: AIRFLOW_SALESOPS | G2: Y | H2: Never Used
A3: DEV_IDENTITY_GRAPH_USER | B3: SERVICE | C3: USERADMIN | D3: DEV_IDENTITY_GRAPH | E3: DEV_IDENTITY_GRAPH | F3: 2025-06-18 10:51:40.351 -0400
A4: AIRFLOW_MONITOR_USER_DEV | B4: SERVICE | C4: USERADMIN | E4: ACCOUNT_MONITOR | F4: 2025-07-07 17:03:59.627 -0400
A5: CONSUMPTION_MONITOR_USER | B5: LEGACY_SERVICE | C5: USERADMIN | D5: CONSUMPTION_MONITOR | E5: CONSUMPTION_MONITOR | F5: 2025-07-09 06:00:30.416 -0400
A6: PIGMENT_USER | B6: SERVICE | C6: USERADMIN | D6: PIGMENT | E6: PIGMENT | F6: 2025-07-09 14:32:39.949 -0400
A7: AIRFLOW_INFOSEC_EXPORT_DEV_USER | B7: SERVICE | C7: USERADMIN | D7: INFOSEC_EXPORT_DEV | E7: INFOSEC_EXPORT_DEV | F7: 2025-07-10 20:36:30.985 -0400
A8: CONSUMPTION_MONITOR_USER_PROD | B8: LEGACY_SERVICE | C8: USERADMIN | D8: CONSUMPTION_MONITOR_PROD | E8: CONSUMPTION_MONITOR_PROD | F8: 2025-07-14 06:00:30.699 -0400
A9: AIRFLOW_EVENTS_ADMIN_USER_DEV | B9: SERVICE | C9: USERADMIN | D9: EVENTS_ADMIN_STAGING | E9: EVENTS_ADMIN_STAGING | F9: 2025-07-21 11:00:03.074 -0400
A10: LOOKER_BAMBOOHR | B10: SERVICE | C10: SECURITYADMIN | D10: BAMBOOHR_READONLY | E10: BAMBOOHR_READONLY | F10: 2025-07-30 04:57:58.228 -0400
A11: LOOKER_PREVIEW_USER | B11: SERVICE | C11: USERADMIN | D11: LOOKER_PREVIEW_READONLY_ROLE | E11: LOOKER_PREVIEW_READONLY_ROLE, PRODUCTION_READ_ROLE | F11: 2025-07-30 06:53:51.879 -0400
A12: SNOWFLAKE_EXTENSIONS | B12: LEGACY_SERVICE | C12: USERADMIN | D12: SNOWFLAKE_EXTENSIONS_ADMIN | E12: SNOWFLAKE_EXTENSIONS_ADMIN | F12: 2025-08-11 03:53:55.481 -0400
A13: DBT_DEV_DEPLOYMENT_WORKSPACES_USER | B13: LEGACY_SERVICE | C13: USERADMIN | E13: DBT_DEPLOYMENTS_WORKSPACES | F13: 2025-08-12 15:00:10.909 -0400
A14: AIRFLOW_DVPP_USER_DEV | B14: LEGACY_SERVICE | C14: USERADMIN | D14: DVPP_STAGING | E14: DVPP_STAGING | F14: 2025-09-17 13:21:59.979 -0400
A15: MULESOFT_USER | B15: LEGACY_SERVICE | C15: USERADMIN | D15: MULESOFT_WRITE_ROLE | E15: CONSUMPTION_BILLING, MULESOFT_SANDBOX_WRITE_ROLE, MULESOFT_WRITE_ROLE | F15: 2025-09-18 06:00:17.014 -0400
A16: AEP_SERVICE_ACCOUNT | B16: SERVICE | C16: SECURITYADMIN | D16: AEP_SERVICE_ROLE | E16: AEP_SERVICE_ROLE | F16: 2025-09-24 06:27:38.505 -0400
A17: STAGING_DVP_DBT_USER | B17: LEGACY_SERVICE | C17: USERADMIN | D17: STAGING_DBT_DVP_DEPLOYMENTS | E17: DVP_DEV, STAGING_DBT_DVP_DEPLOYMENTS | F17: 2025-09-24 10:02:28.490 -0400
A18: ZAPIER_USER | B18: SERVICE | C18: USERADMIN | D18: ZAPIER_ROLE | E18: ZAPIER_ROLE | F18: 2025-09-25 10:43:06.647 -0400
A19: PROD_IDENTITY_GRAPH_USER | B19: LEGACY_SERVICE | C19: USERADMIN | D19: PROD_IDENTITY_GRAPH | E19: PROD_IDENTITY_GRAPH | F19: 2025-09-27 23:02:46.453 -0400
A20: GATO_SALES_RESEARCH_STAGE | B20: SERVICE | C20: USERADMIN | D20: GATO_SALES_RESEARCH_STAGE | E20: GATO_SALES_RESEARCH_STAGE | F20: 2025-10-01 17:44:28.804 -0400
A21: AIRFLOW_MONITOR_USER | B21: SERVICE | C21: USERADMIN | E21: ACCOUNT_MONITOR | F21: 2025-10-01 20:01:49.349 -0400
A22: CONSUMPTION_MONITOR_USER_STAGE | B22: LEGACY_SERVICE | C22: USERADMIN | D22: CONSUMPTION_MONITOR_STAGE | E22: CONSUMPTION_MONITOR_STAGE | F22: 2025-10-01 20:12:07.519 -0400
A23: GITHUB_ACTIONS_COREDATA_USER | B23: LEGACY_SERVICE | C23: USERADMIN | D23: COREDATA_GITHUB_BOT | E23: COREDATA_GITHUB_BOT | F23: 2025-10-01 21:28:15.512 -0400
A24: CENSUS | B24: LEGACY_SERVICE | C24: USERADMIN | D24: CENSUS_ROLE | E24: CENSUS_ROLE | F24: 2025-10-01 22:13:46.962 -0400
A25: AIRFLOW_DVPP_USER_PROD | B25: LEGACY_SERVICE | C25: USERADMIN | D25: DVPP_PROD | E25: DVPP_PROD | F25: 2025-10-02 00:09:06.664 -0400
A26: DDQM_INTEGRATION_ACCOUNT | B26: LEGACY_SERVICE | C26: USERADMIN | D26: DOCKER_DESKTOP_QUALITY_METRICS | E26: DOCKER_DESKTOP_QUALITY_METRICS | F26: 2025-10-02 05:01:09.662 -0400
A27: DATABRICKS_USER | B27: LEGACY_SERVICE | C27: USERADMIN | D27: PROD_DATABRICKS | E27: PROD_DATABRICKS | F27: 2025-10-02 05:02:31.734 -0400
A28: SIGMA_INCR_WH_USER | B28: SERVICE | C28: USERADMIN | D28: SIGMA_DATA_PROD | E28: SIGMA_DATA_PROD | F28: 2025-10-02 05:24:08.838 -0400
A29: GAINSIGHT | B29: LEGACY_SERVICE | C29: USERADMIN | D29: GAINSIGHT | E29: GAINSIGHT | F29: 2025-10-02 06:12:02.952 -0400
A30: AIRFLOW_WOOTRIC_USER_PROD | B30: LEGACY_SERVICE | C30: USERADMIN | D30: WOOTRIC_INGESTION_PROD | E30: WOOTRIC_INGESTION_PROD | F30: 2025-10-02 07:00:39.556 -0400
A31: SIGMA_COREDATA | B31: SERVICE | C31: USERADMIN | D31: SNOWFLAKE_MONITOR | E31: SNOWFLAKE_MONITOR | F31: 2025-10-02 07:24:10.703 -0400
A32: TEST_BI_GG_DEV | B32: LEGACY_SERVICE | C32: SECURITYADMIN | D32: DOCKER_DEFAULT_AND_WORKSPACES_READONLY | E32: DOCKER_DEFAULT_AND_WORKSPACES_READONLY, DOCKER_DESKTOP_READONLY | F32: 2025-10-02 08:01:39.874 -0400
A33: PREVIEW_AIRFLOW_DEPLOYMENTS | B33: SERVICE | C33: USERADMIN | D33: PREVIEW_AIRFLOW_DEPLOYMENTS | E33: PREVIEW_AIRFLOW_DEPLOYMENTS | F33: 2025-10-02 10:48:15.699 -0400
... A35: SIGMA_CS_USER | B35: SERVICE | C35: USERADMIN | D35: SIGMA_CS | E35: SIGMA_CS | F35: 2025-10-02 11:02:09.406 -0400
A36: DEV_DATA_DBT_USER | B36: LEGACY_SERVICE | C36: USERADMIN | E36: DEV_DBT_DEPLOYMENTS, ENGINEERING_DEV, MARKETING_ADMIN, MARKETING_DEV, PRODUCT_ANALYST, SALESOPS_DEV | F36: 2025-10-02 11:47:46.014 -0400
A37: SIGMA_APP_OWNER | B37: SERVICE | C37: USERADMIN | D37: SIGMA_APP_OWNER_ROLE | E37: SIGMA_APP_OWNER_ROLE | F37: 2025-10-02 11:49:35.088 -0400
A38: SIGMA_DEV_USER | B38: SERVICE | C38: USERADMIN | D38: SIGMA_DATA_DEV | E38: SIGMA_DATA_DEV | F38: 2025-10-02 12:51:26.968 -0400
A39: DBT_PROD_DEPLOYMENT_WORKSPACES_USER | B39: LEGACY_SERVICE | C39: USERADMIN | D39: DBT_PROD_DEPLOYMENTS_WORKSPACES_ROLE | E39: DBT_DEPLOYMENTS_WORKSPACES | F39: 2025-10-02 13:24:03.831 -0400
A40: MCP_SERVICE_ACCOUNT_TEMP | B40: SERVICE | C40: USERADMIN | D40: MCP_SERVICE_ACCOUNT_TEMP | E40: MCP_SERVICE_ACCOUNT_TEMP | F40: 2025-10-02 13:25:37.572 -0400
A41: GITHUB_ACTIONS_BUGSNAG_USER | B41: LEGACY_SERVICE | C41: USERADMIN | D41: BUGSNAG | E41: BUGSNAG | F41: 2025-10-02 14:03:11.584 -0400
A42: LOOKER_COREDATA_USER | B42: SERVICE | C42: USERADMIN | D42: LOOKER_COREDATA | E42: ACCOUNT_MONITOR, COREDATA_DEV, LOOKER_COREDATA, LOOKER_COREDATA_PII | F42: 2025-10-02 14:26:39.950 -0400
A43: SEGMENT_USER | B43: LEGACY_SERVICE | C43: USERADMIN | D43: SEGMENT_ROLE | E43: SEGMENT_ROLE | F43: 2025-10-02 15:18:11.675 -0400
A44: INSIGHTS_USER | B44: LEGACY_SERVICE | C44: USERADMIN | D44: INSIGHTS_ROLE | E44: INSIGHTS_ROLE | F44: 2025-10-02 15:18:18.870 -0400
A45: HIGHTOUCH_USER | B45: SERVICE | C45: SECURITYADMIN | D45: HIGHTOUCH_ROLE | E45: HIGHTOUCH_ROLE | F45: 2025-10-02 15:44:50.762 -0400
A46: DBT_CI | B46: LEGACY_SERVICE | C46: USERADMIN | D46: DBT_CI_DEPLOYMENTS | E46: DBT_CI_DEPLOYMENTS | F46: 2025-10-02 15:54:34.813 -0400
A47: LOOKER_DOCKER_DESKTOP_USER | B47: SERVICE | C47: USERADMIN | D47: LOOKER_DOCKER_DESKTOP | E47: LOOKER_DOCKER_DESKTOP | F47: 2025-10-02 15:59:56.135 -0400
A48: AIRFLOW_EVENTS_ADMIN_USER | B48: SERVICE | C48: USERADMIN | D48: EVENTS_ADMIN | E48: EVENTS_ADMIN, EVENTS_ADMIN_STAGING | F48: 2025-10-02 16:00:38.441 -0400
... A60: SALESFORCE | B60: LEGACY_SERVICE | C60: USERADMIN | D60: SALESFORCE | E60: SALESFORCE | F60: 2025-10-02 16:04:56.080 -0400

Sheet Sigma
A1: User Name | B1: User Email | C1: License Type | D1: Account Type | E1: User Created at (UTC) | F1: Last Query Time (UTC) | G1: Days Since Last Query | H1: Invited By User Name | I1: Invited By User Email | J1: Invite Date (UTC) | K1: Account Permissions | L1: # Queries, Last 90 Days | M1: Teams | N1: # Teams | O1: Org Member Is Email Verified | P1: Should Downgrade | Q1: Should Delete | R1: Active Employee | S1: Notes | T1: Downgraded Permissions or Removed (If disabled for 90+ days, please remove)
A2: Exit Test 1 | B2: exit.test1@docker.com | C2: view | D2: View | E2: 45170.648 | H2: Fiona McShane | I2: fiona.mcshane@docker.com | J2: 45170.645 | K2: canComment, canDownloadLegacyDocs, canViewDashboard, canViewDatasetOrSql, canViewWorkbook, canViewWorksheet | L2: 0 | M2: All Members, Product | N2: 2 | O2: FALSE | Q2: Y | R2: =IF(COUNTIF('Active Employees'!B:B, B2)>0,"Y","N") -> N | S2: Test account
A3: Cheryl Lim | B3: Cheryl_lim@docker.com | C3: view | D3: View | E3: 45310.159 | H3: Zoey Kramer | I3: zoey.kramer@docker.com | J3: 45308.662 | K3: canComment, canDownloadLegacyDocs, canViewDashboard, canViewDatasetOrSql, canViewWorkbook, canViewWorksheet | L3: 0 | M3: All Members, Customer-Support | N3: 2 | O3: TRUE | Q3: Y | R3: =IF(COUNTIF('Active Employees'!B:B, B3)>0,"Y","N") -> N | S3: No queries
A4: Affandi Kamarolzaman | B4: affandi_kamarolzaman@docker.com | C4: view | D4: View | E4: 45799.775 | I4: [Invited via SAML] | K4: canComment, canDownloadLegacyDocs, canViewDashboard, canViewDatasetOrSql, canViewWorkbook, canViewWorksheet | L4: 0 | M4: All Members, Marketing | N4: 2 | O4: TRUE | Q4: Y | R4: =IF(COUNTIF('Active Employees'!B:B, B4)>0,"Y","N") -> N | S4: No queries
A5: Alex Salkever | B5: alex_salkever@docker.com | C5: view | D5: View | E5: 45854.891 | I5: [Invited via SAML] | K5: canComment, canDownloadLegacyDocs, canViewDashboard, canViewDatasetOrSql, canViewWorkbook, canViewWorksheet | L5: 0 | M5: All Members, Marketing | N5: 2 | O5: TRUE | Q5: Y | R5: =IF(COUNTIF('Active Employees'!B:B, B5)>0,"Y","N") -> N | S5: No queries
A6: Arlie Queenie | B6: arlie_queenie@docker.com | C6: view | D6: View | E6: 45799.775 | I6: [Invited via SAML] | K6: canComment, canDownloadLegacyDocs, canViewDashboard, canViewDatasetOrSql, canViewWorkbook, canViewWorksheet | L6: 0 | M6: All Members, Marketing | N6: 2 | O6: TRUE | Q6: Y | R6: =IF(COUNTIF('Active Employees'!B:B, B6)>0,"Y","N") -> N | S6: No queries
A7: Bjorn Hovd | B7: bjorn.hovd@docker.com | C7: view | D7: View | E7: 45922.38 | I7: [Invited via SAML] | K7: canComment, canDownloadLegacyDocs, canViewDashboard, canViewDatasetOrSql, canViewWorkbook, canViewWorksheet | L7: 0 | M7: All Members, Sales Team | N7: 2 | O7: TRUE | Q7: Y | R7: =IF(COUNTIF('Active Employees'!B:B, B7)>0,"Y","N") -> N | S7: No queries
A8: Blaine Wilson | B8: blaine.wilson@docker.com | C8: view | D8: View | E8: 45929.609 | I8: [Invited via SAML] | K8: canComment, canDownloadLegacyDocs, canViewDashboard, canViewDatasetOrSql, canViewWorkbook, canViewWorksheet | L8: 0 | M8: All Members, G&A | N8: 2 | O8: TRUE | Q8: Y | R8: =IF(COUNTIF('Active Employees'!B:B, B8)>0,"Y","N") -> N | S8: No queries
A9: Brent Seaton | B9: brent.seaton@docker.com | C9: view | D9: View | E9: 45799.774 | I9: [Invited via SAML] | K9: canComment, canDownloadLegacyDocs, canViewDashboard, canViewDatasetOrSql, canViewWorkbook, canViewWorksheet | L9: 0 | M9: All Members, Finance-Ops, G&A | N9: 3 | O9: TRUE | Q9: Y | R9: =IF(COUNTIF('Active Employees'!B:B, B9)>0,"Y","N") -> N | S9: No queries
A10: Bryan Chan | B10: bryan_chan@docker.com | C10: view | D10: View | E10: 45799.775 | I10: [Invited via SAML] | K10: canComment, canDownloadLegacyDocs, canViewDashboard, canViewDatasetOrSql, canViewWorkbook, canViewWorksheet | L10: 0 | M10: All Members, Marketing | N10: 2 | O10: TRUE | Q10: Y | R10: =IF(COUNTIF('Active Employees'!B:B, B10)>0,"Y","N") -> N | S10: No queries
A11: Chongghee Lee | B11: chongghee_lee@docker.com | C11: view | D11: View | E11: 45799.775 | I11: [Invited via SAML] | K11: canComment, canDownloadLegacyDocs, canViewDashboard, canViewDatasetOrSql, canViewWorkbook, canViewWorksheet | L11: 0 | M11: All Members, Marketing | N11: 2 | O11: TRUE | Q11: Y | R11: =IF(COUNTIF('Active Employees'!B:B, B11)>0,"Y","N") -> N | S11: No queries
A12: Chooi Gaik Goh | B12: chooi_goh@docker.com | C12: view | D12: View | E12: 45799.775 | I12: [Invited via SAML] | K12: canComment, canDownloadLegacyDocs, canViewDashboard, canViewDatasetOrSql, canViewWorkbook, canViewWorksheet | L12: 0 | M12: All Members, Sales Team | N12: 2 | O12: TRUE | Q12: Y | R12: =IF(COUNTIF('Active Employees'!B:B, B12)>0,"Y","N") -> N | S12: No queries
A13: Danielle Schwolow | B13: danielle_schwolow@docker.com | C13: view | D13: View | E13: 45799.775 | I13: [Invited via SAML] | K13: canComment, canDownloadLegacyDocs, canViewDashboard, canViewDatasetOrSql, canViewWorkbook, canViewWorksheet | L13: 0 | M13: All Members, Marketing | N13: 2 | O13: TRUE | Q13: Y | R13: =IF(COUNTIF('Active Employees'!B:B, B13)>0,"Y","N") -> N | S13: No queries
A14: David Oro | B14: david_oro@docker.com | C14: view | D14: View | E14: 45799.775 | I14: [Invited via SAML] | K14: canComment, canDownloadLegacyDocs, canViewDashboard, canViewDatasetOrSql, canViewWorkbook, canViewWorksheet | L14: 0 | M14: All Members, Marketing | N14: 2 | O14: TRUE | Q14: Y | R14: =IF(COUNTIF('Active Employees'!B:B, B14)>0,"Y","N") -> N | S14: No queries
A15: David Otero | B15: david_otero@docker.com | C15: view | D15: View | E15: 45799.775 | I15: [Invited via SAML] | K15: canComment, canDownloadLegacyDocs, canViewDashboard, canViewDatasetOrSql, canViewWorkbook, canViewWorksheet | L15: 0 | M15: All Members, Marketing | N15: 2 | O15: TRUE | Q15: Y | R15: =IF(COUNTIF('Active Employees'!B:B, B15)>0,"Y","N") -> N | S15: No queries
... A54: Voon Yee | B54: voon_yee@docker.com | C54: view | D54: View | E54: 45799.774 | I54: [Invited via SAML] | K54: canComment, canDownloadLegacyDocs, canViewDashboard, canViewDatasetOrSql, canViewWorkbook, canViewWorksheet | L54: 0 | M54: All Members, Customer-Support, Engineering-Team | N54: 3 | O54: TRUE | Q54: Y | R54: =IF(COUNTIF('Active Employees'!B:B, B54)>0,"Y","N") -> N | S54: External_consultant
A55: Sarb Adhikari | B55: sarbajit.adhikari@docker.com | C55: build | D55: admin | E55: 45678.932 | F55: 45846.74 | G55: 86 | H55: Jordan Hembling | I55: jordan.hembling@docker.com | J55: 45678.918 | K55: canAdmin, canAnnotate, canApplyTag, canBadge, canBasicExploreWorkbook, canComment, canCreateDatasheet, canCreateWarehouseView, canCreateWorkspace, canDevelopPlugins, canDownloadLegacyDocs, canEditDashboard, canEditDatasetOrSql, canEditInputTable, canEditWorksheet, canEmbed, canExploreWorkbook, canExport, canExportToCloud, canJoin, canManageBranding, canManageConnection, canManageFontsThemes, canMaterialize, canOrganize, canSaveWorkbook, canScheduleExport, canSeeOrgUsage, canShare, canUpdateDataRefresh, canUpdateTable, canUploadCsv, canVersionTag, canViewConnection, canViewDashboard, canViewDatasetOrSql, canViewWorkbook, canViewWorksheet, canWriteCode | L55: 3 | M55: All Members, PROD-Data & Growth Group, Product | N55: 3 | O55: TRUE | Q55: Y | R55: =IF(COUNTIF('Active Employees'!B:B, B55)>0,"Y","N") -> N | S55: Former employee
A56: Jonathan Gan | B56: Jonathan_gan@docker.com | C56: view | D56: View | E56: 45799.774 | F56: 45856.274 | G56: 76 | I56: [Invited via SAML] | K56: canComment, canDownloadLegacyDocs, canViewDashboard, canViewDatasetOrSql, canViewWorkbook, canViewWorksheet | L56: 11 | M56: All Members, Customer-Support, Engineering-Team | N56: 3 | O56: TRUE | Q56: Y | R56: =IF(COUNTIF('Active Employees'!B:B, B56)>0,"Y","N") -> N | S56: Former employee
A57: Joe Lai | B57: yongzhu_lai@docker.com | C57: view | D57: View | E57: 45799.774 | F57: 45856.317 | G57: 76 | I57: [Invited via SAML] | K57: canComment, canDownloadLegacyDocs, canViewDashboard, canViewDatasetOrSql, canViewWorkbook, canViewWorksheet | L57: 1 | M57: All Members, Customer-Support, Engineering-Team | N57: 3 | O57: TRUE | Q57: Y | R57: =IF(COUNTIF('Active Employees'!B:B, B57)>0,"Y","N") -> N | S57: Former employee
A58: Ysfin Tazky | B58: ysfin_tazky@docker.com | C58: view | D58: View | E58: 45799.774 | F58: 45856.315 | G58: 76 | I58: [Invited via SAML] | K58: canComment, canDownloadLegacyDocs, canViewDashboard, canViewDatasetOrSql, canViewWorkbook, canViewWorksheet | L58: 2 | M58: All Members, Customer-Support, Engineering-Team | N58: 3 | O58: TRUE | Q58: Y | R58: =IF(COUNTIF('Active Employees'!B:B, B58)>0,"Y","N") -> N | S58: Former employee
A59: Benjamin Abarzua | B59: Ben_Abarzua@docker.com | C59: view | D59: View | E59: 45799.774 | F59: 45915.631 | G59: 17 | I59: [Invited via SAML] | K59: canComment, canDownloadLegacyDocs, canViewDashboard, canViewDatasetOrSql, canViewWorkbook, canViewWorksheet | L59: 6 | M59: All Members, Customer-Support, Engineering-Team | N59: 3 | O59: TRUE | Q59: Y | R59: =IF(COUNTIF('Active Employees'!B:B, B59)>0,"Y","N") -> N | S59: Former employee
A60: Ajeet Raina | B60: ajeet_raina@docker.com | C60: view | D60: View | E60: 45799.775 | F60: 45926.363 | G60: 6 | I60: [Invited via SAML] | K60: canComment, canDownloadLegacyDocs, canViewDashboard, canViewDatasetOrSql, canViewWorkbook, canViewWorksheet | L60: 20 | M60: All Members, Marketing | N60: 2 | O60: TRUE | Q60: Y | R60: =IF(COUNTIF('Active Employees'!B:B, B60)>0,"Y","N") -> N | S60: Former employee
A61: Bill Marozas | B61: bill.marozas@docker.com | C61: view | D61: View | E61: 45922.382 | F61: 45931.803 | G61: 1 | I61: [Invited via SAML] | K61: canComment, canDownloadLegacyDocs, canViewDashboard, canViewDatasetOrSql, canViewWorkbook, canViewWorksheet | L61: 3 | M61: All Members, Sales Team | N61: 2 | O61: TRUE | Q61: Y | R61: =IF(COUNTIF('Active Employees'!B:B, B61)>0,"Y","N") -> N | S61: Former employee
A62: Tuna Icingir | B62: tuna.icingir@docker.com | C62: view | D62: View | E62: 45922.379 | F62: 45931.942 | G62: 1 | I62: [Invited via SAML] | K62: canComment, canDownloadLegacyDocs, canViewDashboard, canViewDatasetOrSql, canViewWorkbook, canViewWorksheet | L62: 3 | M62: All Members, Engineering-Team | N62: 2 | O62: TRUE | Q62: Y | R62: =IF(COUNTIF('Active Employees'!B:B, B62)>0,"Y","N") -> N | S62: Former employee
A63: Yifeng Tek | B63: yifeng_tek@docker.com | C63: build | D63: Build | E63: 45784.159 | F63: 45931.414 | G63: 1 | I63: [Invited via SAML] | K63: canAnnotate, canApplyTag, canBadge, canBasicExploreWorkbook, canComment, canCreateDatasheet, canDownloadLegacyDocs, canEditDashboard, canEditDatasetOrSql, canEditInputTable, canEditWorksheet, canExploreWorkbook, canExport, canJoin, canMaterialize, canOrganize, canSaveWorkbook, canScheduleExport, canSeeOrgUsage, canShare, canUpdateDataRefresh, canUpdateTable, canUploadCsv, canViewConnection, canViewDashboard, canViewDatasetOrSql, canViewWorkbook, canViewWorksheet | L63: 12165 | M63: All Members, Marketing | N63: 2 | O63: TRUE | Q63: Y | R63: =IF(COUNTIF('Active Employees'!B:B, B63)>0,"Y","N") -> N | S63: Former employee
A64: Hasyir Hashim | B64: hasyir_hashim@docker.com | C64: build | D64: Build | E64: 45784.289 | F64: 45932.177 | G64: 0 | I64: [Invited via SAML] | K64: canAnnotate, canApplyTag, canBadge, canBasicExploreWorkbook, canComment, canCreateDatasheet, canDownloadLegacyDocs, canEditDashboard, canEditDatasetOrSql, canEditInputTable, canEditWorksheet, canExploreWorkbook, canExport, canJoin, canMaterialize, canOrganize, canSaveWorkbook, canScheduleExport, canSeeOrgUsage, canShare, canUpdateDataRefresh, canUpdateTable, canUploadCsv, canViewConnection, canViewDashboard, canViewDatasetOrSql, canViewWorkbook, canViewWorksheet | L64: 2813 | M64: All Members, Marketing | N64: 2 | O64: TRUE | Q64: Y | R64: =IF(COUNTIF('Active Employees'!B:B, B64)>0,"Y","N") -> N | S64: Former employee
A65: Abi-Drey Totow | B65: abidrey.totow@docker.com | C65: view | D65: View | E65: 45799.775 | I65: [Invited via SAML] | K65: canComment, canDownloadLegacyDocs, canViewDashboard, canViewDatasetOrSql, canViewWorkbook, canViewWorksheet | L65: 0 | M65: All Members, Sales Team | N65: 2 | O65: TRUE | R65: =IF(COUNTIF('Active Employees'!B:B, B65)>0,"Y","N") -> Y | S65: No queries
A66: Alano Terblanche | B66: alano.terblanche@docker.com | C66: view | D66: View | E66: 45799.774 | I66: [Invited via SAML] | K66: canComment, canDownloadLegacyDocs, canViewDashboard, canViewDatasetOrSql, canViewWorkbook, canViewWorksheet | L66: 0 | M66: All Members, Engineering-Team | N66: 2 | O66: TRUE | R66: =IF(COUNTIF('Active Employees'!B:B, B66)>0,"Y","N") -> Y | S66: No queries
A67: Alec Carter | B67: alec.carter@docker.com | C67: view | D67: View | E67: 45799.774 | I67: [Invited via SAML] | K67: canComment, canDownloadLegacyDocs, canViewDashboard, canViewDatasetOrSql, canViewWorkbook, canViewWorksheet | L67: 0 | M67: All Members, G&A, People Team | N67: 3 | O67: TRUE | R67: =IF(COUNTIF('Active Employees'!B:B, B67)>0,"Y","N") -> Y | S67: No queries
A68: Alec Warren | B68: alec.warren@docker.com | C68: view | D68: View | E68: 45810.606 | I68: [Invited via SAML] | K68: canComment, canDownloadLegacyDocs, canViewDashboard, canViewDatasetOrSql, canViewWorkbook, canViewWorksheet | L68: 0 | M68: All Members, Engineering-Team | N68: 2 | O68: TRUE | R68: =IF(COUNTIF('Active Employees'!B:B, B68)>0,"Y","N") -> Y | S68: No queries
A69: Alex Griffen | B69: alex.griffen@docker.com | C69: view | D69: View | E69: 45901.619 | I69: [Invited via SAML] | K69: canComment, canDownloadLegacyDocs, canViewDashboard, canViewDatasetOrSql, canViewWorkbook, canViewWorksheet | L69: 0 | M69: All Members, Sales Team | N69: 2 | O69: TRUE | R69: =IF(COUNTIF('Active Employees'!B:B, B69)>0,"Y","N") -> Y | S69: No queries
A70: Alex Hokanson | B70: alex.hokanson@docker.com | C70: view | D70: View | E70: 45799.774 | I70: [Invited via SAML] | K70: canComment, canDownloadLegacyDocs, canViewDashboard, canViewDatasetOrSql, canViewWorkbook, canViewWorksheet | L70: 0 | M70: All Members, Engineering-Team | N70: 2 | O70: TRUE | R70: =IF(COUNTIF('Active Employees'!B:B, B70)>0,"Y","N") -> Y | S70: No queries
A71: Alex Rojas | B71: alexandra.rojas@docker.com | C71: view | D71: View | E71: 45799.774 | I71: [Invited via SAML] | K71: canComment, canDownloadLegacyDocs, canViewDashboard, canViewDatasetOrSql, canViewWorkbook, canViewWorksheet | L71: 0 | M71: All Members, G&A | N71: 2 | O71: TRUE | R71: =IF(COUNTIF('Active Employees'!B:B, B71)>0,"Y","N") -> Y | S71: No queries
A72: Alexandre Vallières-Lagacé | B72: alexandre.valliereslagace@docker.com | C72: view | D72: View | E72: 45799.774 | I72: [Invited via SAML] | K72: canComment, canDownloadLegacyDocs, canViewDashboard, canViewDatasetOrSql, canViewWorkbook, canViewWorksheet | L72: 0 | M72: All Members, Engineering-Team | N72: 2 | O72: TRUE | R72: =IF(COUNTIF('Active Employees'!B:B, B72)>0,"Y","N") -> Y | S72: No queries
A73: Ali Mulla Mahmoud | B73: ali.mulla@docker.com | C73: view | D73: View | E73: 45799.817 | I73: [Invited via SAML] | K73: canComment, canDownloadLegacyDocs, canViewDashboard, canViewDatasetOrSql, canViewWorkbook, canViewWorksheet | L73: 0 | M73: All Members, Sales Team | N73: 2 | O73: TRUE | R73: =IF(COUNTIF('Active Employees'!B:B, B73)>0,"Y","N") -> Y | S73: No queries
A74: Allie Sadler | B74: allie.sadler@docker.com | C74: view | D74: View | E74: 45799.775 | I74: [Invited via SAML] | K74: canComment, canDownloadLegacyDocs, canViewDashboard, canViewDatasetOrSql, canViewWorkbook, canViewWorksheet | L74: 0 | M74: All Members, Product | N74: 2 | O74: TRUE | R74: =IF(COUNTIF('Active Employees'!B:B, B74)>0,"Y","N") -> Y | S74: No queries
A75: Alton Dunkley | B75: alton.dunkley@docker.com | C75: view | D75: View | E75: 45799.775 | I75: [Invited via SAML] | K75: canComment, canDownloadLegacyDocs, canViewDashboard, canViewDatasetOrSql, canViewWorkbook, canViewWorksheet | L75: 0 | M75: All Members, Sales Team | N75: 2 | O75: TRUE | R75: =IF(COUNTIF('Active Employees'!B:B, B75)>0,"Y","N") -> Y | S75: No queries
A76: Amanda Maderic | B76: amanda.maderic@docker.com | C76: view | D76: View | E76: 45799.775 | I76: [Invited via SAML] | K76: canComment, canDownloadLegacyDocs, canViewDashboard, canViewDatasetOrSql, canViewWorkbook, canViewWorksheet | L76: 0 | M76: All Members, Product | N76: 2 | O76: TRUE | R76: =IF(COUNTIF('Active Employees'!B:B, B76)>0,"Y","N") -> Y | S76: No queries
... A86: Barbara Fusinska | B86: barbara.fusinska@docker.com | C86: view | D86: View | E86: 45799.774 | I86: [Invited via SAML] | K86: canComment, canDownloadLegacyDocs, canViewDashboard, canViewDatasetOrSql, canViewWorkbook, canViewWorksheet | L86: 0 | M86: All Members, Engineering-Team | N86: 2 | O86: TRUE | R86: =IF(COUNTIF('Active Employees'!B:B, B86)>0,"Y","N") -> Y | S86: No queries
A87: Beck Matuszek | B87: beck.matuszek@docker.com | C87: view | D87: View | E87: 45447.685 | H87: Zoey Kramer | I87: zoey.kramer@docker.com | J87: 45447.59 | K87: canComment, canDownloadLegacyDocs, canViewDashboard, canViewDatasetOrSql, canViewWorkbook, canViewWorksheet | L87: 0 | M87: All Members, Customer-Support, Engineering-Team | N87: 3 | O87: TRUE | R87: =IF(COUNTIF('Active Employees'!B:B, B87)>0,"Y","N") -> Y | S87: No queries
A88: Ben Griffiths | B88: ben.griffiths@docker.com | C88: view | D88: View | E88: 45799.774 | I88: [Invited via SAML] | K88: canComment, canDownloadLegacyDocs, canViewDashboard, canViewDatasetOrSql, canViewWorkbook, canViewWorksheet | L88: 0 | M88: All Members, Engineering-Team | N88: 2 | O88: TRUE | R88: =IF(COUNTIF('Active Employees'!B:B, B88)>0,"Y","N") -> Y | S88: No queries
A89: Bill Pijewski | B89: bill.pijewski@docker.com | C89: view | D89: View | E89: 45840.694 | I89: [Invited via SAML] | K89: canComment, canDownloadLegacyDocs, canViewDashboard, canViewDatasetOrSql, canViewWorkbook, canViewWorksheet | L89: 0 | M89: All Members, Engineering-Team | N89: 2 | O89: TRUE | R89: =IF(COUNTIF('Active Employees'!B:B, B89)>0,"Y","N") -> Y | S89: No queries
A90: Breanna Paredes | B90: breanna.paredes@docker.com | C90: view | D90: View | E90: 45799.774 | I90: [Invited via SAML] | K90: canComment, canDownloadLegacyDocs, canViewDashboard, canViewDatasetOrSql, canViewWorkbook, canViewWorksheet | L90: 0 | M90: All Members, G&A, People Team | N90: 3 | O90: TRUE | R90: =IF(COUNTIF('Active Employees'!B:B, B90)>0,"Y","N") -> Y | S90: No queries
A91: Brent Paterson | B91: brent.paterson@docker.com | C91: view | D91: View | E91: 45799.774 | I91: [Invited via SAML] | K91: canComment, canDownloadLegacyDocs, canViewDashboard, canViewDatasetOrSql, canViewWorkbook, canViewWorksheet | L91: 0 | M91: All Members, Sales Team | N91: 2 | O91: TRUE | R91: =IF(COUNTIF('Active Employees'!B:B, B91)>0,"Y","N") -> Y | S91: No queries
A92: Brianna Hobbs | B92: brianna.hobbs@docker.com | C92: view | D92: View | E92: 45799.775 | I92: [Invited via SAML] | K92: canComment, canDownloadLegacyDocs, canViewDashboard, canViewDatasetOrSql, canViewWorkbook, canViewWorksheet | L92: 0 | M92: All Members, Sales Team | N92: 2 | O92: TRUE | R92: =IF(COUNTIF('Active Employees'!B:B, B92)>0,"Y","N") -> Y | S92: No queries
A93: Brianna Mabey | B93: brianna.mabey@docker.com | C93: view | D93: View | E93: 45799.774 | I93: [Invited via SAML] | K93: canComment, canDownloadLegacyDocs, canViewDashboard, canViewDatasetOrSql, canViewWorkbook, canViewWorksheet | L93: 0 | M93: All Members, G&A, People Team | N93: 3 | O93: TRUE | R93: =IF(COUNTIF('Active Employees'!B:B, B93)>0,"Y","N") -> Y | S93: No queries
A94: Bryan Ross | B94: bryan.ross@docker.com | C94: view | D94: View | E94: 45762.633 | H94: Nicola Watson | I94: nicola.watson@docker.com | J94: 45762.633 | K94: canComment, canDownloadLegacyDocs, canViewDashboard, canViewDatasetOrSql, canViewWorkbook, canViewWorksheet | L94: 0 | M94: All Members, Engineering-Team | N94: 2 | O94: TRUE | R94: =IF(COUNTIF('Active Employees'!B:B, B94)>0,"Y","N") -> Y | S94: No queries
A95: Carmen Martinho | B95: carmen.martinho@docker.com | C95: view | D95: View | E95: 45799.774 | I95: [Invited via SAML] | K95: canComment, canDownloadLegacyDocs, canViewDashboard, canViewDatasetOrSql, canViewWorkbook, canViewWorksheet | L95: 0 | M95: All Members, G&A, People Team | N95: 3 | O95: TRUE | R95: =IF(COUNTIF('Active Employees'!B:B, B95)>0,"Y","N") -> Y | S95: No queries
A96: Cesar Talledo | B96: cesar.talledo@docker.com | C96: view | D96: View | E96: 45799.774 | I96: [Invited via SAML] | K96: canComment, canDownloadLegacyDocs, canViewDashboard, canViewDatasetOrSql, canViewWorkbook, canViewWorksheet | L96: 0 | M96: All Members, Engineering-Team | N96: 2 | O96: TRUE | R96: =IF(COUNTIF('Active Employees'!B:B, B96)>0,"Y","N") -> Y | S96: No queries
A97: Cesia Mijango | B97: cesia.mijango@docker.com | C97: view | D97: View | E97: 45799.774 | I97: [Invited via SAML] | K97: canComment, canDownloadLegacyDocs, canViewDashboard, canViewDatasetOrSql, canViewWorkbook, canViewWorksheet | L97: 0 | M97: All Members, Finance-Ops, G&A | N97: 3 | O97: TRUE | R97: =IF(COUNTIF('Active Employees'!B:B, B97)>0,"Y","N") -> Y | S97: No queries
A98: Chanon Wahlstrom | B98: chanon.wahlstrom@docker.com | C98: view | D98: View | E98: 45799.775 | I98: [Invited via SAML] | K98: canComment, canDownloadLegacyDocs, canViewDashboard, canViewDatasetOrSql, canViewWorkbook, canViewWorksheet | L98: 0 | M98: All Members, Sales Team | N98: 2 | O98: TRUE | R98: =IF(COUNTIF('Active Employees'!B:B, B98)>0,"Y","N") -> Y | S98: No queries
A99: Chase Frankenfeld | B99: chase.frankenfeld@docker.com | C99: view | D99: View | E99: 45799.774 | I99: [Invited via SAML] | K99: canComment, canDownloadLegacyDocs, canViewDashboard, canViewDatasetOrSql, canViewWorkbook, canViewWorksheet | L99: 0 | M99: All Members, Engineering-Team | N99: 2 | O99: TRUE | R99: =IF(COUNTIF('Active Employees'!B:B, B99)>0,"Y","N") -> Y | S99: No queries
A100: Chris Ainsworth-Patrick | B100: chris.ainsworth-patrick@docker.com | C100: view | D100: View | E100: 45799.774 | I100: [Invited via SAML] | K100: canComment, canDownloadLegacyDocs, canViewDashboard, canViewDatasetOrSql, canViewWorkbook, canViewWorksheet | L100: 0 | M100: All Members, Engineering-Team | N100: 2 | O100: TRUE | R100: =IF(COUNTIF('Active Employees'!B:B, B100)>0,"Y","N") -> Y | S100: No queries
A101: Chris Kenna | B101: chris.kenna@docker.com | C101: view | D101: View | E101: 45810.606 | I101: [Invited via SAML] | K101: canComment, canDownloadLegacyDocs, canViewDashboard, canViewDatasetOrSql, canViewWorkbook, canViewWorksheet | L101: 0 | M101: All Members, Engineering-Team | N101: 2 | O101: TRUE | R101: =IF(COUNTIF('Active Employees'!B:B, B101)>0,"Y","N") -> Y | S101: No queries
A102: Christian Dupuis | B102: christian.dupuis@docker.com | C102: view | D102: View | E102: 45799.774 | I102: [Invited via SAML] | K102: canComment, canDownloadLegacyDocs, canViewDashboard, canViewDatasetOrSql, canViewWorkbook, canViewWorksheet | L102: 0 | M102: All Members, Engineering-Team | N102: 2 | O102: TRUE | R102: =IF(COUNTIF('Active Employees'!B:B, B102)>0,"Y","N") -> Y | S102: No queries
A103: Chris Yee | B103: christopher.yee@docker.com | C103: view | D103: View | E103: 45799.816 | I103: [Invited via SAML] | K103: canComment, canDownloadLegacyDocs, canViewDashboard, canViewDatasetOrSql, canViewWorkbook, canViewWorksheet | L103: 0 | M103: All Members, Marketing | N103: 2 | O103: TRUE | R103: =IF(COUNTIF('Active Employees'!B:B, B103)>0,"Y","N") -> Y | S103: No queries
A104: Dan Deloff | B104: dan.deloff@docker.com | C104: view | D104: View | E104: 45799.774 | I104: [Invited via SAML] | K104: canComment, canDownloadLegacyDocs, canViewDashboard, canViewDatasetOrSql, canViewWorkbook, canViewWorksheet | L104: 0 | M104: All Members, Customer-Support, Engineering-Team | N104: 3 | O104: TRUE | R104: =IF(COUNTIF('Active Employees'!B:B, B104)>0,"Y","N") -> Y | S104: No queries
A105: Daniel Kolev | B105: daniel.kolev@docker.com | C105: view | D105: View | E105: 45799.774 | I105: [Invited via SAML] | K105: canComment, canDownloadLegacyDocs, canViewDashboard, canViewDatasetOrSql, canViewWorkbook, canViewWorksheet | L105: 0 | M105: All Members, Engineering-Team | N105: 2 | O105: TRUE | R105: =IF(COUNTIF('Active Employees'!B:B, B105)>0,"Y","N") -> Y | S105: No queries
A106: Daniel Nguyen | B106: daniel.nguyen@docker.com | C106: view | D106: View | E106: 45799.774 | I106: [Invited via SAML] | K106: canComment, canDownloadLegacyDocs, canViewDashboard, canViewDatasetOrSql, canViewWorkbook, canViewWorksheet | L106: 0 | M106: All Members, Finance-Ops, G&A | N106: 3 | O106: TRUE | R106: =IF(COUNTIF('Active Employees'!B:B, B106)>0,"Y","N") -> Y | S106: No queries
... A134: Innell Agodjro | B134: innell.agodjro@docker.com | C134: view | D134: View | E134: 45799.774 | I134: [Invited via SAML] | K134: canComment, canDownloadLegacyDocs, canViewDashboard, canViewDatasetOrSql, canViewWorkbook, canViewWorksheet | L134: 0 | M134: All Members, G&A, People Team | N134: 3 | O134: TRUE | R134: =IF(COUNTIF('Active Employees'!B:B, B134)>0,"Y","N") -> Y | S134: No queries
A135: Iván Californias | B135: ivan.californias@docker.com | C135: view | D135: View | E135: 45762.633 | H135: Nicola Watson | I135: nicola.watson@docker.com | J135: 45762.633 | K135: canComment, canDownloadLegacyDocs, canViewDashboard, canViewDatasetOrSql, canViewWorkbook, canViewWorksheet | L135: 0 | M135: All Members, Engineering-Team | N135: 2 | O135: TRUE | R135: =IF(COUNTIF('Active Employees'!B:B, B135)>0,"Y","N") -> Y | S135: No queries
A136: Ivan Pedrazas | B136: ivan.pedrazas@docker.com | C136: view | D136: View | E136: 45799.774 | I136: [Invited via SAML] | K136: canComment, canDownloadLegacyDocs, canViewDashboard, canViewDatasetOrSql, canViewWorkbook, canViewWorksheet | L136: 0 | M136: All Members, Engineering-Team | N136: 2 | O136: TRUE | R136: =IF(COUNTIF('Active Employees'!B:B, B136)>0,"Y","N") -> Y | S136: No queries
A137: Jaime Valeta | B137: jaime.valeta@docker.com | C137: view | D137: View | E137: 45799.774 | I137: [Invited via SAML] | K137: canComment, canDownloadLegacyDocs, canViewDashboard, canViewDatasetOrSql, canViewWorkbook, canViewWorksheet | L137: 0 | M137: All Members, Customer-Support, Engineering-Team | N137: 3 | O137: TRUE | R137: =IF(COUNTIF('Active Employees'!B:B, B137)>0,"Y","N") -> Y | S137: No queries
A138: James Childs | B138: james.childs@docker.com | C138: view | D138: View | E138: 45799.774 | I138: [Invited via SAML] | K138: canComment, canDownloadLegacyDocs, canViewDashboard, canViewDatasetOrSql, canViewWorkbook, canViewWorksheet | L138: 0 | M138: All Members, Engineering-Team | N138: 2 | O138: TRUE | R138: =IF(COUNTIF('Active Employees'!B:B, B138)>0,"Y","N") -> Y | S138: No queries
A139: James Hammons | B139: james.hammons@docker.com | C139: view | D139: View | E139: 45799.817 | I139: [Invited via SAML] | K139: canComment, canDownloadLegacyDocs, canViewDashboard, canViewDatasetOrSql, canViewWorkbook, canViewWorksheet | L139: 0 | M139: All Members, Sales Team | N139: 2 | O139: TRUE | R139: =IF(COUNTIF('Active Employees'!B:B, B139)>0,"Y","N") -> Y | S139: No queries
A140: Jason Bivins | B140: jason.bivins@docker.com | C140: view | D140: View | E140: 45799.774 | I140: [Invited via SAML] | K140: canComment, canDownloadLegacyDocs, canViewDashboard, canViewDatasetOrSql, canViewWorkbook, canViewWorksheet | L140: 0 | M140: All Members, Customer-Support, Engineering-Team | N140: 3 | O140: TRUE | R140: =IF(COUNTIF('Active Employees'!B:B, B140)>0,"Y","N") -> Y | S140: No queries
A141: Jason Ching | B141: jason.ching@docker.com | C141: view | D141: View | E141: 45799.775 | I141: [Invited via SAML] | K141: canComment, canDownloadLegacyDocs, canViewDashboard, canViewDatasetOrSql, canViewWorkbook, canViewWorksheet | L141: 0 | M141: All Members, Product | N141: 2 | O141: TRUE | R141: =IF(COUNTIF('Active Employees'!B:B, B141)>0,"Y","N") -> Y | S141: No queries
A142: Javier Garcia Manzano | B142: javier.garcia@docker.com | C142: view | D142: View | E142: 45799.774 | I142: [Invited via SAML] | K142: canComment, canDownloadLegacyDocs, canViewDashboard, canViewDatasetOrSql, canViewWorkbook, canViewWorksheet | L142: 0 | M142: All Members, Engineering-Team | N142: 2 | O142: TRUE | R142: =IF(COUNTIF('Active Employees'!B:B, B142)>0,"Y","N") -> Y | S142: No queries
A143: Jeffrey Strauss | B143: jeffrey.strauss@docker.com | C143: view | D143: View | E143: 45799.774 | I143: [Invited via SAML] | K143: canComment, canDownloadLegacyDocs, canViewDashboard, canViewDatasetOrSql, canViewWorkbook, canViewWorksheet | L143: 0 | M143: All Members, Finance-Ops, G&A | N143: 3 | O143: TRUE | R143: =IF(COUNTIF('Active Employees'!B:B, B143)>0,"Y","N") -> Y | S143: No queries
A144: Jen Fisher | B144: jen.fisher@docker.com | C144: view | D144: View | E144: 45799.775 | I144: [Invited via SAML] | K144: canComment, canDownloadLegacyDocs, canViewDashboard, canViewDatasetOrSql, canViewWorkbook, canViewWorksheet | L144: 0 | M144: All Members, Marketing | N144: 2 | O144: TRUE | R144: =IF(COUNTIF('Active Employees'!B:B, B144)>0,"Y","N") -> Y | S144: No queries
A145: Jennifer Kohl | B145: jennifer.kohl@docker.com | C145: view | D145: View | E145: 45799.816 | I145: [Invited via SAML] | K145: canComment, canDownloadLegacyDocs, canViewDashboard, canViewDatasetOrSql, canViewWorkbook, canViewWorksheet | L145: 0 | M145: All Members, Marketing | N145: 2 | O145: TRUE | R145: =IF(COUNTIF('Active Employees'!B:B, B145)>0,"Y","N") -> Y | S145: No queries
A146: Jessica Jacobs | B146: jessica.jacobs@docker.com | C146: view | D146: View | E146: 45799.775 | I146: [Invited via SAML] | K146: canComment, canDownloadLegacyDocs, canViewDashboard, canViewDatasetOrSql, canViewWorkbook, canViewWorksheet | L146: 0 | M146: All Members, Sales Team | N146: 2 | O146: TRUE | R146: =IF(COUNTIF('Active Employees'!B:B, B146)>0,"Y","N") -> Y | S146: No queries
A147: Jin Kim | B147: jin.kim@docker.com | C147: view | D147: View | E147: 45799.775 | I147: [Invited via SAML] | K147: canComment, canDownloadLegacyDocs, canViewDashboard, canViewDatasetOrSql, canViewWorkbook, canViewWorksheet | L147: 0 | M147: All Members, Marketing | N147: 2 | O147: TRUE | R147: =IF(COUNTIF('Active Employees'!B:B, B147)>0,"Y","N") -> Y | S147: No queries
A148: Joel Benavides | B148: joel.benavides@docker.com | C148: view | D148: View | E148: 45799.774 | I148: [Invited via SAML] | K148: canComment, canDownloadLegacyDocs, canViewDashboard, canViewDatasetOrSql, canViewWorkbook, canViewWorksheet | L148: 0 | M148: All Members, Finance-Ops, G&A | N148: 3 | O148: TRUE | R148: =IF(COUNTIF('Active Employees'!B:B, B148)>0,"Y","N") -> Y | S148: No queries
A149: Gonzo Gonzalez | B149: johnny.gonzalez@docker.com | C149: view | D149: View | E149: 45519.606 | H149: Zoey Kramer | I149: zoey.kramer@docker.com | J149: 45519.597 | K149: canComment, canDownloadLegacyDocs, canViewDashboard, canViewDatasetOrSql, canViewWorkbook, canViewWorksheet | L149: 0 | M149: All Members, Customer-Support, Engineering-Team | N149: 3 | O149: TRUE | R149: =IF(COUNTIF('Active Employees'!B:B, B149)>0,"Y","N") -> Y | S149: No queries
A150: Jonathan Dieu | B150: jonathan.dieu@docker.com | C150: view | D150: View | E150: 45799.774 | I150: [Invited via SAML] | K150: canComment, canDownloadLegacyDocs, canViewDashboard, canViewDatasetOrSql, canViewWorkbook, canViewWorksheet | L150: 0 | M150: All Members, Engineering-Team | N150: 2 | O150: TRUE | R150: =IF(COUNTIF('Active Employees'!B:B, B150)>0,"Y","N") -> Y | S150: No queries
A151: Jonathan Lawson | B151: jonathan.lawson@docker.com | C151: view | D151: View | E151: 45799.774 | I151: [Invited via SAML] | K151: canComment, canDownloadLegacyDocs, canViewDashboard, canViewDatasetOrSql, canViewWorkbook, canViewWorksheet | L151: 0 | M151: All Members, Finance-Ops, G&A | N151: 3 | O151: TRUE | R151: =IF(COUNTIF('Active Employees'!B:B, B151)>0,"Y","N") -> Y | S151: No queries
A152: Jonathan Sternberg | B152: jonathan.sternberg@docker.com | C152: view | D152: View | E152: 45799.774 | I152: [Invited via SAML] | K152: canComment, canDownloadLegacyDocs, canViewDashboard, canViewDatasetOrSql, canViewWorkbook, canViewWorksheet | L152: 0 | M152: All Members, Engineering-Team | N152: 2 | O152: TRUE | R152: =IF(COUNTIF('Active Employees'!B:B, B152)>0,"Y","N") -> Y | S152: No queries
A153: Jorge Fernandez Ocana | B153: jorge.fernandez@docker.com | C153: view | D153: View | E153: 45799.775 | I153: [Invited via SAML] | K153: canComment, canDownloadLegacyDocs, canViewDashboard, canViewDatasetOrSql, canViewWorkbook, canViewWorksheet | L153: 0 | M153: All Members, Sales Team | N153: 2 | O153: TRUE | R153: =IF(COUNTIF('Active Employees'!B:B, B153)>0,"Y","N") -> Y | S153: No queries
A154: Joseph Ferguson | B154: joseph.ferguson@docker.com | C154: view | D154: View | E154: 45799.774 | I154: [Invited via SAML] | K154: canComment, canDownloadLegacyDocs, canViewDashboard, canViewDatasetOrSql, canViewWorkbook, canViewWorksheet | L154: 0 | M154: All Members, Engineering-Team | N154: 2 | O154: TRUE | R154: =IF(COUNTIF('Active Employees'!B:B, B154)>0,"Y","N") -> Y | S154: No queries
A155: Julianne Campbell | B155: julianne.campbell@docker.com | C155: view | D155: View | E155: 45799.774 | I155: [Invited via SAML] | K155: canComment, canDownloadLegacyDocs, canViewDashboard, canViewDatasetOrSql, canViewWorkbook, canViewWorksheet | L155: 0 | M155: All Members, G&A | N155: 2 | O155: TRUE | R155: =IF(COUNTIF('Active Employees'!B:B, B155)>0,"Y","N") -> Y | S155: No queries
A156: Kathleen Swift | B156: kathleen.swift@docker.com | C156: view | D156: View | E156: 45799.774 | I156: [Invited via SAML] | K156: canComment, canDownloadLegacyDocs, canViewDashboard, canViewDatasetOrSql, canViewWorkbook, canViewWorksheet | L156: 0 | M156: All Members, G&A, People Team | N156: 3 | O156: TRUE | R156: =IF(COUNTIF('Active Employees'!B:B, B156)>0,"Y","N") -> Y | S156: No queries
A157: Katja Gussmann | B157: katja.gussmann@docker.com | C157: view | D157: View | E157: 45845.345 | I157: [Invited via SAML] | K157: canComment, canDownloadLegacyDocs, canViewDashboard, canViewDatasetOrSql, canViewWorkbook, canViewWorksheet | L157: 0 | M157: All Members, G&A | N157: 2 | O157: TRUE | R157: =IF(COUNTIF('Active Employees'!B:B, B157)>0,"Y","N") -> Y | S157: No queries
A158: Kavindira Amarendiran | B158: kavindira.amarendiran@docker.com | C158: analyze | D158: Analyze | E158: 45687.784 | I158: [Invited via SAML] | K158: canBasicExploreWorkbook, canComment, canDownloadLegacyDocs, canEditInputTable, canExploreWorkbook, canExport, canScheduleExport, canViewDashboard, canViewDatasetOrSql, canViewWorkbook, canViewWorksheet | L158: 0 | M158: All Members, Customer-Support | N158: 2 | O158: TRUE | P158: Y | R158: =IF(COUNTIF('Active Employees'!B:B, B158)>0,"Y","N") -> Y | S158: No queries
A159: Keirah Dein | B159: keirah.dein@docker.com | C159: view | D159: View | E159: 45799.816 | I159: [Invited via SAML] | K159: canComment, canDownloadLegacyDocs, canViewDashboard, canViewDatasetOrSql, canViewWorkbook, canViewWorksheet | L159: 0 | M159: All Members, Marketing | N159: 2 | O159: TRUE | R159: =IF(COUNTIF('Active Employees'!B:B, B159)>0,"Y","N") -> Y | S159: No queries
A160: Kelly Freet | B160: kelly.freet@docker.com | C160: view | D160: View | E160: 45799.774 | I160: [Invited via SAML] | K160: canComment, canDownloadLegacyDocs, canViewDashboard, canViewDatasetOrSql, canViewWorkbook, canViewWorksheet | L160: 0 | M160: All Members, Engineering-Team | N160: 2 | O160: TRUE | R160: =IF(COUNTIF('Active Employees'!B:B, B160)>0,"Y","N") -> Y | S160: No queries
A161: Kenan Salihbegovic | B161: kenan.salihbegovic@docker.com | C161: analyze | D161: Analyze | E161: 45799.774 | I161: [Invited via SAML] | K161: canBasicExploreWorkbook, canComment, canDownloadLegacyDocs, canEditInputTable, canExploreWorkbook, canExport, canScheduleExport, canViewDashboard, canViewDatasetOrSql, canViewWorkbook, canViewWorksheet | L161: 0 | M161: All Members, Exec, Marketing | N161: 3 | O161: TRUE | P161: Y | R161: =IF(COUNTIF('Active Employees'!B:B, B161)>0,"Y","N") -> Y | S161: No queries
A162: Kyle Marscellas | B162: kyle.marscellas@docker.com | C162: view | D162: View | E162: 45799.774 | I162: [Invited via SAML] | K162: canComment, canDownloadLegacyDocs, canViewDashboard, canViewDatasetOrSql, canViewWorkbook, canViewWorksheet | L162: 0 | M162: All Members, G&A, People Team | N162: 3 | O162: TRUE | R162: =IF(COUNTIF('Active Employees'!B:B, B162)>0,"Y","N") -> Y | S162: No queries
A163: Kyle Seely | B163: kyle.seely@docker.com | C163: view | D163: View | E163: 45799.774 | I163: [Invited via SAML] | K163: canComment, canDownloadLegacyDocs, canViewDashboard, canViewDatasetOrSql, canViewWorkbook, canViewWorksheet | L163: 0 | M163: All Members, Engineering-Team | N163: 2 | O163: TRUE | R163: =IF(COUNTIF('Active Employees'!B:B, B163)>0,"Y","N") -> Y | S163: No queries
A164: Kyle Trantham | B164: kyle.trantham@docker.com | C164: view | D164: View | E164: 45845.345 | I164: [Invited via SAML] | K164: canComment, canDownloadLegacyDocs, canViewDashboard, canViewDatasetOrSql, canViewWorkbook, canViewWorksheet | L164: 0 | M164: All Members, Engineering-Team | N164: 2 | O164: TRUE | R164: =IF(COUNTIF('Active Employees'!B:B, B164)>0,"Y","N") -> Y | S164: No queries
A165: Larissa Abaidoo | B165: larissa.abaidoo@docker.com | C165: view | D165: View | E165: 45708.753 | H165: Zoey Kramer | I165: zoey.kramer@docker.com | J165: 45708.529 | K165: canComment, canDownloadLegacyDocs, canViewDashboard, canViewDatasetOrSql, canViewWorkbook, canViewWorksheet | L165: 0 | M165: All Members, Product | N165: 2 | O165: TRUE | R165: =IF(COUNTIF('Active Employees'!B:B, B165)>0,"Y","N") -> Y | S165: No queries
A166: Laurent Goderre | B166: laurent.goderre@docker.com | C166: view | D166: View | E166: 45799.774 | I166: [Invited via SAML] | K166: canComment, canDownloadLegacyDocs, canViewDashboard, canViewDatasetOrSql, canViewWorkbook, canViewWorksheet | L166: 0 | M166: All Members, Engineering-Team | N166: 2 | O166: TRUE | R166: =IF(COUNTIF('Active Employees'!B:B, B166)>0,"Y","N") -> Y | S166: No queries
A167: Leslie Hopp | B167: leslie.hopp@docker.com | C167: analyze | D167: Analyze | E167: 45799.774 | I167: [Invited via SAML] | K167: canBasicExploreWorkbook, canComment, canDownloadLegacyDocs, canEditInputTable, canExploreWorkbook, canExport, canScheduleExport, canViewDashboard, canViewDatasetOrSql, canViewWorkbook, canViewWorksheet | L167: 0 | M167: All Members, Finance Team, Finance-Ops, G&A | N167: 4 | O167: TRUE | P167: Y | R167: =IF(COUNTIF('Active Employees'!B:B, B167)>0,"Y","N") -> Y | S167: No queries
A168: Linda Tan | B168: linda.tan@docker.com | C168: view | D168: View | E168: 45799.774 | I168: [Invited via SAML] | K168: canComment, canDownloadLegacyDocs, canViewDashboard, canViewDatasetOrSql, canViewWorkbook, canViewWorksheet | L168: 0 | M168: All Members, G&A, People Team | N168: 3 | O168: TRUE | R168: =IF(COUNTIF('Active Employees'!B:B, B168)>0,"Y","N") -> Y | S168: No queries
A169: Lizz Thabet | B169: lizz.thabet@docker.com | C169: view | D169: View | E169: 45799.774 | I169: [Invited via SAML] | K169: canComment, canDownloadLegacyDocs, canViewDashboard, canViewDatasetOrSql, canViewWorkbook, canViewWorksheet | L169: 0 | M169: All Members, Engineering-Team | N169: 2 | O169: TRUE | R169: =IF(COUNTIF('Active Employees'!B:B, B169)>0,"Y","N") -> Y | S169: No queries
A170: Lorena Rangel Hernandez | B170: lorena.rangel@docker.com | C170: view | D170: View | E170: 45799.774 | I170: [Invited via SAML] | K170: canComment, canDownloadLegacyDocs, canViewDashboard, canViewDatasetOrSql, canViewWorkbook, canViewWorksheet | L170: 0 | M170: All Members, Engineering-Team | N170: 2 | O170: TRUE | R170: =IF(COUNTIF('Active Employees'!B:B, B170)>0,"Y","N") -> Y | S170: No queries
A171: Luca Druda | B171: luca.druda@docker.com | C171: view | D171: View | E171: 45799.774 | I171: [Invited via SAML] | K171: canComment, canDownloadLegacyDocs, canViewDashboard, canViewDatasetOrSql, canViewWorkbook, canViewWorksheet | L171: 0 | M171: All Members, Engineering-Team | N171: 2 | O171: TRUE | R171: =IF(COUNTIF('Active Employees'!B:B, B171)>0,"Y","N") -> Y | S171: No queries
A172: Luca Guerra | B172: luca.guerra@docker.com | C172: view | D172: View | E172: 45831.649 | I172: [Invited via SAML] | K172: canComment, canDownloadLegacyDocs, canViewDashboard, canViewDatasetOrSql, canViewWorkbook, canViewWorksheet | L172: 0 | M172: All Members, Engineering-Team | N172: 2 | O172: TRUE | R172: =IF(COUNTIF('Active Employees'!B:B, B172)>0,"Y","N") -> Y | S172: No queries
A173: Lucas Bernalte Pérez | B173: lucas.bernalte@docker.com | C173: view | D173: View | E173: 45799.774 | I173: [Invited via SAML] | K173: canComment, canDownloadLegacyDocs, canViewDashboard, canViewDatasetOrSql, canViewWorkbook, canViewWorksheet | L173: 0 | M173: All Members, Engineering-Team | N173: 2 | O173: TRUE | R173: =IF(COUNTIF('Active Employees'!B:B, B173)>0,"Y","N") -> Y | S173: No queries
A174: Luke Sowinski | B174: luke.sowinski@docker.com | C174: view | D174: View | E174: 45799.774 | I174: [Invited via SAML] | K174: canComment, canDownloadLegacyDocs, canViewDashboard, canViewDatasetOrSql, canViewWorkbook, canViewWorksheet | L174: 0 | M174: All Members, Engineering-Team | N174: 2 | O174: TRUE | R174: =IF(COUNTIF('Active Employees'!B:B, B174)>0,"Y","N") -> Y | S174: No queries
...

Sheet Auth0 - Docker
A1: id | B1: email | C1: Reviewed by Josh | D1: Downgraded Permissions or Removed (If disabled for 90+ days, please remove) | E1: Notes
A2: samlp|docker|bryan.ross@docker.com | B2: ["editor-specific-apps","viewer-config","support-access","elevated-support-access"] | C2: x
A3: samlp|docker|gurleen.sethi@docker.com | B3: ["viewer-config","support-access","editor-users","editor-specific-apps","elevated-support-access","editor-connections"] | C3: x
A4: samlp|docker|ivan.californias@docker.com | B4: ["admin","elevated-support-access"] | C4: x
A5: samlp|docker|jonathan.dieu@docker.com | B5: ["elevated-support-access"] | C5: x
A6: samlp|docker|josh.newman@docker.com | B6: ["admin","elevated-support-access"] | C6: x
A7: samlp|docker|shawn.axsom@docker.com | B7: ["elevated-support-access"] | C7: x
A8: samlp|docker|siarhei.karneichyk@docker.com | B8: ["admin","elevated-support-access"] | C8: x

Sheet Datadog - Scout
A1: Name | B1: Role | C1: Active Employee | D1: Checked
A2: alexandre.valliereslagace@docker.com | B2: Datadog Read Only Role | C2: Yes | D2: C.F.
A3: andre.ramos@docker.com | B3: Datadog Standard Role | C3: Yes | D3: C.F.
A4: ben.griffiths@docker.com | B4: Datadog Admin Role | C4: Yes | D4: C.F.
A5: chase.frankenfeld@docker.com | B5: Datadog Standard Role | C5: Yes | D5: C.F.
A6: chris.ainsworth-patrick@docker.com | B6: Datadog Standard Role | C6: Yes | D6: C.F.
A7: christian.dupuis@docker.com | B7: Datadog Admin Role | C7: Yes | D7: C.F.
A8: david.dooling@docker.com | B8: Datadog Standard Role | C8: Yes | D8: C.F.
A9: laurent.goderre@docker.com | B9: Datadog Standard Role | C9: Yes | D9: C.F.
A10: nate.fitch@docker.com | B10: Datadog Read Only Role | C10: Yes | D10: C.F.
A11: neil.prosser@docker.com | B11: Datadog Admin Role | C11: Yes | D11: C.F.
A12: chad.fryer@docker.com | B12: Datadog Read Only Role | C12: Yes | D12: C.F.

Sheet Github - Scout (atomisthq)
A1: login | B1: name | C1: tfa_enabled | D1: tfa_level | E1: tfa_required_by | F1: is_public | G1: role | H1: saml_name_id | I1: organization_roles_count | J1: Active Employee | K1: Checked
A2: AndreSilva1993 | B2: André Silva | C2: TRUE | D2: insecure | F2: FALSE | G2: Member | I2: 0 | J2: Yes | K2: C.F.
A3: andrestylianos | B3: André Stylianos Ramos | C3: TRUE | D3: secure | F3: FALSE | G3: Member | I3: 0 | J3: Yes | K3: C.F.
A4: atomist-bot | B4: Atomist Bot | C4: TRUE | D4: insecure | F4: FALSE | G4: Member | I4: 0
A5: benja-M-1 | B5: Benjamin Grandfond | C5: TRUE | D5: insecure | F5: FALSE | G5: Member | I5: 0 | J5: Yes | K5: C.F.
A6: Bkblodget | B6: Britney Blodget | C6: TRUE | D6: insecure | F6: FALSE | G6: Member | I6: 0 | J6: Yes | K6: C.F.
A7: cdupuis | B7: Christian Dupuis | C7: TRUE | D7: insecure | F7: FALSE | G7: Owner | I7: 0 | J7: Yes | K7: C.F.
A8: chadfryer | B8: Chad Fryer | C8: TRUE | D8: secure | F8: FALSE | G8: Member | I8: 0 | J8: Yes | K8: C.F.
A9: chasefrankenfeld | B9: Chase Frankenfeld | C9: TRUE | D9: insecure | F9: FALSE | G9: Member | I9: 0 | J9: Yes | K9: C.F.
A10: chrispatrick | B10: Chris Ainsworth-Patrick | C10: TRUE | D10: secure | F10: FALSE | G10: Member | I10: 0 | J10: Yes | K10: C.F.
A11: ckenna | B11: Christopher Kenna | C11: TRUE | D11: secure | F11: FALSE | G11: Member | I11: 0 | J11: Yes | K11: C.F.
A12: Daniel-Kolev | B12: Daniel Kolev | C12: TRUE | D12: secure | F12: FALSE | G12: Member | I12: 0 | J12: Yes | K12: C.F.
A13: EmreUgurluDocker | B13: Emre Ugurlu | C13: TRUE | D13: insecure | F13: FALSE | G13: Member | I13: 0 | J13: Yes | K13: C.F.
A14: fjmcs | B14: Fiona McShane | C14: TRUE | D14: insecure | F14: FALSE | G14: Owner | I14: 0 | J14: Yes | K14: C.F.
A15: jcarter3 | B15: Jeff Carter | C15: TRUE | D15: insecure | F15: FALSE | G15: Member | I15: 0 | J15: Yes | K15: C.F.
A16: jeanlaurent | B16: Jean-Laurent de Morlhon | C16: TRUE | D16: insecure | F16: FALSE | G16: Owner | I16: 0 | J16: Yes | K16: C.F.
... A30: wolfshirts | B30: Ross Russell | C30: TRUE | D30: insecure | F30: FALSE | G30: Member | I30: 0 | J30: Yes | K30: C.F.

Sheet Github - Scout (atomist-contain
A1: login | B1: name | C1: tfa_enabled | D1: tfa_level | E1: tfa_required_by | F1: is_public | G1: role | H1: saml_name_id | I1: organization_roles_count | J1: Active Employee | K1: Checked
A2: atomist-bot | B2: Atomist Bot | C2: TRUE | D2: insecure | F2: FALSE | G2: Owner | I2: 0
A3: benja-M-1 | B3: Benjamin Grandfond | C3: TRUE | D3: insecure | F3: FALSE | G3: Member | I3: 0 | J3: Yes | K3: C.F.
A4: cdupuis | B4: Christian Dupuis | C4: TRUE | D4: insecure | F4: FALSE | G4: Owner | I4: 0 | J4: Yes | K4: C.F.
A5: chadfryer | B5: Chad Fryer | C5: TRUE | D5: secure | F5: FALSE | G5: Member | I5: 0 | J5: Yes | K5: C.F.
A6: EmreUgurluDocker | B6: Emre Ugurlu | C6: TRUE | D6: insecure | F6: FALSE | G6: Member | I6: 0 | J6: Yes | K6: C.F.
A7: Kyle-Trantham | B7: Kyle Trantham | C7: TRUE | D7: secure | F7: FALSE | G7: Member | I7: 0 | J7: Yes | K7: C.F.
A8: LucaGuerra | B8: Luca Guerra | C8: TRUE | D8: secure | F8: FALSE | G8: Member | I8: 0 | J8: Yes | K8: C.F.
A9: neilprosser | B9: Neil Prosser | C9: TRUE | D9: insecure | F9: FALSE | G9: Owner | I9: 0 | J9: Yes | K9: C.F.
A10: quentin-laplanche | B10: Quentin Laplanche | C10: TRUE | D10: secure | F10: FALSE | G10: Member | I10: 0 | J10: Yes | K10: C.F.
A11: temenuzhka-thede | B11: Tem Thede | C11: TRUE | D11: secure | F11: FALSE | G11: Owner | I11: 0 | J11: Yes | K11: C.F.
A12: uid0 | B12: Ian Wilson | C12: TRUE | D12: insecure | F12: FALSE | G12: Member | I12: 0 | J12: Yes | K12: C.F.
A13: vallieres | B13: Alexandre Vallières-Lagacé | C13: TRUE | D13: insecure | F13: FALSE | G13: Owner | I13: 0 | J13: Yes | K13: C.F.
A14: whostolebenfrog | B14: Ben Griffiths | C14: TRUE | D14: insecure | F14: FALSE | G14: Owner | I14: 0 | J14: Yes | K14: C.F.
A15: wolfshirts | B15: Ross Russell | C15: TRUE | D15: insecure | F15: FALSE | G15: Member | I15: 0 | J15: Yes | K15: C.F.

Sheet Github - Scout (docker-hardened
A1: login | B1: name | C1: tfa_enabled | D1: tfa_level | E1: tfa_required_by | F1: is_public | G1: role | H1: saml_name_id | I1: organization_roles_count | J1: Active Employee | K1: Checked | L1: Note
A2: sakoht | B2: Scott Smith | C2: TRUE | D2: insecure | F2: FALSE | G2: Member | H2: scott_smith@docker.com | I2: 0 | J2: Contractor
A3: 1wilkens | B3: Florian Wilkens | C3: TRUE | D3: secure | F3: FALSE | G3: Member | I3: 0 | J3: No | K3: C.F.
A4: ajeetraina | B4: Ajeet Singh Raina, Docker Captain, ARM Innovator, | C4: TRUE | D4: insecure | F4: FALSE | G4: Member | I4: 0 | J4: No | K4: C.F.
A5: dimomatt | B5: Matthew Dimond | C5: TRUE | D5: secure | F5: FALSE | G5: Member | I5: 0 | J5: No | K5: C.F.
A6: jakoblell | B6: Jakob Lell | C6: TRUE | D6: secure | F6: FALSE | G6: Member | I6: 0 | J6: No | K6: C.F.
A7: kenanwarren | B7: Kenan Warren | C7: TRUE | D7: secure | F7: FALSE | G7: Member | I7: 0 | J7: No | K7: C.F.
A8: MrWoo034 | B8: Leif A Brockman | C8: TRUE | D8: insecure | F8: FALSE | G8: Member | I8: 0 | J8: No | K8: C.F.
A9: stze | B9: Stephan Zeisberg | C9: TRUE | D9: secure | F9: FALSE | G9: Member | I9: 0 | J9: No | K9: C.F.
A10: dockermfies | C10: TRUE | D10: secure | F10: FALSE | G10: Member | I10: 0 | K10: C.F.
A11: genco-srl | C11: TRUE | D11: secure | F11: FALSE | G11: Member | I11: 0 | K11: C.F.
A12: hannahSiimpl | C12: FALSE | D12: disabled | F12: FALSE | G12: Member | I12: 0 | K12: C.F.
A13: Ollrogge | B13: Nils | C13: TRUE | D13: secure | F13: FALSE | G13: Member | I13: 0 | K13: C.F.
A14: trevorbye | C14: TRUE | D14: insecure | F14: FALSE | G14: Member | I14: 0 | K14: C.F.
A15: zubes1 | C15: TRUE | D15: insecure | F15: FALSE | G15: Member | I15: 0 | K15: C.F.
A16: tianon-sso | B16: Andrew Page | C16: TRUE | D16: secure | F16: FALSE | G16: Member | H16: tianon.gravi@docker.com | I16: 0 | J16: Yes | K16: C.F. | L16: Name and email do not match
A17: a-dubs | B17: Alec Warren | C17: TRUE | D17: secure | F17: FALSE | G17: Member | H17: alec.warren@docker.com | I17: 0 | J17: Yes | K17: C.F.
A18: AndreSilva1993 | B18: André Silva | C18: TRUE | D18: insecure | F18: FALSE | G18: Member | H18: andre.silva@docker.com | I18: 0 | J18: Yes | K18: C.F.
A19: andrestylianos | B19: André Stylianos Ramos | C19: TRUE | D19: secure | F19: FALSE | G19: Member | H19: andre.ramos@docker.com | I19: 0 | J19: Yes | K19: C.F.
A20: benharris-docker | B20: Ben Harris | C20: TRUE | D20: secure | F20: FALSE | G20: Member | H20: ben.harris@docker.com | I20: 0 | J20: Yes | K20: C.F.
A21: benja-M-1 | B21: Benjamin Grandfond | C21: TRUE | D21: insecure | F21: FALSE | G21: Member | H21: benjamin.grandfond@docker.com | I21: 0 | J21: Yes | K21: C.F.
A22: Bkblodget | B22: Britney Blodget | C22: TRUE | D22: insecure | F22: FALSE | G22: Member | H22: britney.blodget@docker.com | I22: 0 | J22: Yes | K22: C.F.
A23: blueprismo | B23: Enin Kaduk | C23: TRUE | D23: insecure | F23: FALSE | G23: Member | H23: enin.kaduk@docker.com | I23: 0 | J23: Yes | K23: C.F.
A24: brunoproduit | B24: Bruno de Sousa | C24: TRUE | D24: secure | F24: FALSE | G24: Member | I24: 0 | J24: Yes | K24: C.F.
A25: cdupuis | B25: Christian Dupuis | C25: TRUE | D25: insecure | F25: FALSE | G25: Owner | H25: christian.dupuis@docker.com | I25: 0 | J25: Yes | K25: C.F.
A26: craig-osterhout | B26: Craig Osterhout | C26: TRUE | D26: insecure | F26: FALSE | G26: Member | I26: 0 | J26: Yes | K26: C.F.
A27: elliotrushton | B27: Elliot Rushton | C27: TRUE | D27: secure | F27: FALSE | G27: Member | H27: elliot.rushton@docker.com | I27: 0 | J27: Yes | K27: C.F.
A28: fabienne0708 | B28: Fabienne Anhalt | C28: FALSE | D28: disabled | F28: FALSE | G28: Member | H28: fabienne.anhalt@docker.com | I28: 0 | J28: Yes | K28: C.F.
A29: fazlan-nazeem | B29: Fazlan Nazeem | C29: TRUE | D29: insecure | F29: FALSE | G29: Member | I29: 0 | J29: Yes | K29: C.F.
A30: ForestEckhardt | B30: Forest Eckhardt | C30: TRUE | D30: insecure | F30: FALSE | G30: Member | H30: forest.eckhardt@docker.com | I30: 0 | J30: Yes | K30: C.F.
A31: jeffreystrauss | B31: Jeff Strauss | C31: TRUE | D31: insecure | F31: FALSE | G31: Owner | I31: 0 | J31: Yes | K31: C.F.
A32: john-craft | B32: John Craft | C32: TRUE | D32: insecure | F32: FALSE | G32: Member | H32: john.craft@docker.com | I32: 0 | J32: Yes | K32: C.F.
A33: jtwils17 | B33: Julia Wilson | C33: TRUE | D33: insecure | F33: FALSE | G33: Member | H33: julia.wilson@docker.com | I33: 0 | J33: Yes | K33: C.F.
A34: Kyle-Trantham | B34: Kyle Trantham | C34: TRUE | D34: secure | F34: FALSE | G34: Member | I34: 0 | J34: Yes | K34: C.F.
A35: LaurentGoderre | B35: Laurent Goderre | C35: TRUE | D35: insecure | F35: FALSE | G35: Member | H35: laurent.goderre@docker.com | I35: 0 | J35: Yes | K35: C.F.
A36: lizzthabet | B36: Lizz Thabet | C36: TRUE | D36: insecure | F36: FALSE | G36: Member | H36: lizz.thabet@docker.com | I36: 0 | J36: Yes | K36: C.F.
A37: LucaGuerra | B37: Luca Guerra | C37: TRUE | D37: secure | F37: FALSE | G37: Member | I37: 0 | J37: Yes | K37: C.F.
A38: lukoboi | B38: Luke Sowinski | C38: TRUE | D38: insecure | F38: FALSE | G38: Member | H38: luke.sowinski@docker.com | I38: 0 | J38: Yes | K38: C.F.
A39: mikedon | B39: Michael Donovan | C39: TRUE | D39: secure | F39: FALSE | G39: Member | I39: 0 | J39: Yes | K39: C.F.
A40: mpermar | B40: Martín Pérez | C40: TRUE | D40: insecure | F40: FALSE | G40: Member | H40: martin.perez@docker.com | I40: 0 | J40: Yes | K40: C.F.
A41: natebDev | B41: Nate Bittinger | C41: TRUE | D41: insecure | F41: FALSE | G41: Member | H41: nate.bittinger@docker.com | I41: 0 | J41: Yes | K41: C.F.
A42: nathancar11c-code | B42: Nathan Carlson | C42: FALSE | D42: disabled | F42: FALSE | G42: Member | H42: nathan.carlson@docker.com | I42: 0 | J42: Yes | K42: C.F.
A43: neersighted | B43: Bjorn Neergaard | C43: TRUE | D43: secure | F43: TRUE | G43: Member | H43: bjorn.neergaard@docker.com | I43: 0 | J43: Yes | K43: C.F.
A44: neilprosser | B44: Neil Prosser | C44: TRUE | D44: insecure | F44: FALSE | G44: Owner | H44: neil.prosser@docker.com | I44: 0 | J44: Yes | K44: C.F.
A45: orndorffgrant | B45: Grant Orndorff | C45: TRUE | D45: insecure | F45: FALSE | G45: Member | H45: grant.orndorff@docker.com | I45: 0 | J45: Yes | K45: C.F.
A46: pkhanchandan | B46: Prashant Khanchandani | C46: TRUE | D46: secure | F46: FALSE | G46: Member | I46: 0 | J46: Yes | K46: C.F.
A47: quentin-laplanche | B47: Quentin Laplanche | C47: TRUE | D47: secure | F47: FALSE | G47: Member | I47: 0 | J47: Yes | K47: C.F.
A48: sarahsanders-docker | B48: Sarah Sanders | C48: TRUE | D48: insecure | F48: FALSE | G48: Member | I48: 0 | J48: Yes | K48: C.F.
A49: temenuzhka-thede | B49: Tem Thede | C49: TRUE | D49: secure | F49: FALSE | G49: Owner | H49: temenuzhka.thede@docker.com | I49: 0 | J49: Yes | K49: C.F.
A50: usha-mandya | B50: Usha Mandya | C50: TRUE | D50: insecure | F50: FALSE | G50: Member | I50: 0 | J50: Yes | K50: C.F.
A51: vallieres | B51: Alexandre Vallières-Lagacé | C51: TRUE | D51: insecure | F51: FALSE | G51: Member | I51: 0 | J51: Yes | K51: C.F.
A52: whalelines | B52: David Dooling | C52: TRUE | D52: insecure | F52: FALSE | G52: Owner | H52: david.dooling@docker.com | I52: 0 | J52: Yes | K52: C.F.
A53: whostolebenfrog | B53: Ben Griffiths | C53: TRUE | D53: insecure | F53: FALSE | G53: Owner | H53: ben.griffiths@docker.com | I53: 0 | J53: Yes | K53: C.F.
A54: wolfshirts | B54: Ross Russell | C54: TRUE | D54: insecure | F54: FALSE | G54: Member | I54: 0 | J54: Yes | K54: C.F.
A55: yosifkit | B55: Joseph Ferguson | C55: TRUE | D55: insecure | F55: FALSE | G55: Member | H55: joseph.ferguson@docker.com | I55: 0 | J55: Yes | K55: C.F.
A56: dhi-bot | B56: Docker Hardened Images [bot] | C56: TRUE | D56: secure | F56: FALSE | G56: Member | I56: 0 | K56: C.F.
A57: docker-scout | B57: Docker Scout [bot] | C57: FALSE | D57: disabled | F57: FALSE | G57: Member | I57: 0 | K57: C.F.

Sheet Okta
A1: Resource set | B1: Contained resources | C1: Resources constrained with conditions | D1: Role | E1: Contained permissions | F1: Permissions constrained with conditions | G1: Admin | H1: Login | I1: Email | J1: Last Login_ISO8601 | K1: role assigned to | L1: Expires in | M1: Bundle name | N1: VSLOOKUP | O1: Active Employee | P1: Reviewed by: | Q1: Downgraded Permissions or Removed (If disabled for 90+ days, please remove) | R1: Notes
B2: AWS IAM Identity Center | C2: FALSE | D2: AppAdmin | E2: Standard Role | F2: FALSE | G2: Alex Hokanson | H2: alex.hokanson@docker.com | I2: alex.hokanson@docker.com | J2: 2025-10-02T14:05:02.000Z | K2: group: Infrastructure Team | N2: =VLOOKUP(I2,'Active Employees'!$B$2:$B$498,1,false) -> alex.hokanson@docker.com | O2: Yes
B3: AWSSSO_OktaAppAccess | C3: FALSE | D3: GroupAdmin | E3: Standard Role | F3: FALSE | G3: Alex Hokanson | H3: alex.hokanson@docker.com | I3: alex.hokanson@docker.com | J3: 2025-10-02T14:05:02.000Z | K3: group: Infrastructure Team | N3: =VLOOKUP(I3,'Active Employees'!$B$2:$B$498,1,false) -> alex.hokanson@docker.com | O3: Yes
B4: AWSSSO_BillingManagers | C4: FALSE | D4: GroupAdmin | E4: Standard Role | F4: FALSE | G4: Alex Hokanson | H4: alex.hokanson@docker.com | I4: alex.hokanson@docker.com | J4: 2025-10-02T14:05:02.000Z | K4: group: Infrastructure Team | N4: =VLOOKUP(I4,'Active Employees'!$B$2:$B$498,1,false) -> alex.hokanson@docker.com | O4: Yes
B5: AWSSSO_CloudExperimentEngineers | C5: FALSE | D5: GroupAdmin | E5: Standard Role | F5: FALSE | G5: Alex Hokanson | H5: alex.hokanson@docker.com | I5: alex.hokanson@docker.com | J5: 2025-10-02T14:05:02.000Z | K5: group: Infrastructure Team | N5: =VLOOKUP(I5,'Active Employees'!$B$2:$B$498,1,false) -> alex.hokanson@docker.com | O5: Yes
B6: AWSSSO_HubCloudEngineers | C6: FALSE | D6: GroupAdmin | E6: Standard Role | F6: FALSE | G6: Alex Hokanson | H6: alex.hokanson@docker.com | I6: alex.hokanson@docker.com | J6: 2025-10-02T14:05:02.000Z | K6: group: Infrastructure Team | N6: =VLOOKUP(I6,'Active Employees'!$B$2:$B$498,1,false) -> alex.hokanson@docker.com | O6: Yes
B7: AWSSSO_MarketplaceReportingUsers | C7: FALSE | D7: GroupAdmin | E7: Standard Role | F7: FALSE | G7: Alex Hokanson | H7: alex.hokanson@docker.com | I7: alex.hokanson@docker.com | J7: 2025-10-02T14:05:02.000Z | K7: group: Infrastructure Team | N7: =VLOOKUP(I7,'Active Employees'!$B$2:$B$498,1,false) -> alex.hokanson@docker.com | O7: Yes
B8: AWSSSO_SalesOperations | C8: FALSE | D8: GroupAdmin | E8: Standard Role | F8: FALSE | G8: Alex Hokanson | H8: alex.hokanson@docker.com | I8: alex.hokanson@docker.com | J8: 2025-10-02T14:05:02.000Z | K8: group: Infrastructure Team | N8: =VLOOKUP(I8,'Active Employees'!$B$2:$B$498,1,false) -> alex.hokanson@docker.com | O8: Yes
B9: AWSSSO_HubCloudAdministrators | C9: FALSE | D9: GroupAdmin | E9: Standard Role | F9: FALSE | G9: Alex Hokanson | H9: alex.hokanson@docker.com | I9: alex.hokanson@docker.com | J9: 2025-10-02T14:05:02.000Z | K9: group: Infrastructure Team | N9: =VLOOKUP(I9,'Active Employees'!$B$2:$B$498,1,false) -> alex.hokanson@docker.com | O9: Yes
B10: AWSSSO_ComplianceEngineers | C10: FALSE | D10: GroupAdmin | E10: Standard Role | F10: FALSE | G10: Alex Hokanson | H10: alex.hokanson@docker.com | I10: alex.hokanson@docker.com | J10: 2025-10-02T14:05:02.000Z | K10: group: Infrastructure Team | N10: =VLOOKUP(I10,'Active Employees'!$B$2:$B$498,1,false) -> alex.hokanson@docker.com | O10: Yes
B11: AWSSSO_DeveloperPlatformEngineers | C11: FALSE | D11: GroupAdmin | E11: Standard Role | F11: FALSE | G11: Alex Hokanson | H11: alex.hokanson@docker.com | I11: alex.hokanson@docker.com | J11: 2025-10-02T14:05:02.000Z | K11: group: Infrastructure Team | N11: =VLOOKUP(I11,'Active Employees'!$B$2:$B$498,1,false) -> alex.hokanson@docker.com | O11: Yes
B12: AWSSSO_DataEngineers | C12: FALSE | D12: GroupAdmin | E12: Standard Role | F12: FALSE | G12: Alex Hokanson | H12: alex.hokanson@docker.com | I12: alex.hokanson@docker.com | J12: 2025-10-02T14:05:02.000Z | K12: group: Infrastructure Team | N12: =VLOOKUP(I12,'Active Employees'!$B$2:$B$498,1,false) -> alex.hokanson@docker.com | O12: Yes
B13: AWSSSO_AutoBuildManagers | C13: FALSE | D13: GroupAdmin | E13: Standard Role | F13: FALSE | G13: Alex Hokanson | H13: alex.hokanson@docker.com | I13: alex.hokanson@docker.com | J13: 2025-10-02T14:05:02.000Z | K13: group: Infrastructure Team | N13: =VLOOKUP(I13,'Active Employees'!$B$2:$B$498,1,false) -> alex.hokanson@docker.com | O13: Yes
... B121: AWSSSO_GoToMarketAITeam | C121: FALSE | D121: GroupAdmin | E121: Standard Role | F121: FALSE | G121: Jonathan Dieu | H121: jonathan.dieu@docker.com | I121: jonathan.dieu@docker.com | J121: 2025-10-02T13:50:51.000Z | K121: group: Infrastructure Team | N121: =VLOOKUP(I121,'Active Employees'!$B$2:$B$498,1,false) -> jonathan.dieu@docker.com | O121: Yes
A122: Create Group Resource Set | B122: All groups | C122: FALSE | D122: Create Group Admin | E122: okta.groups.manage | F122: FALSE | G122: Josh Newman | H122: josh.newman@docker.com | I122: josh.newman@docker.com | J122: 2025-10-02T17:19:19.000Z | K122: individual | N122: =VLOOKUP(I122,'Active Employees'!$B$2:$B$498,1,false) -> josh.newman@docker.com | O122: Yes
B123: All | C123: FALSE | D123: AppAdmin | E123: Standard Role | F123: FALSE | G123: Josh Newman | H123: josh.newman@docker.com | I123: josh.newman@docker.com | J123: 2025-10-02T17:19:19.000Z | K123: individual | N123: =VLOOKUP(I123,'Active Employees'!$B$2:$B$498,1,false) -> josh.newman@docker.com | O123: Yes
B124: All OpenID Connect Client apps | C124: FALSE | D124: ApiAccessManagementAdmin | E124: Standard Role | F124: FALSE | G124: Josh Newman | H124: josh.newman@docker.com | I124: josh.newman@docker.com | J124: 2025-10-02T17:19:19.000Z | K124: individual | N124: =VLOOKUP(I124,'Active Employees'!$B$2:$B$498,1,false) -> josh.newman@docker.com | O124: Yes
B125: All | C125: FALSE | D125: GroupMembershipAdmin | E125: Standard Role | F125: FALSE | G125: Josh Newman | H125: josh.newman@docker.com | I125: josh.newman@docker.com | J125: 2025-10-02T17:19:19.000Z | K125: individual | N125: =VLOOKUP(I125,'Active Employees'!$B$2:$B$498,1,false) -> josh.newman@docker.com | O125: Yes
B126: All | C126: FALSE | D126: GroupAdmin | E126: Standard Role | F126: FALSE | G126: Josh Newman | H126: josh.newman@docker.com | I126: josh.newman@docker.com | J126: 2025-10-02T17:19:19.000Z | K126: individual | N126: =VLOOKUP(I126,'Active Employees'!$B$2:$B$498,1,false) -> josh.newman@docker.com | O126: Yes
B127: All | C127: FALSE | D127: HelpDeskAdmin | E127: Standard Role | F127: FALSE | G127: Kottu Jessy Kanth | H127: kottu_jessykanth@docker.com | I127: kottu_jessykanth@docker.com | J127: 2025-10-02T16:20:31.000Z | K127: individual | N127: =VLOOKUP(I127,'Active Employees'!$B$2:$B$498,1,false) -> #N/A | O127: Yes
B128: All | C128: FALSE | D128: ReadOnlyAdmin | E128: Standard Role | F128: FALSE | G128: Kottu Jessy Kanth | H128: kottu_jessykanth@docker.com | I128: kottu_jessykanth@docker.com | J128: 2025-10-02T16:20:31.000Z | K128: individual | N128: =VLOOKUP(I128,'Active Employees'!$B$2:$B$498,1,false) -> #N/A | O128: Yes
B129: All | C129: FALSE | D129: GroupAdmin | E129: Standard Role | F129: FALSE | G129: Kottu Jessy Kanth | H129: kottu_jessykanth@docker.com | I129: kottu_jessykanth@docker.com | J129: 2025-10-02T16:20:31.000Z | K129: individual | N129: =VLOOKUP(I129,'Active Employees'!$B$2:$B$498,1,false) -> #N/A | O129: Yes
A130: Workflows Resource Set | C130: FALSE | D130: Workflows Administrator | E130: okta.workflows.invoke, okta.workflows.folders.manage, okta.workflows.connectors.manage, okta.workflows.tables.manage, okta.workflows.flows.invoke, okta.workflows.connections.manage, okta.workflows.flows.manage | F130: FALSE | G130: Kyle Trantham | H130: kyle.trantham@docker.com | I130: kyle.trantham@docker.com | J130: 2025-10-02T14:09:47.000Z | K130: individual | N130: =VLOOKUP(I130,'Active Employees'!$B$2:$B$498,1,false) -> kyle.trantham@docker.com | O130: Yes
B131: All | C131: FALSE | D131: ReadOnlyAdmin | E131: Standard Role | F131: FALSE | G131: Kyle Trantham | H131: kyle.trantham@docker.com | I131: kyle.trantham@docker.com | J131: 2025-10-02T14:09:47.000Z | K131: individual | N131: =VLOOKUP(I131,'Active Employees'!$B$2:$B$498,1,false) -> kyle.trantham@docker.com | O131: Yes
B132: All | C132: FALSE | D132: HelpDeskAdmin | E132: Standard Role | F132: FALSE | G132: Malarvannan Velu | H132: malarvannan_velu@docker.com | I132: malarvannan_velu@docker.com | J132: 2025-10-02T01:06:52.000Z | K132: individual | N132: =VLOOKUP(I132,'Active Employees'!$B$2:$B$498,1,false) -> #N/A | O132: Yes
B133: All | C133: FALSE | D133: ReadOnlyAdmin | E133: Standard Role | F133: FALSE | G133: Malarvannan Velu | H133: malarvannan_velu@docker.com | I133: malarvannan_velu@docker.com | J133: 2025-10-02T01:06:52.000Z | K133: individual | N133: =VLOOKUP(I133,'Active Employees'!$B$2:$B$498,1,false) -> #N/A | O133: Yes
B134: All | C134: FALSE | D134: GroupAdmin | E134: Standard Role | F134: FALSE | G134: Malarvannan Velu | H134: malarvannan_velu@docker.com | I134: malarvannan_velu@docker.com | J134: 2025-10-02T01:06:52.000Z | K134: individual | N134: =VLOOKUP(I134,'Active Employees'!$B$2:$B$498,1,false) -> #N/A | O134: Yes
B135: TeamOhana Users | C135: FALSE | D135: GroupMembershipAdmin | E135: Standard Role | F135: FALSE | G135: Pooja Agrawal | H135: pooja.agrawal@docker.com | I135: pooja.agrawal@docker.com | J135: 2025-10-01T22:02:16.000Z | K135: individual | N135: =VLOOKUP(I135,'Active Employees'!$B$2:$B$498,1,false) -> pooja.agrawal@docker.com | O135: Yes
B136: All | C136: FALSE | D136: GroupAdmin | E136: Standard Role | F136: FALSE | G136: Pooja Agrawal | H136: pooja.agrawal@docker.com | I136: pooja.agrawal@docker.com | J136: 2025-10-01T22:02:16.000Z | K136: individual | N136: =VLOOKUP(I136,'Active Employees'!$B$2:$B$498,1,false) -> pooja.agrawal@docker.com | O136: Yes
B137: All | C137: FALSE | D137: AppAdmin | E137: Standard Role | F137: FALSE | G137: Quentin Laplanche | H137: quentin.laplanche@docker.com | I137: quentin.laplanche@docker.com | J137: 2025-10-02T12:47:17.000Z | K137: individual | N137: =VLOOKUP(I137,'Active Employees'!$B$2:$B$498,1,false) -> quentin.laplanche@docker.com | O137: Yes
B138: All | C138: FALSE | D138: ReadOnlyAdmin | E138: Standard Role | F138: FALSE | G138: Quentin Laplanche | H138: quentin.laplanche@docker.com | I138: quentin.laplanche@docker.com | J138: 2025-10-02T12:47:17.000Z | K138: individual | N138: =VLOOKUP(I138,'Active Employees'!$B$2:$B$498,1,false) -> quentin.laplanche@docker.com | O138: Yes
B139: AWS IAM Identity Center | C139: FALSE | D139: AppAdmin | E139: Standard Role | F139: FALSE | G139: Rob Braden | H139: james.braden@docker.com | I139: james.braden@docker.com | J139: 2025-10-02T17:26:32.000Z | K139: group: Infrastructure Team | N139: =VLOOKUP(I139,'Active Employees'!$B$2:$B$498,1,false) -> james.braden@docker.com | O139: Yes
B140: AWSSSO_OktaAppAccess | C140: FALSE | D140: GroupAdmin | E140: Standard Role | F140: FALSE | G140: Rob Braden | H140: james.braden@docker.com | I140: james.braden@docker.com | J140: 2025-10-02T17:26:32.000Z | K140: group: Infrastructure Team | N140: =VLOOKUP(I140,'Active Employees'!$B$2:$B$498,1,false) -> james.braden@docker.com | O140: Yes
B141: AWSSSO_BillingManagers | C141: FALSE | D141: GroupAdmin | E141: Standard Role | F141: FALSE | G141: Rob Braden | H141: james.braden@docker.com | I141: james.braden@docker.com | J141: 2025-10-02T17:26:32.000Z | K141: group: Infrastructure Team | N141: =VLOOKUP(I141,'Active Employees'!$B$2:$B$498,1,false) -> james.braden@docker.com | O141: Yes
B142: AWSSSO_CloudExperimentEngineers | C142: FALSE | D142: GroupAdmin | E142: Standard Role | F142: FALSE | G142: Rob Braden | H142: james.braden@docker.com | I142: james.braden@docker.com | J142: 2025-10-02T17:26:32.000Z | K142: group: Infrastructure Team | N142: =VLOOKUP(I142,'Active Employees'!$B$2:$B$498,1,false) -> james.braden@docker.com | O142: Yes
... B261: All | C261: FALSE | D261: GroupAdmin | E261: Standard Role | F261: FALSE | G261: Tem Thede | H261: temenuzhka.thede@docker.com | I261: temenuzhka.thede@docker.com | J261: 2025-10-02T18:08:07.000Z | K261: individual | N261: =VLOOKUP(I261,'Active Employees'!$B$2:$B$498,1,false) -> temenuzhka.thede@docker.com | O261: Yes
B262: All | C262: FALSE | D262: ReadOnlyAdmin | E262: Standard Role | F262: FALSE | G262: anecdotes anecdotes | H262: docker@anecdotes.ai | I262: docker@anecdotes.ai | J262: 2023-03-14T15:32:49.000Z | K262: individual | O262: Service Account
B263: All | C263: FALSE | D263: SuperOrgAdmin | E263: Standard Role | F263: FALSE | G263: API Integration | H263: svc-apiintegration@docker.com | I263: svc-apiintegration@docker.com | J263: 2025-03-25T16:48:19.000Z | K263: individual | N263: =VLOOKUP(I263,'Active Employees'!$B$2:$B$498,1,false) -> #N/A | O263: Service Account
B264: All | C264: FALSE | D264: ReadOnlyAdmin | E264: Standard Role | F264: FALSE | G264: DataGrail Integrations | H264: datagrail-integration@docker.com | I264: datagrail-integration@docker.com | J264: 2023-06-01T20:19:45.000Z | K264: individual | N264: =VLOOKUP(I264,'Active Employees'!$B$2:$B$498,1,false) -> #N/A | O264: Service Account
B265: All | C265: FALSE | D265: ReadOnlyAdmin | E265: Standard Role | F265: FALSE | G265: Jira Automation Integration | H265: svc-jira-automation-integration@docker.com | I265: svc-jira-automation-integration@docker.com | J265: 2025-10-02T15:29:58.000Z | K265: individual | N265: =VLOOKUP(I265,'Active Employees'!$B$2:$B$498,1,false) -> #N/A | O265: Service Account
B266: All | C266: FALSE | D266: SuperOrgAdmin | E266: Standard Role | F266: FALSE | G266: Okta Integration | H266: it+okta@docker.com | I266: it+okta@docker.com | J266: 2024-07-22T17:05:33.000Z | K266: individual | N266: =VLOOKUP(I266,'Active Employees'!$B$2:$B$498,1,false) -> #N/A | O266: Service Account
B267: All | C267: FALSE | D267: ReadOnlyAdmin | E267: Standard Role | F267: FALSE | G267: Okta Read-Only | H267: okta.readonly@docker.com | I267: okta.readonly@docker.com | J267: 2025-10-02T18:14:07.000Z | K267: individual | N267: =VLOOKUP(I267,'Active Employees'!$B$2:$B$498,1,false) -> #N/A | O267: Service Account
B268: All | C268: FALSE | D268: ReadOnlyAdmin | E268: Standard Role | F268: FALSE | G268: Oomnitza Integration | H268: oomnitza-integration@docker.com | I268: oomnitza-integration@docker.com | J268: 2023-03-10T19:04:52.000Z | K268: individual | N268: =VLOOKUP(I268,'Active Employees'!$B$2:$B$498,1,false) -> #N/A | O268: Service Account
B269: All | C269: FALSE | D269: ReadOnlyAdmin | E269: Standard Role | F269: FALSE | G269: pritunl integration | H269: pritunl-integration@docker.com | I269: pritunl-integration@docker.com | J269: 2024-09-30T14:24:54.000Z | K269: individual | N269: =VLOOKUP(I269,'Active Employees'!$B$2:$B$498,1,false) -> #N/A | O269: Service Account
B270: All | C270: FALSE | D270: ReadOnlyAdmin | E270: Standard Role | F270: FALSE | G270: ProphetAI Integration | H270: svc-prophet-integration@docker.com | I270: svc-prophet-integration@docker.com | J270: 2025-06-05T13:32:18.000Z | K270: individual | N270: =VLOOKUP(I270,'Active Employees'!$B$2:$B$498,1,false) -> #N/A | O270: Service Account
A271: User & Group Resource Set | B271: All users, All groups | C271: FALSE | D271: User & Group Role | E271: okta.users.manage, okta.groups.manage | F271: FALSE | G271: Security Ownership | H271: security-ownership@docker.com | I271: security-ownership@docker.com | J271: 2024-02-21T15:00:53.000Z | K271: individual | N271: =VLOOKUP(I271,'Active Employees'!$B$2:$B$498,1,false) -> #N/A | O271: Service Account
B272: All | C272: FALSE | D272: SuperOrgAdmin | E272: Standard Role | F272: FALSE | G272: Skalable Tech | H272: skalable.tech@docker.com | I272: skalable.tech@docker.com | J272: 2024-10-03T20:50:18.000Z | K272: individual | N272: =VLOOKUP(I272,'Active Employees'!$B$2:$B$498,1,false) -> #N/A | O272: Service Account
B273: All | C273: FALSE | D273: ReadOnlyAdmin | E273: Standard Role | F273: FALSE | G273: svc-crowdstrike-integration account | H273: svc-crowdstrike-integration@docker.com | I273: svc-crowdstrike-integration@docker.com | J273: 2024-08-13T13:24:25.000Z | K273: individual | N273: =VLOOKUP(I273,'Active Employees'!$B$2:$B$498,1,false) -> #N/A | O273: Service Account
B274: All | C274: FALSE | D274: OrgAdmin | E274: Standard Role | F274: FALSE | G274: Tines Integration | H274: svc-tines-integration@docker.com | I274: svc-tines-integration@docker.com | J274: 2023-06-13T15:52:50.000Z | K274: individual | N274: =VLOOKUP(I274,'Active Employees'!$B$2:$B$498,1,false) -> #N/A | O274: Service Account
B275: All | C275: FALSE | D275: ReadOnlyAdmin | E275: Standard Role | F275: FALSE | G275: Tracebit Access | K275: client | N275: =VLOOKUP(I275,'Active Employees'!$B$2:$B$498,1,false) -> #N/A | O275: Service Account
B276: All | C276: FALSE | D276: SuperOrgAdmin | E276: Standard Role | F276: FALSE | G276: TripActions Integration | H276: tripactions-okta@docker.com | I276: tripactions-okta@docker.com | J276: 2022-04-07T15:30:29.000Z | K276: individual | N276: =VLOOKUP(I276,'Active Employees'!$B$2:$B$498,1,false) -> #N/A | O276: Service Account

Sheet Auth0 - Testcontainers
A1: Name | B1: Roles | C1: Email | D1: Active Employee
A2: Anna Chernyshova | B2: Elevated Support Access, Viewer - Users, Viewer - Config Settings | C2: anna.chernyshova@docker.com | D2: yes
A3: Kirill Merkushev | B3: Admin, Elevated Support Access | C3: kirill.merkushev@docker.com | D3: yes
A4: Leo Cross | B4: Elevated Support Access, Viewer - Users, Viewer - Config Settings | C4: leo.cross@docker.com | D4: yes
A5: R.J. Lorimer | B5: Admin, Elevated Support Access | C5: robert.lorimer@docker.com | D5: yes
A6: Ivan Californias | B6: Admin, Elevated Support Access | C6: ivan.californias@docker.com | D6: yes
A7: Josh Newman | B7: Admin, Elevated Support Access | C7: josh.newman@docker.com | D7: yes

Sheet Github - TestContainers
A1: login | B1: name | C1: tfa_enabled | D1: tfa_level | E1: tfa_required_by | F1: is_public | G1: role | H1: saml_name_id | I1: organization_roles_count | J1: Active Employee
A2: chadfryer | B2: Chad Fryer | C2: TRUE | D2: secure | F2: FALSE | G2: Member | I2: 0 | J2: yes
A3: cybercyst | B3: Forrest Loomis | C3: TRUE | D3: secure | F3: FALSE | G3: Member | I3: 0 | J3: yes
A4: eddumelendez | B4: Eddú Meléndez Gonzales | C4: TRUE | D4: secure | F4: TRUE | G4: Member | I4: 0 | J4: yes
A5: EmreUgurluDocker | B5: Emre Ugurlu | C5: TRUE | D5: insecure | F5: FALSE | G5: Member | I5: 0 | J5: yes
A6: fiam | B6: Alberto García Hierro | C6: TRUE | D6: secure | F6: FALSE | G6: Member | I6: 0 | J6: yes
A7: fjmcs | B7: Fiona McShane | C7: TRUE | D7: insecure | F7: FALSE | G7: Owner | I7: 0 | J7: yes
A8: GannaChernyshova | B8: Ganna Chernyshova | C8: TRUE | D8: secure | F8: FALSE | G8: Member | I8: 0 | J8: yes
A9: ilopezluna | B9: Ignasi | C9: TRUE | D9: insecure | F9: FALSE | G9: Member | I9: 0 | J9: yes
A10: ivan-curkovic | B10: Ivan Curkovic | C10: TRUE | D10: insecure | F10: FALSE | G10: Member | I10: 0 | J10: yes
A11: jeffreystrauss | B11: Jeff Strauss | C11: TRUE | D11: insecure | F11: FALSE | G11: Owner | I11: 0 | J11: yes
A12: kiview | B12: Kevin Wittek | C12: TRUE | D12: insecure | F12: TRUE | G12: Member | I12: 0 | J12: yes
A13: Kyle-Trantham | B13: Kyle Trantham | C13: TRUE | D13: secure | F13: FALSE | G13: Member | I13: 0 | J13: yes
... A30: wolfshirts | B30: Ross Russell | C30: TRUE | D30: insecure | F30: FALSE | G30: Member | I30: 0 | J30: yes

Sheet TestContainers
A1: Name | B1: Email | C1: Role | D1: Joined | E1: Status | F1: VLOOKUP | G1: Active Employee | H1: Reviewed by: | I1: Downgraded Permissions or Removed (If disabled for 90+ days, please remove) | J1: Notes
A2: Ignasi | B2: ignasi.lopez.luna@gmail.com | C2: admin | D2: 45596 | E2: Active | F2: =VLOOKUP(B2,'Active Employees'!$B$2:$B$498,1,false) -> #N/A | G2: No | I2: Removed
A3: Kirill Merkushev | B3: kirill.merkushev@docker.com | C3: admin | D3: 45596 | E3: Active | F3: =VLOOKUP(B3,'Active Employees'!$B$2:$B$498,1,false) -> kirill.merkushev@docker.com | G3: Yes
A4: Kevin Wittek | B4: kevin.wittek@docker.com | C4: admin | D4: 45551 | E4: Active | F4: =VLOOKUP(B4,'Active Employees'!$B$2:$B$498,1,false) -> kevin.wittek@docker.com | G4: Yes
A5: R.J. Lorimer | B5: Robert.Lorimer@docker.com | C5: admin | D5: 45336 | E5: Active | F5: =VLOOKUP(B5,'Active Employees'!$B$2:$B$498,1,false) -> Robert.Lorimer@docker.com | G5: Yes
A6: ignacio.lopezluna@docker.com | B6: ignacio.lopezluna@docker.com | C6: admin | D6: 45365 | E6: Active | F6: =VLOOKUP(B6,'Active Employees'!$B$2:$B$498,1,false) -> ignacio.lopezluna@docker.com | G6: Yes
A7: Leo Cross | B7: leo.cross@docker.com | C7: admin | D7: 45335 | E7: Active | F7: =VLOOKUP(B7,'Active Employees'!$B$2:$B$498,1,false) -> leo.cross@docker.com | G7: Yes
A8: Manuel de la Peña | B8: manuel.delapena@docker.com | C8: admin | D8: 45330 | E8: Active | F8: =VLOOKUP(B8,'Active Employees'!$B$2:$B$498,1,false) -> manuel.delapena@docker.com | G8: Yes
A9: Eddú Meléndez Gonzales | B9: eddu.melendez@docker.com | C9: admin | D9: 45329 | E9: Active | F9: =VLOOKUP(B9,'Active Employees'!$B$2:$B$498,1,false) -> eddu.melendez@docker.com | G9: Yes
A10: Chun Tat Leow | B10: chuntat.leow@docker.com | C10: member | D10: 45817 | E10: Active | F10: =VLOOKUP(B10,'Active Employees'!$B$2:$B$498,1,false) -> #N/A | G10: No | I10: Removed
A11: Sam Morris | B11: sam.morris@docker.com | C11: member | D11: 45719 | E11: Active | F11: =VLOOKUP(B11,'Active Employees'!$B$2:$B$498,1,false) -> #N/A | G11: No | I11: Removed
A12: Van Sullivan IV | B12: van.sullivan@docker.com | C12: member | D12: 45679 | E12: Active | F12: =VLOOKUP(B12,'Active Employees'!$B$2:$B$498,1,false) -> #N/A | G12: No | I12: Removed
A13: Bryan English | B13: bryan.english@docker.com | C13: member | D13: 45665 | E13: Active | F13: =VLOOKUP(B13,'Active Employees'!$B$2:$B$498,1,false) -> #N/A | G13: No | I13: Removed
A14: Jeff Kormanik | B14: jeffrey.kormanik@docker.com | C14: member | D14: 45643 | E14: Active | F14: =VLOOKUP(B14,'Active Employees'!$B$2:$B$498,1,false) -> #N/A | G14: No | I14: Removed
A15: Frédéric Dalleau | B15: Frederic.dalleau@docker.com | C15: member | D15: 45608 | E15: Active | F15: =VLOOKUP(B15,'Active Employees'!$B$2:$B$498,1,false) -> #N/A | G15: No | I15: Removed
A16: Benjamin Abarzua | B16: Ben_Abarzua@docker.com | C16: member | D16: 45607 | E16: Active | F16: =VLOOKUP(B16,'Active Employees'!$B$2:$B$498,1,false) -> #N/A | G16: No | I16: Removed
A17: Surendren Sivaraj | B17: surendren_sivaraj@docker.com | C17: member | D17: 45607 | E17: Active | F17: =VLOOKUP(B17,'Active Employees'!$B$2:$B$498,1,false) -> #N/A | G17: No | I17: Removed
A18: Giorgi Modebadze | B18: giorgi.modebadze@docker.com | C18: member | D18: 45603 | E18: Active | F18: =VLOOKUP(B18,'Active Employees'!$B$2:$B$498,1,false) -> #N/A | G18: No | I18: Removed
A19: Cormac McMahon | B19: cormac.mcmahon@docker.com | C19: member | D19: 45560 | E19: Active | F19: =VLOOKUP(B19,'Active Employees'!$B$2:$B$498,1,false) -> #N/A | G19: No | I19: Removed
A20: Paul Serilas | B20: paul.serilas@docker.com | C20: member | D20: 45559 | E20: Active | F20: =VLOOKUP(B20,'Active Employees'!$B$2:$B$498,1,false) -> #N/A | G20: No | I20: Removed
A21: Vlad Budica | B21: vlad.budica@docker.com | C21: member | D21: 45559 | E21: Active | F21: =VLOOKUP(B21,'Active Employees'!$B$2:$B$498,1,false) -> #N/A | G21: No | I21: Removed
... A25: Djordje Lukic | B25: lukic.djordje@gmail.com | C25: member | D25: 45330 | E25: Active | F25: =VLOOKUP(B25,'Active Employees'!$B$2:$B$498,1,false) -> #N/A | G25: No | I25: Removed
A26: Cezar Cezar-George | B26: martin.cezar-george@docker.com | C26: member | D26: 45923 | E26: Active | F26: =VLOOKUP(B26,'Active Employees'!$B$2:$B$498,1,false) -> martin.cezar-george@docker.com | G26: Yes
A27: Ashime Amandong | B27: ashime.ashime@docker.com | C27: member | D27: 45916 | E27: Active | F27: =VLOOKUP(B27,'Active Employees'!$B$2:$B$498,1,false) -> ashime.ashime@docker.com | G27: Yes
A28: Colin Hemmings | B28: colin.hemmings@docker.com | C28: member | D28: 45916 | E28: Active | F28: =VLOOKUP(B28,'Active Employees'!$B$2:$B$498,1,false) -> colin.hemmings@docker.com | G28: Yes
A29: Oleg Burov | B29: oleg.burov@docker.com | C29: member | D29: 45911 | E29: Active | F29: =VLOOKUP(B29,'Active Employees'!$B$2:$B$498,1,false) -> oleg.burov@docker.com | G29: Yes
A30: Kelsey Quirke | B30: kelsey.quirke@docker.com | C30: member | D30: 45896 | E30: Active | F30: =VLOOKUP(B30,'Active Employees'!$B$2:$B$498,1,false) -> kelsey.quirke@docker.com | G30: Yes
A31: Brandon Roth | B31: brandon.roth@docker.com | C31: member | D31: 45896 | E31: Active | F31: =VLOOKUP(B31,'Active Employees'!$B$2:$B$498,1,false) -> brandon.roth@docker.com | G31: Yes
A32: Juanjo Fernandez | B32: juan.fernandez@docker.com | C32: member | D32: 45894 | E32: Active | F32: =VLOOKUP(B32,'Active Employees'!$B$2:$B$498,1,false) -> juan.fernandez@docker.com | G32: Yes
A33: Maja Chapus | B33: maja.chapus@docker.com | C33: member | D33: 45894 | E33: Active | F33: =VLOOKUP(B33,'Active Employees'!$B$2:$B$498,1,false) -> maja.chapus@docker.com | G33: Yes
A34: Bjorn Neergaard | B34: bjorn.neergaard@docker.com | C34: member | D34: 45875 | E34: Active | F34: =VLOOKUP(B34,'Active Employees'!$B$2:$B$498,1,false) -> bjorn.neergaard@docker.com | G34: Yes
A35: Trevor Smith | B35: trevor.smith@docker.com | C35: member | D35: 45862 | E35: Active | F35: =VLOOKUP(B35,'Active Employees'!$B$2:$B$498,1,false) -> trevor.smith@docker.com | G35: Yes
A36: Stuart Minchington | B36: stuart.minchington@docker.com | C36: member | D36: 45860 | E36: Active | F36: =VLOOKUP(B36,'Active Employees'!$B$2:$B$498,1,false) -> stuart.minchington@docker.com | G36: Yes
A37: Stephane Montri | B37: stephane.montri@docker.com | C37: member | D37: 45854 | E37: Active | F37: =VLOOKUP(B37,'Active Employees'!$B$2:$B$498,1,false) -> stephane.montri@docker.com | G37: Yes
... A143: Christopher Petito | B143: christopher.petito@docker.com | C143: member | D143: 45330 | E143: Active | F143: =VLOOKUP(B143,'Active Employees'!$B$2:$B$498,1,false) -> christopher.petito@docker.com | G143: Yes
A144: David Dooling | B144: david.dooling@docker.com | C144: member | D144: 45330 | E144: Active | F144: =VLOOKUP(B144,'Active Employees'!$B$2:$B$498,1,false) -> david.dooling@docker.com | G144: Yes | I144: Removed | J144: David left a couple weeks ago

Sheet Docker Hub
